Workbook

Sheet Use Case Tracker
A1: UC ID | B1: UC Name | C1: Main Flow | D1: Module | E1: Primary Actor | F1: Description / Goal | G1: Priority | H1: Status | I1: Owner | J1: Related Rule ID | K1: Notes | L1: Final Scope Decision
A2: UC01 | B2: Manage Subscription Plans and Feature Access | C2: Supporting Admin/Docker | D2: Subscription | E2: Admin | F2: Admin creates/updates/deactivates Free, Plus and Premium plans. Paid plans are billed annually only. Each plan defines yearly price and feature access such as finance reports, AI insights, SOS safety features, wearable support, storage and export capability. | G2: Must-have | H2: Not Started | J2: BR-SUB-01, BR-SUB-02, BR-SUB-03, BR-SUB-04, BR-SUB-08 | K2: Annual-only billing for paid plans. Monthly billing is out of scope for MVP. | L2: Keep
A3: UC02 | B3: Manage Family Workspaces and Subscription Status | C3: Supporting Admin/Docker | D3: Admin | E3: Admin | F3: Admin views workspaces, main Family Manager, subscription and activation status. | G3: Must-have | H3: Not Started | J3: BR-SUB-01, BR-WS-02 | L3: Keep
A4: UC03 | B4: Manage User Account Access | C4: Supporting Admin/Docker | D4: Admin | E4: Admin | F4: Admin locks/unlocks/restricts/restores user access when needed. | G4: Must-have | H4: Not Started | J4: BR-ADM-01, BR-AUTH-02 | L4: Keep
A5: UC04 | B5: Monitor Workspace Activation Status | C5: Supporting Admin/Docker | D5: Admin | E5: Admin | F5: Admin checks active/pending/suspended/failed/expired workspace states. | G5: Must-have | H5: Not Started | J5: BR-WS-02, BR-DEP-01 | L5: Keep
A6: UC05 | B6: View Basic Service Status | C6: Supporting Admin/Docker | D6: Admin | E6: Admin | F6: Admin views basic demo service status such as Backend, Admin Web, API and Database. | G6: Should-have | H6: Not Started | J6: BR-DEP-01, BR-FUT-01 | L6: Keep
A7: UC06 | B7: View Workspace Provisioning Logs | C7: Supporting Admin/Docker | D7: Admin | E7: Admin | F7: Admin views basic provisioning logs for workspace activation/demo startup failures. | G7: Should-have | H7: Not Started | J7: BR-DEP-01 | L7: Keep
A8: UC07 | B8: Retry Workspace Provisioning | C8: Supporting Admin/Docker | D8: Admin | E8: Admin | F8: Admin retries workspace activation/provisioning when a demo setup fails. | G8: Should-have | H8: Not Started | J8: BR-DEP-01 | L8: Keep
A9: UC08 | B9: View Basic Subscription Summary | C9: Supporting Admin/Docker | D9: Admin | E9: Admin | F9: Admin views a basic subscription summary only; advanced charts/export are Future. | G9: Could-have | H9: Not Started | J9: BR-SUB-01, BR-FUT-01 | L9: Could-have / Do after core
A10: UC09 | B10: Complete Family Onboarding Form - Account Info | C10: Flow 1 | D10: Auth | E10: Onboarding User / Family Representative | F10: Enter account registration information as part of the Family Onboarding Form. (Create Account Info -> Create Family Workspace info) | G10: Must-have | H10: Not Started | J10: BR-AUTH-01, BR-AUTH-03 | K10: Account info is collected before workspace setup. If email/phone already exists, system should redirect user to login/forgot password or resend verification if unverified. | L10: Keep
A11: UC10 | B11: Verify Account | C11: Flow 1 | D11: Auth | E11: Onboarding User / Family Representative | F11: Verify account after onboarding submission if verification is required before full workspace activation. | G11: Must-have | H11: Not Started | J11: BR-AUTH-01 | K11: Verification can be email/phone/code or simulated for demo. | L11: Keep
A12: UC11 | B12: Login / Logout | C12: Flow 1 | D12: Auth | E12: All Users | F12: Login or logout after account/workspace onboarding is completed. | G12: Must-have | H12: Not Started | J12: BR-AUTH-02 | K12: Login may be automatic after successful onboarding depending on implementation. | L12: Keep
A13: UC12 | B13: Create Family Workspace with Default Plan | C13: Flow 1 | D13: Family | E13: Onboarding User / Family Representative | F13: Submit family information in the onboarding form; system creates the Family Workspace, applies the default Free/Basic subscription status, and assigns the creator as the only main Family Manager. | G13: Must-have | H13: Not Started | J13: BR-WS-01, BR-WS-02, BR-SUB-01, BR-ROLE-01 | K13: This UC is triggered by the same Family Onboarding Form, not a fully separate manual flow. | L13: Keep
A14: UC13 | B14: Join Family via Invitation Link | C14: Flow 1 | D14: Family | E14: Invited User | F14: Join an existing Family Workspace through a valid invitation link after login/register. | G14: Must-have | H14: Not Started | J14: BR-INV-01 | K14: Used for invited members, not for the first Family Manager. | L14: Keep
A15: UC14 | B15: Manage Family Profile | C15: Flow 2 | D15: Family | E15: Family Manager | F15: Manage Family Profile | G15: Must-have | H15: Not Started | J15: BR-ROLE-01 | L15: Keep
A16: UC15 | B16: Invite Family Member | C16: Flow 2 | D16: Family | E16: Family Manager | F16: Invite Family Member | G16: Must-have | H16: Not Started | J16: BR-INV-01, BR-ROLE-01 | L16: Keep
A17: UC16 | B17: Manage Family Invitations | C17: Flow 2 | D17: Family | E17: Family Manager | F17: Manage Family Invitations | G17: Should-have | H17: Not Started | J17: BR-INV-01 | L17: Keep
A18: UC17 | B18: Manage Member Role and Relationship | C18: Flow 2 | D18: Family | E18: Family Manager | F18: Manage Member Role and Relationship | G18: Must-have | H18: Not Started | J18: BR-ROLE-03, BR-ROLE-04 | L18: Keep
A19: UC18 | B19: Grant or Revoke Deputy Permission | C19: Flow 2 | D19: Family | E19: Family Manager | F19: Grant or Revoke Deputy Permission | G19: Must-have | H19: Not Started | J19: BR-ROLE-02, BR-ROLE-01 | L19: Keep
A20: UC19 | B20: Remove or Deactivate Family Member | C20: Flow 2 | D20: Family | E20: Family Manager | F20: Remove or Deactivate Family Member | G20: Must-have | H20: Not Started | J20: BR-ROLE-01 | L20: Keep
A21: UC20 | B21: View Family Member List and Details | C21: Flow 2 | D21: Family | E21: Family Manager | F21: View Family Member List and Details | G21: Must-have | H21: Not Started | J21: BR-ROLE-03, BR-ROLE-04 | L21: Keep
A22: UC21 | B22: View Member Financial Profile Summary | C22: Flow 3 | D22: Finance | E22: Family Manager | F22: View member financial profile summary such as income status and aggregated planning data based on permission; Family Manager does not directly edit each member's private income/expense by default. | G22: Must-have | H22: Not Started | J22: BR-FIN-05, BR-FIN-06 | K22: Manager views summary for planning, not direct personal data control. | L22: Keep
A23: UC22 | B23: Set Personal Income and Expense | C23: Flow 3 | D23: Finance | E23: Family Member | F23: Family Member sets or updates personal income status, expected income, actual income, expected personal expense and actual personal expense. | G23: Must-have | H23: Not Started | J23: BR-FIN-05, BR-FIN-06, BR-AUTH-02 | K23: Each member owns their personal finance declaration. | L23: Keep
A24: UC23 | B24: Manage Shared Expense Categories | C24: Flow 3 | D24: Finance | E24: Family Manager / Family Member with delegated Deputy permission | F24: Manage shared family expense categories such as rent, electricity, water, food and school fees. | G24: Should-have | H24: Not Started | J24: BR-FIN-05 | K24: Shared categories are family-level, not member-private. | L24: Keep
A25: UC24 | B25: Set Expected Shared Family Income / Fund | C25: Flow 3 | D25: Finance | E25: Family Manager | F25: Set expected shared family income or family fund planning values, excluding private member income that members declare themselves. | G25: Must-have | H25: Not Started | J25: BR-FIN-05, BR-FIN-06 | K25: Use for common fund, shared contribution, or family-level income planning. | L25: Keep
A26: UC25 | B26: Set Expected Shared Family Expenses | C26: Flow 3 | D26: Finance | E26: Family Manager | F26: Set expected shared family expenses such as rent, utilities, food, school fees or other common household expenses. | G26: Must-have | H26: Not Started | J26: BR-FIN-05 | K26: Manager controls family-level shared expenses. | L26: Keep
A27: UC26 | B27: View Planned Family Budget | C27: Flow 3 | D27: Finance | E27: Family Manager | F27: View planned family budget calculated from member-declared personal income/expense and manager-defined shared family income/expense. | G27: Must-have | H27: Not Started | J27: BR-FIN-05, BR-FIN-06 | K27: Respect privacy/permission when showing details. | L27: Keep
A28: UC27 | B28: Record Actual Personal Income and Expense | C28: Flow 3 | D28: Finance | E28: Family Member | F28: Family Member records actual personal income and personal expense for their own financial tracking if allowed. | G28: Must-have | H28: Not Started | J28: BR-FIN-05, BR-FIN-06 | K28: Core finance scope after Review 1: budget planning, actual spending tracking, planned-vs-actual comparison and budget alerts. | L28: Keep
A29: UC28 | B29: Record Actual Shared Family Expense | C29: Flow 3 | D29: Finance | E29: Family Manager / Family Member with delegated Deputy permission | F29: Record actual shared family expense against the family fund ledger for tracking/planned-vs-actual reporting. The system does not hold or pay real money. | G29: Must-have | H29: Not Started | J29: BR-FIN-01, BR-FIN-04, BR-FIN-07 | K29: Shared actual expense is recorded in the family fund ledger only; no real money is held by the system. | L29: Keep
A30: UC29 | B30: View Actual Finance and Family Fund Report | C30: Flow 3 | D30: Finance | E30: Family Manager / Family Member with delegated Deputy permission | F30: View actual shared finance, family fund balance, and planned-vs-actual comparison; personal details are shown only according to privacy/permission rules. | G30: Must-have | H30: Not Started | J30: BR-FIN-01, BR-FIN-05, BR-FIN-06, BR-FIN-07 | K30: Report focuses on planned-vs-actual, fund ledger balance and privacy-aware finance summaries. | L30: Keep
A31: UC30 | B31: View Budget Alerts | C31: Flow 3 | D31: Finance | E31: Family Manager / Family Member with delegated Deputy permission | F31: View alerts when actual shared expenses exceed plan or family fund has shortage risk. | G31: Must-have | H31: Not Started | J31: BR-FIN-05, BR-FIN-06 | K31: Budget alerts are part of the core finance value after Review 1. | L31: Keep
A32: UC31 | B32: Manage Family Fund Ledger | C32: Flow 3 | D32: Finance / Family Fund | E32: Family Manager / Family Member with delegated Deputy permission | F32: Manage internal family fund ledger records for shared family planning, allowance and reward tracking. This is not a real e-wallet. | G32: Must-have | H32: Not Started | J32: BR-FIN-01, BR-FIN-04, BR-FIN-07, BR-FIN-08 | K32: This replaces the old top-up wallet concept. It is a ledger record, not a payment transaction. | L32: Keep, standardized as internal ledger scope after Review 1
A33: UC32 | B33: Record Family Fund Contribution | C33: Flow 3 | D33: Finance / Family Fund | E33: Family Manager / Family Member with delegated Deputy permission | F33: Record a contribution entry to the family fund ledger for planning and tracking purposes only. | G33: Must-have | H33: Not Started | J33: BR-FIN-01, BR-FIN-04, BR-FIN-07, BR-FIN-08 | K33: This replaces Record Family Fund Contribution. It is a ledger record, not a payment transaction. | L33: Keep, standardized as internal ledger scope after Review 1
... A37: UC36 | B37: View Family Fund and Allowance History | C37: Flow 3 | D37: Finance / Family Fund | E37: Family Manager / Family Member | F37: View family fund ledger, internal allowance, reward and spending support request history according to permission. | G37: Must-have | H37: Not Started | J37: BR-FIN-04, BR-FIN-06, BR-FIN-07 | K37: Transaction history means internal ledger history, not bank/payment transaction history. | L37: Keep, renamed from Family Fund Ledger history
A38: UC37 | B38: Manage Household Task Categories | C38: Flow 4 | D38: Task | E38: Family Manager / Family Member with delegated Deputy permission | F38: Manage Household Task Categories | G38: Should-have | H38: Not Started | J38: BR-TASK-01 | L38: Keep
A39: UC38 | B39: Create Ad-hoc Task | C39: Flow 4 | D39: Task | E39: Family Manager / Family Member with delegated Deputy permission | F39: Create Ad-hoc Task | G39: Must-have | H39: Not Started | J39: BR-TASK-01 | L39: Keep
A40: UC39 | B40: Create Recurring Mandatory Task | C40: Flow 4 | D40: Task | E40: Family Manager / Family Member with delegated Deputy permission | F40: Create Recurring Mandatory Task | G40: Must-have | H40: Not Started | J40: BR-TASK-01, BR-TASK-02 | L40: Keep
A41: UC40 | B41: Assign or Reassign Household Task | C41: Flow 4 | D41: Task | E41: Family Manager / Family Member with delegated Deputy permission | F41: Assign or Reassign Household Task | G41: Must-have | H41: Not Started | J41: BR-TASK-02 | L41: Keep
A42: UC41 | B42: Report Task Unavailability | C42: Flow 4 | D42: Task | E42: Family Member | F42: Report Task Unavailability | G42: Must-have | H42: Not Started | J42: BR-TASK-02 | L42: Keep
A43: UC42 | B43: Handle Recurring Task Takeover | C43: Flow 4 | D43: Task | E43: System / Family Manager / Family Member with delegated Deputy permission | F43: Handle Recurring Task Takeover | G43: Must-have | H43: Not Started | J43: BR-TASK-02 | L43: Keep
A44: UC43 | B44: Submit Task Completion with Proof | C44: Flow 4 | D44: Task | E44: Family Member | F44: Family Member submits task completion with proof such as note/image/video if required. | G44: Must-have | H44: Not Started | J44: BR-TASK-03 | K44: Task completion must be reviewed before any reward obligation is created. | L44: Keep
A45: UC44 | B45: Review Task Completion | C45: Flow 4 | D45: Task | E45: Family Manager / Family Member with delegated Deputy permission | F45: Review submitted task proof and approve or reject task completion. | G45: Must-have | H45: Not Started | J45: BR-TASK-03, BR-TASK-04 | K45: Approved task completion creates reward obligation if the task has reward, but does not mean real money has been paid. | L45: Keep
A46: UC45 | B46: Create Reward Settlement Record | C46: Flow 4 | D46: Reward / Settlement | E46: System | F46: After task completion is approved, the system creates a reward settlement record with Pending Settlement status if the task has reward. | G46: Must-have | H46: Not Started | J46: BR-TASK-04, BR-REW-01, BR-REW-02 | K46: Task approved does not equal reward received. Reward starts as Pending Settlement. | L46: Keep
A47: UC46 | B47: Mark Reward as Settled Externally | C47: Flow 4 | D47: Reward / Settlement | E47: Family Manager / Family Member with delegated Deputy permission | F47: Family Manager or delegated Deputy records that the reward was settled outside the system via cash, bank transfer, third-party wallet or other method. | G47: Must-have | H47: Not Started | J47: BR-REW-02, BR-REW-03, BR-FIN-08 | K47: This only records external/offline settlement status; the system does not transfer real money. | L47: Keep
A48: UC47 | B48: Confirm Reward Received | C48: Flow 4 | D48: Reward / Settlement | E48: Family Member | F48: Assigned member confirms that the externally settled reward has actually been received. | G48: Must-have | H48: Not Started | J48: BR-REW-04 | K48: Reward becomes fully settled only after the assigned member confirms receipt. | L48: Keep
A49: UC48 | B49: Report Reward Not Received / Dispute | C49: Flow 4 | D49: Reward / Settlement | E49: Family Member | F49: Assigned member reports that the reward marked as settled has not been received or needs review. | G49: Should-have | H49: Not Started | J49: BR-REW-05 | K49: Dispute status helps handle mismatch between manager-settled record and member receipt confirmation. | L49: Keep / Should-have
A50: UC49 | B50: View Assigned Tasks and Reward Settlement History | C50: Flow 4 | D50: Task / Reward | E50: Family Member | F50: View assigned tasks, completion status, reward settlement status and reward receipt history. | G50: Must-have | H50: Not Started | J50: BR-TASK-04, BR-REW-01, BR-REW-04 | K50: Reward status should show Pending Settlement, Waiting Confirmation, Settled or Disputed. | L50: Keep
A51: UC50 | B51: Trigger SOS Alert from Mobile App | C51: Flow 5 | D51: SOS | E51: Family Member | F51: Family Member triggers SOS from the mobile app and sends high-priority alert with location context when available. | G51: Must-have | H51: Not Started | J51: BR-SOS-01, BR-SOS-02, BR-SOS-05 | K51: Mobile SOS remains core; wearable SOS is added as a separate UC. | L51: Keep
A52: UC51 | B52: View and Respond to SOS Alert | C52: Flow 5 | D52: SOS | E52: All Family Members | F52: View SOS details, source, location context and response actions. | G52: Must-have | H52: Not Started | J52: BR-SOS-02 | K52: Family members can see who triggered SOS and respond quickly. | L52: Keep
A53: UC52 | B53: Confirm Safety | C53: Flow 5 | D53: SOS | E53: Family Member | F53: Confirm safety after an SOS event is handled or false alarm is resolved. | G53: Must-have | H53: Not Started | J53: BR-SOS-03 | K53: Safety confirmation is required before final resolution when applicable. | L53: Keep
A54: UC53 | B54: Resolve or Cancel SOS Alert | C54: Flow 5 | D54: SOS | E54: Family Manager / Family Member with delegated Deputy permission | F54: Resolve or cancel SOS alert with safety confirmation or clear handling reason. | G54: Must-have | H54: Not Started | J54: BR-SOS-03 | K54: SOS closure must be traceable. | L54: Keep
A55: UC54 | B55: View Basic SOS Location or Route History | C55: Flow 5 | D55: SOS | E55: Family Manager / Family Member with delegated Deputy permission / Family Member | F55: View basic SOS location or route history when available and permitted. | G55: Should-have | H55: Not Started | J55: BR-SOS-04 | K55: Basic active SOS route/location history only; advanced continuous GPS is future. | L55: Keep
... A69: UC68 | B69: Receive AI-based Budget and Saving Suggestions | C69: Supporting AI Insight | D69: AI / Finance | E69: Family Manager | F69: AI provides budget and saving suggestions based on recorded budget, actual expense, task reward and allowed family finance data. | G69: Should-have | H69: Not Started | J69: BR-AI-01, BR-AI-02, BR-AI-04, BR-FIN-05, BR-FIN-06 | K69: AI only gives summaries and suggestions. It does not make automatic financial decisions or change data automatically. | L69: Keep / Supporting
A70: UC69 | B70: Request Password Reset | C70: Flow 1 | D70: Auth | E70: Guest / User | F70: Guest or User requests a password reset link to regain access to their account. | G70: Must-have | H70: Not Started | J70: BR-AUTH-02 | L70: Keep
A71: UC70 | B71: Create Family Calendar Event | C71: Supporting Calendar | D71: Calendar | E71: Family Manager / Deputy | F71: Family Manager or Deputy creates a new event in the shared family calendar. | G71: Must-have | H71: Not Started | J71: BR-CAL-01 | L71: Keep
A72: UC71 | B72: View Family Calendar Events | C72: Supporting Calendar | D72: Calendar | E72: All Family Members | F72: All Family Members view upcoming events and reminders in the shared family calendar. | G72: Must-have | H72: Not Started | J72: BR-CAL-01 | L72: Keep
A73: UC72 | B73: Upload Media to Shared Family Album | C73: Supporting Album | D73: Album | E73: All Family Members | F73: All Family Members upload photos and videos to the shared family album. | G73: Must-have | H73: Not Started | J73: BR-ALB-01 | K73: Basic album upload/view remains supporting, not core flow. | L73: Keep
A74: UC73 | B74: View Shared Family Album Media | C74: Supporting Album | D74: Album | E74: All Family Members | F74: All Family Members view and interact with photos and videos in the shared family album. | G74: Must-have | H74: Not Started | J74: BR-ALB-01 | K74: Basic shared album remains supporting feature. | L74: Keep
A75: UC74 | B75: Tag Family Members in Album Media | C75: Supporting Album | D75: Album | E75: All Family Members | F75: User manually tags family members in shared album photos/videos to make family album more meaningful. | G75: Could-have | H75: Not Started | J75: BR-ALB-01, BR-ALB-02 | K75: Manual tagging is safer for MVP than full AI face clustering. | L75: Do after core
A76: UC75 | B76: Suggest Face-based Album Grouping | C76: Supporting Album / AI | D76: Album / AI | E76: System / All Family Members | F76: System suggests grouping photos by detected similar faces, but user confirmation is required before tagging or organizing. | G76: Could-have | H76: Not Started | J76: BR-ALB-02, BR-AI-01 | K76: Face clustering is future enhancement or demo-only, not core MVP. | L76: Future / AI Enhancement
A77: UC76 | B77: View Current Subscription and Feature Access | C77: Supporting Subscription | D77: Subscription | E77: Family Manager | F77: Family Manager views current plan, annual billing status, yearly price, start date, expiration date, remaining days, active features and locked/unlocked capabilities. | G77: Must-have | H77: Not Started | J77: BR-SUB-01, BR-SUB-02, BR-SUB-03, BR-SUB-04, BR-SUB-07, BR-SUB-08, BR-SUB-10 | K77: Shows annual plan, expiry date, remaining days and feature access. | L77: Keep
A78: UC77 | B78: Upgrade Subscription Plan | C78: Supporting Subscription | D78: Subscription / Payment | E78: Family Manager | F78: Family Manager upgrades from Free to Plus/Premium or from Plus to Premium. Paid plans are annual-only. If upgrading from Plus to Premium during an active yearly cycle, the system calculates a prorated upgrade fee based on the annual price difference and remaining days. | G78: Should-have | H78: Not Started | J78: BR-SUB-03, BR-SUB-04, BR-SUB-06, BR-SUB-08, BR-SUB-09, BR-SUB-10, BR-FIN-08 | K78: Upgrade fee = (Premium yearly price - Plus yearly price) × remaining days / 365. Payment is only for subscription, not family fund/allowance/reward. | L78: Keep / Demo payment
A79: UC78 | B79: Handle Subscription Expiration / Limited Access | C79: Supporting Subscription | D79: Subscription | E79: System / Family Manager | F79: When the annual subscription expires, advanced features are locked but existing family data remains viewable according to permission. | G79: Should-have | H79: Not Started | J79: BR-SUB-05, BR-SUB-07, BR-SUB-08 | K79: Annual subscription expiry locks advanced features rather than deleting data. | L79: Keep
A80: UC79 | B80: Enable / Disable Location Sharing | C80: SF4 | D80: Location / Safety | E80: Family Member | F80: Family Member enables or disables normal location sharing for family tracking. This controls routine location tracking outside SOS events. | G80: Should-have | H80: Not Started | J80: BR-LOC-01, BR-LOC-03 | K80: Normal location tracking should be opt-in/permission-based. SOS location behavior remains controlled by SOS settings. | L80: Planned / Prototype
A81: UC80 | B81: Share / Record Member Location Point | C81: SF4 | D81: Location / Safety | E81: Family Member / Mobile App / Wearable Device | F81: Mobile app or wearable device sends the member's current GPS location. The system stores it as a normal MemberLocationPoint, separate from SOS route tracking. | G81: Should-have | H81: Not Started | J81: BR-LOC-01, BR-LOC-02, BR-LOC-04 | K81: Related Physical ERD entity: member_location_points. This is normal tracking, not sos_location_points. | L81: Planned / ERD Present
A82: UC81 | B82: View Family Member Location Tracking | C82: SF4 | D82: Location / Safety | E82: Family Manager / Deputy / Authorized Family Member | F82: Authorized family members view latest shared location or basic location history of members who have enabled location sharing. | G82: Should-have | H82: Not Started | J82: BR-LOC-01, BR-LOC-02, BR-LOC-03 | K82: Family map/member tracking feature. If sharing is disabled or permission is missing, location must be hidden. | L82: Planned / Prototype
A83: UC82 | B83: Select Family Finance Model | C83: Flow 3 | D83: Finance / Planning Model | E83: Family Manager / Family Member with delegated Deputy permission | F83: Select the family finance management model such as 5 Jars, 80/20, or Custom model for budgeting and allocation. | G83: Must-have | H83: Not Started | J83: BR-FIN-MODEL-01 | K83: Added from 02/06 mentor note: finance should follow a clear model instead of only recording transactions. | L83: Keep
A84: UC83 | B84: Configure Finance Jars / Funds | C84: Flow 3 | D84: Finance / Jar | E84: Family Manager / Family Member with delegated Deputy permission | F84: Configure finance jars/funds such as essential spending, non-essential spending, saving goal fund, education/development, and emergency/reserve. | G84: Must-have | H84: Not Started | J84: BR-FIN-MODEL-01, BR-FIN-JAR-01 | K84: Jars/funds can have allocation percentage, threshold, purpose, and owner/visibility rule. | L84: Keep
... A92: UC91 | B92: Suggest Transaction Category by AI / OCR | C92: Supporting AI Insight | D92: AI / OCR / Finance | E92: Family Manager / Family Member | F92: AI/OCR suggests transaction category, jar, or essential/non-essential classification from text or receipt image; user confirms final record. | G92: Could-have | H92: Not Started | J92: BR-AI-FIN-01 | K92: Keep OCR/LLM as supporting technology, not Must-have for MVP. | L92: Could-have / Future

Sheet Main Core Flow Mapping
A1: Flow ID | B1: Flow Name | C1: Flow Type | D1: Business Goal | E1: Related UC IDs | F1: Main Actor | G1: Main Module | H1: Priority | I1: Owner | J1: Demo Scenario / Notes
A2: F1 | B2: Account Registration & Family Workspace Setup | C2: Core | D2: Let a user register/login first, then guide them to either create a new Family Workspace or join an existing one by invitation link before entering the dashboard. | E2: UC09-UC13; UC01-UC04 | F2: Guest / User / Family Representative / Invited User | G2: Auth, Family, Subscription | H2: Must-have | I2: Nhật | J2: Register/Login -> verify if required -> check workspace membership -> create new workspace or join by invitation -> assign role -> apply default plan for new workspace -> enter dashboard.
A3: F2 | B3: Member, Relationship & Delegated Permission Management | C3: Core | D3: Manage invitations, workspace members, family relationship, member status and delegated Deputy permission within one Family Workspace. | E3: UC13-UC20 | F3: Family Manager / Invited User | G3: Family, Member, Permission | H3: Must-have | I3: Nhật | J3: Invite member -> user joins workspace -> manager updates relationship/role -> grant or revoke delegated permission -> view or deactivate member.
A4: F3 | B4: Family Finance Planning, Fund Ledger and Goal-based Budgeting | C4: Core | D4: Manage family income/expense records, finance model, finance jars, essential/non-essential spending, family financial goals, planned-vs-actual reports, budget/goal risk alerts, and reward allocation without holding real user money. | E4: UC21-UC36; UC82-UC91 | F4: Family Manager / Family Member | G4: Finance, Family Fund Ledger, Goal-based Budgeting, AI Insight | H4: Must-have | J4: Select model -> configure jars -> record/categorize transactions -> create goal -> track progress -> view risk alerts -> allocate reward to jar/goal -> optional AI/OCR suggestion.
A5: F4 | B5: Household Task Coordination and Reward Settlement Management | C5: Core | D5: Create, assign, complete and approve household tasks; then create reward settlement record, mark external settlement, confirm member receipt or handle dispute. | E5: UC37-UC49 | F5: Family Manager / Family Member | G5: Task, Reward Settlement | H5: Must-have | J5: Create task -> assign -> submit proof -> approve task -> create pending reward settlement -> manager marks external settlement -> member confirms received or disputes -> view history.
A6: F5 | B6: SOS Alert, Wearable Safety and Safety Response Management | C6: Core | D6: Trigger SOS from mobile or wearable/safety device, notify family, confirm safety, resolve/cancel, track basic location during active SOS and store basic route/history. | E6: UC50-UC59 | F6: All Family Members | G6: SOS, Notification, Location, Wearable | H6: Must-have | J6: Mobile/device SOS -> notify family -> track active SOS location -> confirm safety -> resolve -> view history. Wearable can be simulated.
A7: SF4 | B7: Family Location Sharing and Member Tracking | C7: Supporting | D7: Allow members to opt in/out of normal location sharing, record routine location points from mobile/wearable, and let authorized family members view latest/basic location history without mixing it with SOS routes. | E7: UC79-UC81 | F7: Family Member / Authorized Family Member | G7: Location, Family, Wearable | H7: Should-have | J7: Enable sharing -> app/device sends location point -> authorized viewer opens family map -> system returns latest location/history. Normal tracking uses MemberLocationPoint; active SOS route uses SOSLocationPoint.
A8: SF1 | B8: Family Communication, Calendar and Album | C8: Supporting | D8: Support family coordination through notifications, basic chat, announcement, calendar, shared album and optional member tagging. | E8: UC60-UC64; UC70-UC75 | F8: All Family Members | G8: Communication, Calendar, Album | H8: Could-have | J8: Keep basic only; album tagging is optional; face clustering is not core MVP.
A9: SF2 | B9: AI-assisted Family Insight | C9: Supporting | D9: Provide AI assistant answers, finance summaries, task summaries and budget/saving suggestions based only on data the current user is allowed to view. | E9: UC65-UC68 | F9: All Family Members | G9: AI, Finance, Task, Reward, Reminder | H9: Should-have | J9: AI summarizes and suggests only; it does not make automatic decisions or update finance/task/SOS data.
A10: SF3 | B10: Subscription Plan and Feature Access Management | C10: Supporting | D10: View plan, compare Free/Plus/Premium, upgrade/renew subscription, handle expired plan and control feature access by plan. | E10: UC76-UC78 | F10: Family Manager / System | G10: Subscription, Payment, Feature Access | H10: Should-have | J10: Payment is only for subscription, not Family Fund Ledger, allowance or reward settlement.

Sheet Business Rule & Permission
A1: Rule ID | B1: Category | C1: Business Rule | D1: Applies To | E1: Can Delegate to Deputy? | F1: Related UC | G1: Module | H1: Priority | I1: Status | J1: Notes
A2: BR-ROLE-01 | B2: Role | C2: Each Family Workspace has only one main Family Manager. | D2: Family Workspace | E2: No | F2: UC12, UC17, UC18 | G2: Family | H2: Must-have | I2: Not Started | J2: Critical review point.
A3: BR-ROLE-02 | B3: Role | C3: Deputy is not a separate actor; it is delegated permission for a Family Member. | D3: Family Manager, Family Member | E3: N/A | F3: UC18 | G3: Permission | H3: Must-have | I3: Not Started | J3: Use wording: Family Member with delegated Deputy permission.
A4: BR-ROLE-03 | B4: Relationship | C4: Relationship describes family relation only and does not grant system permission. | D4: Family Member | E4: No | F4: UC17, UC20 | G4: Family | H4: Must-have | I4: Not Started | J4: Examples: father, mother, child, spouse, grandparent.
A5: BR-ROLE-04 | B5: Relationship | C5: Each member should have both role and relationship. | D5: Family Member | E5: No | F5: UC17, UC20 | G5: Family | H5: Must-have | I5: Not Started | J5: Useful for ERD and validation.
A6: BR-INV-01 | B6: Invitation | C6: Invited users join an existing family only through a valid invitation link. | D6: Invited User | E6: No | F6: UC13, UC15, UC16 | G6: Family | H6: Must-have | I6: Not Started | J6: Token must be valid and not expired/canceled.
A7: BR-AUTH-01 | B7: Authentication | C7: Users must register and verify their account before using protected family functions. | D7: Onboarding User / Family Representative | E7: No | F7: UC09, UC10 | G7: Auth | H7: Must-have | I7: Not Started | J7: Basic onboarding rule.
A8: BR-AUTH-02 | B8: Authorization | C8: Users can access resources only according to role, delegated permission and Family Workspace context. | D8: All Users | E8: No | F8: UC11 and protected UCs | G8: Auth / Permission | H8: Must-have | I8: Not Started | J8: Backend guard rule for all protected APIs.
A9: BR-AUTH-03 | B9: Authentication | C9: Email/phone number must be unique in the system. If an account already exists, the system must not create a duplicated account. | D9: Guest / User | E9: No | F9: UC09 | G9: Auth | H9: Must-have | I9: Not Started | J9: Existing verified account should be redirected to login or forgot password; existing unverified account can resend verification.
A10: BR-WS-01 | B10: Workspace | C10: The first user who creates a Family Workspace becomes the only main Family Manager. | D10: Onboarding User / Family Representative | E10: No | F10: UC12 | G10: Family | H10: Must-have | I10: Not Started | J10: Critical review point.
A11: BR-WS-02 | B11: Workspace | C11: A Family Workspace can be fully used only when subscription and activation status are valid. | D11: Family Workspace | E11: No | F11: UC04, UC12 | G11: Subscription / Workspace | H11: Must-have | I11: Not Started | J11: Supports onboarding and Admin workspace monitoring.
A12: BR-SUB-01 | B12: Subscription | C12: Subscription plans are limited to Free, Plus and Premium in current scope. Paid plans are annual-only. | D12: Admin, Family Manager | E12: No | F12: UC01, UC12, UC76-UC78 | G12: Subscription | H12: Must-have | I12: Not Started | J12: Plans are differentiated by feature access, not mainly by member count.
... A58: BR-AI-05 | B58: AI / Finance | C58: AI finance insight only summarizes and suggests; it cannot automatically change budgets, ledger records, rewards or SOS status. | D58: AI Assistant, System | E58: No | F58: UC65-UC68 | G58: AI / Finance | H58: Must-have | I58: Not Started | J58: Keeps AI as advisory feature.
A59: 54 | B59: BR-FIN-MODEL-01 | C59: Finance Model | D59: Family can select a finance model such as 5 Jars, 80/20, or Custom model for budgeting and allocation. | E59: Family Manager, delegated Deputy member | F59: Yes | G59: UC82, UC83 | H59: Finance / Planning Model | I59: Must-have | J59: Added from 02/06 mentor note about using a finance management model.
A60: 55 | B60: BR-FIN-JAR-01 | C60: Finance Jar / Fund | D60: Each finance jar/fund has name, purpose, allocation percentage or threshold, and can be used for budgeting or goal tracking. | E60: Family Manager, delegated Deputy member, System | F60: Yes | G60: UC83, UC87, UC90 | H60: Finance / Jar | I60: Must-have | J60: Example jars: essential, non-essential, saving goal, education, emergency.
A61: 56 | B61: BR-FIN-CAT-01 | C61: Finance Category | D61: Each income or expense record should be categorized into a finance category/jar for reporting, alerting and AI suggestion. | E61: Family Manager, Family Member, System | F61: No | G61: UC84, UC91 | H61: Finance / Category | I61: Must-have | J61: Manual classification is Must-have; AI/OCR suggestion is optional.
A62: 57 | B62: BR-FIN-CAT-02 | C62: Finance Category | D62: Each expense should be marked as Essential or Non-essential to support spending control, saving suggestions and goal-risk alerts. | E62: Family Manager, Family Member, System | F62: No | G62: UC85, UC89, UC91 | H62: Finance / Category | I62: Must-have | J62: Essential: food, utilities, tuition. Non-essential: entertainment, games, optional shopping.
A63: 58 | B63: BR-FIN-GOAL-01 | C63: Financial Goal | D63: Financial goal must have target amount, deadline, related fund, current progress and monthly contribution target. | E63: Family Manager, delegated Deputy member, System | F63: Yes | G63: UC86, UC87, UC88 | H63: Finance / Goal | I63: Must-have | J63: Example: buy a 30M VND motorbike by year-end.
A64: 59 | B64: BR-FIN-ALERT-01 | C64: Finance Alert | D64: System alerts when spending exceeds threshold, non-essential spending is too high, or financial goal progress is at risk. | E64: System, Family Manager, Family Member | F64: No | G64: UC30, UC88, UC89 | H64: Finance / Alert | I64: Must-have | J64: Extends Budget Alerts into Budget and Goal Risk Alerts.
A65: 60 | B65: BR-REW-JAR-01 | C65: Reward / Finance Jar | D65: Task reward should be allocated to a finance jar or goal fund after member confirms reward receipt. | E65: Family Member, System | F65: No | G65: UC47, UC90 | H65: Reward Settlement / Finance | I65: Must-have | J65: Added from 02/06 mentor note: reward must know which jar it belongs to.
A66: 61 | B66: BR-AI-FIN-01 | C66: AI / OCR / Finance | D66: AI/OCR only suggests category, jar, essential/non-essential type or saving advice; user must confirm the final finance record. | E66: AI Assistant, System, User | F66: No | G66: UC91, UC65-UC68 | H66: AI / OCR / Finance | I66: Could-have | J66: OCR/LLM should remain supporting technology, not core MVP dependency.
A67: BR-CAL-01 | B67: Calendar | C67: Family calendar events are shared within the same Family Workspace and can be managed by Family Manager or delegated Deputy. | D67: Family Manager, Deputy, All Family Members | E67: Yes | F67: UC70, UC71 | G67: Calendar | H67: Must-have | I67: Not Started | J67: All members can view; creation/editing is permission-based.
A68: BR-ALB-01 | B68: Album | C68: Shared family album media is visible only within the same Family Workspace according to permission. | D68: All Family Members | E68: No | F68: UC72, UC73, UC74 | G68: Album | H68: Must-have | I68: Not Started | J68: Basic album upload/view remains supporting.
A69: BR-ALB-02 | B69: Album / AI | C69: Face clustering is not required for MVP; it is a future enhancement or demo-only feature. | D69: System, All Family Members | E69: No | F69: UC74, UC75 | G69: Album / AI | H69: Could-have | I69: Not Started | J69: MVP focuses on shared album and optional manual tagging.
A70: BR-ADM-01 | B70: Admin | C70: Admin Dashboard is Web only. | D70: Admin | E70: No | F70: UC01-UC08 | G70: Admin | H70: Must-have | I70: Not Started | J70: No Admin mobile app.
A71: BR-DEP-01 | B71: Deployment | C71: Docker is used only for local/demo deployment with Docker Desktop / Docker Compose. | D71: System, Admin | E71: No | F71: UC05-UC07 | G71: Docker Demo | H71: Must-have | I71: Not Started | J71: No production-grade infrastructure in current scope.
A72: BR-FUT-01 | B72: Future | C72: Kubernetes, auto-scaling, CPU/RAM/disk monitoring and backup/restore automation are Future Enhancements. | D72: Admin | E72: No | F72: UC05-UC08 | G72: Future | H72: Must-have | I72: Not Started | J72: Do not implement now.
A75: BR-SUB-10 | B75: Subscription / Feature Activation | C75: After successful upgrade payment, Premium features are activated immediately while the original subscription expiration date remains unchanged. | D75: Family Manager, System | E75: No | F75: UC76, UC77 | G75: Subscription / Feature Access | H75: Must-have | I75: Not Started | J75: Next renewal uses the Premium annual price.

Sheet API Screen DB Mapping
A1: UC ID | B1: Screen Name | C1: Platform | D1: API Endpoint | E1: Method | F1: Request DTO | G1: Response DTO | H1: DB Tables / Entities | I1: FE Owner | J1: BE Owner | K1: Status | L1: Notes
A2: UC01 | B2: Manage Basic Subscription Plans | C2: Admin Web | D2: /api/admin | E2: GET/POST/PATCH | F2: TBD | G2: TBD | H2: SubscriptionPlan, FamilyWorkspace, ProvisioningLog, AccountStatus | K2: Not Started | L2: Add exact endpoint after API design.
A3: UC02 | B3: Manage Family Workspaces and Subscription Status | C3: Admin Web | D3: /api/admin | E3: GET/POST/PATCH | F3: TBD | G3: TBD | H3: SubscriptionPlan, FamilyWorkspace, ProvisioningLog, AccountStatus | K3: Not Started | L3: Add exact endpoint after API design.
A4: UC03 | B4: Manage User Account Access | C4: Admin Web | D4: /api/admin | E4: GET/POST/PATCH | F4: TBD | G4: TBD | H4: SubscriptionPlan, FamilyWorkspace, ProvisioningLog, AccountStatus | K4: Not Started | L4: Add exact endpoint after API design.
A5: UC04 | B5: Monitor Workspace Activation Status | C5: Admin Web | D5: /api/admin | E5: GET/POST/PATCH | F5: TBD | G5: TBD | H5: SubscriptionPlan, FamilyWorkspace, ProvisioningLog, AccountStatus | K5: Not Started | L5: Add exact endpoint after API design.
A6: UC05 | B6: View Basic Service Status | C6: Admin Web | D6: /api/admin | E6: GET/POST/PATCH | F6: TBD | G6: TBD | H6: SubscriptionPlan, FamilyWorkspace, ProvisioningLog, AccountStatus | K6: Not Started | L6: Add exact endpoint after API design.
A7: UC06 | B7: View Workspace Provisioning Logs | C7: Admin Web | D7: /api/admin | E7: GET/POST/PATCH | F7: TBD | G7: TBD | H7: SubscriptionPlan, FamilyWorkspace, ProvisioningLog, AccountStatus | K7: Not Started | L7: Add exact endpoint after API design.
A8: UC07 | B8: Retry Workspace Provisioning | C8: Admin Web | D8: /api/admin | E8: GET/POST/PATCH | F8: TBD | G8: TBD | H8: SubscriptionPlan, FamilyWorkspace, ProvisioningLog, AccountStatus | K8: Not Started | L8: Add exact endpoint after API design.
A9: UC08 | B9: View Basic Subscription Summary | C9: Admin Web | D9: /api/admin | E9: GET/POST/PATCH | F9: TBD | G9: TBD | H9: SubscriptionPlan, FamilyWorkspace, ProvisioningLog, AccountStatus | K9: Not Started | L9: Add exact endpoint after API design.
A10: UC09 | B10: Register Account | C10: Flutter Mobile | D10: /api/auth | E10: POST | F10: TBD | G10: TBD | H10: User, AuthSession | K10: Not Started | L10: Add exact endpoint after API design.
A11: UC10 | B11: Verify Account | C11: Flutter Mobile | D11: /api/auth | E11: POST | F11: TBD | G11: TBD | H11: User, AuthSession | K11: Not Started | L11: Add exact endpoint after API design.
A12: UC11 | B12: Login / Logout | C12: Flutter Mobile | D12: /api/auth | E12: POST | F12: TBD | G12: TBD | H12: User, AuthSession | K12: Not Started | L12: Add exact endpoint after API design.
A13: UC12 | B13: Create Family Workspace with Default Plan | C13: Flutter Mobile | D13: /api/families | E13: GET/POST/PATCH | F13: TBD | G13: TBD | H13: Family, FamilyMember, Invitation, RolePermission | K13: Not Started | L13: Add exact endpoint after API design.
... A65: UC65 | B65: Ask AI Assistant | C65: Flutter Mobile | D65: /api/ai-assistant/chat | E65: POST | F65: AskAIRequestDto | G65: AIAnswerResponseDto | H65: AIConversation, AIMessage, User, FamilyMember, FamilyWorkspace | K65: Not Started | L65: Basic AI Q&A based on authorized family data.
A66: UC66 | B66: View AI Finance Summary | C66: Flutter Mobile | D66: /api/ai-assistant/finance-summary | E66: GET/POST | F66: AIFinanceSummaryRequestDto | G66: AIFinanceSummaryResponseDto | H66: Budget, FamilyFundLedger, LedgerEntry, SpendingSupportRequest, MemberFinancialProfile | J66: Nghĩa | K66: Not Started | L66: Must check finance permission before generating summary.
A67: UC67 | B67: View AI Task Summary | C67: Flutter Mobile | D67: /api/ai-assistant/task-summary | E67: GET/POST | F67: AITaskSummaryRequestDto | G67: AITaskSummaryResponseDto | H67: Task, TaskAssignment, TaskCompletion, RewardSettlement, FamilyMember | K67: Not Started | L67: AI summarizes task/reward settlement status only.
A68: UC68 | B68: Receive AI-based Budget and Saving Suggestions | C68: Flutter Mobile | D68: /api/ai-assistant/saving-suggestions | E68: GET/POST | F68: AISavingSuggestionRequestDto | G68: AISavingSuggestionResponseDto | H68: Budget, ExpenseCategory, LedgerEntry, FamilyFundLedger | J68: Nghĩa | K68: Not Started | L68: Advisory only; AI does not change data automatically.
A69: UC69 | B69: Request Password Reset | C69: Flutter Mobile | D69: /api/auth/forgot-password | E69: POST | F69: ForgotPasswordDto | G69: ForgotPasswordResponseDto | H69: User, PasswordResetToken | K69: Not Started | L69: Password recovery flow.
A70: UC70 | B70: Create Family Calendar Event | C70: Flutter Mobile | D70: /api/calendar/events | E70: POST | F70: CreateEventDto | G70: EventResponseDto | H70: FamilyCalendarEvent | K70: Not Started | L70: Family Manager or Deputy creates shared event.
A71: UC71 | B71: View Family Calendar Events | C71: Flutter Mobile | D71: /api/calendar/events | E71: GET | G71: List<EventResponseDto> | H71: FamilyCalendarEvent | K71: Not Started | L71: All family members view shared calendar.
A72: UC72 | B72: Upload Media to Shared Family Album | C72: Flutter Mobile | D72: /api/album/media | E72: POST | F72: UploadMediaDto | G72: MediaResponseDto | H72: FamilyAlbumMedia | K72: Not Started | L72: Basic upload/view remains supporting.
A73: UC73 | B73: View Shared Family Album Media | C73: Flutter Mobile | D73: /api/album/media | E73: GET | G73: List<MediaResponseDto> | H73: FamilyAlbumMedia | K73: Not Started | L73: Basic shared album remains supporting.
A74: UC74 | B74: Tag Family Members in Album Media | C74: Flutter Mobile | D74: /api/album/media/{id}/tags | E74: POST/PATCH | F74: TBD | G74: TBD | H74: FamilyAlbumMedia, AlbumMediaTag, FamilyMember | K74: Not Started | L74: Manual tagging is safer for MVP.
A75: UC75 | B75: Suggest Face-based Album Grouping | C75: Flutter Mobile | D75: /api/album/face-grouping/suggestions | E75: GET/POST | F75: TBD | G75: TBD | H75: FamilyAlbumMedia, FaceGroupingSuggestion, AIMessage | K75: Not Started | L75: Future/demo-only enhancement.
A76: UC76 | B76: View Current Subscription and Feature Access | C76: Flutter Mobile | D76: /api/subscriptions/current | E76: GET | F76: TBD | G76: TBD | H76: SubscriptionPlan, SubscriptionPeriod, FamilyWorkspace, FeatureAccess | K76: Not Started | L76: Shows annual plan, yearly price, expiration date, remaining days and available/locked features.
A77: UC77 | B77: Upgrade Subscription Plan | C77: Flutter Mobile | D77: /api/subscriptions/upgrade-preview; /api/subscriptions/upgrade | E77: GET/POST | F77: UpgradePreviewRequestDto; UpgradeSubscriptionRequestDto | G77: UpgradePreviewResponseDto; SubscriptionPaymentResponseDto | H77: SubscriptionPlan, SubscriptionPeriod, SubscriptionPayment, UpgradeInvoice, FamilyWorkspace, FeatureAccess | K77: Not Started | L77: Preview prorated upgrade fee before payment. Plus-to-Premium upgrade uses annual price difference and remaining days. Payment is only for subscription.
A78: UC78 | B78: Handle Subscription Expiration / Limited Access | C78: Flutter Mobile | D78: /api/subscriptions/limited-access | E78: GET/PATCH | F78: TBD | G78: TBD | H78: SubscriptionPlan, SubscriptionPeriod, FamilyWorkspace, FeatureAccess | K78: Not Started | L78: Expired annual plan locks advanced features but keeps existing data viewable.
A79: UC79 | B79: Location Sharing Settings | C79: Flutter Mobile | D79: /api/location-sharing | E79: GET/PATCH | F79: UpdateLocationSharingDto | G79: LocationSharingStatusResponseDto | H79: FamilyMember, FamilyWorkspace | K79: Not Started | L79: May be stored as member setting/profile depending on final implementation.
A80: UC80 | B80: Share / Record Member Location Point | C80: Flutter Mobile / Wearable | D80: /api/locations/member-points | E80: POST | F80: RecordMemberLocationPointDto | G80: MemberLocationPointResponseDto | H80: MemberLocationPoint, FamilyMember, FamilyWorkspace, WearableDevice | K80: Not Started | L80: Normal tracking record. Do not use SOSLocationPoint unless an SOS alert is active.
A81: UC81 | B81: View Family Member Location Tracking | C81: Flutter Mobile | D81: /api/locations/member-points | E81: GET | F81: MemberLocationQueryDto | G81: List<MemberLocationPointResponseDto> | H81: MemberLocationPoint, FamilyMember, FamilyWorkspace | K81: Not Started | L81: Used for family map/latest location/basic history with permission checks.
A82: UC82 | B82: Select Family Finance Model | C82: Flutter Mobile | D82: /api/finance/models | E82: GET/POST | F82: CreateFinanceModelDto | G82: FinanceModelResponseDto | H82: FinanceModel, FinanceJar, FamilyWorkspace | K82: Not Started | L82: Select 5 Jars, 80/20, or Custom model for family finance planning.
A83: UC83 | B83: Configure Finance Jars / Funds | C83: Flutter Mobile | D83: /api/finance/jars | E83: GET/POST/PATCH | F83: UpsertFinanceJarDto | G83: FinanceJarResponseDto | H83: FinanceJar, FinanceModel, FamilyWorkspace | K83: Not Started | L83: Configure jar/fund purpose, allocation percentage, threshold, and visibility.
A84: UC84 | B84: Categorize Income and Expense | C84: Flutter Mobile | D84: /api/finance/ledger-entries/{id}/category | E84: PATCH | F84: CategorizeLedgerEntryDto | G84: LedgerEntryResponseDto | H84: LedgerEntry, FinanceCategory, FinanceJar | K84: Not Started | L84: Manual classification is core; AI/OCR suggestion is optional.
A85: UC85 | B85: Mark Expense as Essential or Non-essential | C85: Flutter Mobile | D85: /api/finance/ledger-entries/{id}/essential-type | E85: PATCH | F85: UpdateEssentialTypeDto | G85: LedgerEntryResponseDto | H85: LedgerEntry, FinanceCategory | K85: Not Started | L85: Supports saving suggestions, budget alerts, and goal-risk analysis.
... A91: UC91 | B91: Suggest Transaction Category by AI / OCR | C91: Flutter Mobile | D91: /api/ai-assistant/transaction-category-suggestion | E91: POST | F91: TransactionCategorySuggestionRequestDto | G91: TransactionCategorySuggestionResponseDto | H91: AIMessage, LedgerEntry, FinanceCategory, FinanceJar | K91: Not Started | L91: Could-have/Future support; user must confirm final record.

Sheet Main Flow Steps
A1: x | B1: Flow Name | C1: Step No. | D1: Step Type | E1: Actor / System | F1: Action / Event | G1: System Response / Validation | H1: Related UC | I1: Related Rule ID | J1: Final Status / Output | K1: Notes
A2: F1 | B2: Account Registration & Family Workspace Setup | C2: 1 | D2: Start | E2: Guest / User | F2: Open the application and choose Register or Login. | G2: The system displays authentication screens. | H2: UC09, UC11 | I2: BR-AUTH-01, BR-AUTH-02 | J2: User starts the authentication flow. | K2: Account setup is handled before workspace setup.
A3: F1 | B3: Account Registration & Family Workspace Setup | C3: 2 | D3: User Action | E3: Guest / User | F3: Enter registration or login information. | G3: The system validates required fields, account uniqueness, and login credentials. | H3: UC09, UC11 | I3: BR-AUTH-01, BR-AUTH-02, BR-AUTH-03 | J3: Account information is submitted for validation. | K3: If the account already exists, guide the user to login, forgot password, or resend verification.
A4: F1 | B4: Account Registration & Family Workspace Setup | C4: 3 | D4: System Action | E4: System | F4: Create or authenticate the user account and handle verification if required. | G4: The system creates/authenticates the account and sets the verified or pending-verification status. | H4: UC09, UC10, UC11 | I4: BR-AUTH-01 | J4: User account is ready or waiting for verification. | K4: Verification may be simulated in demo.
A5: F1 | B5: Account Registration & Family Workspace Setup | C5: 4 | D5: System Action | E5: System | F5: Check whether the user already belongs to a Family Workspace. | G5: The system searches the user's existing workspace membership. | H5: UC11, UC12, UC13 | I5: BR-AUTH-02, BR-WS-02 | J5: Workspace membership status is identified. | K5: If the user already belongs to a workspace, route directly to the dashboard.
A6: F1 | B6: Account Registration & Family Workspace Setup | C6: 5 | D6: System Action | E6: System | F6: If the user has no workspace, show Family Workspace setup options. | G6: The system displays two options: create a new Family Workspace or join an existing workspace by invitation link. | H6: UC12, UC13 | I6: BR-WS-01, BR-INV-01 | J6: Workspace setup options are displayed. | K6: Do not send the user to an empty dashboard before workspace setup.
A7: F1 | B7: Account Registration & Family Workspace Setup | C7: 6 | D7: User Action | E7: Authenticated User | F7: Choose Create New Family Workspace or Join by Invitation Link. | G7: The system validates submitted workspace information or invitation token. | H7: UC12, UC13 | I7: BR-WS-01, BR-INV-01 | J7: A create-workspace or join-workspace request is submitted. | K7: Creator and invited-member paths are shown as separate branches in the swimlane.
A8: F1 | B8: Account Registration & Family Workspace Setup | C8: 7 | D8: System Action | E8: System | F8: Create a new Family Workspace or add the invited user to an existing workspace. | G8: If creating a workspace, the system creates it and assigns the creator as the only primary Family Manager. If joining by invitation, the system adds the user as a Family Member. | H8: UC12, UC13 | I8: BR-WS-01, BR-ROLE-01, BR-INV-01 | J8: User is linked to a valid Family Workspace. | K8: Only the workspace creator becomes the primary Family Manager.
A9: F1 | B9: Account Registration & Family Workspace Setup | C9: 8 | D9: System Action | E9: System | F9: Apply the default Free/Basic subscription status to a newly created workspace. | G9: The system initializes the default subscription status; renewal or upgrade is handled later after activation. | H9: UC12, UC01, UC02 | I9: BR-SUB-01, BR-WS-02 | J9: Default subscription status is applied. | K9: Subscription management is not part of initial onboarding.
A10: F1 | B10: Account Registration & Family Workspace Setup | C10: 9 | D10: System Action | E10: System | F10: Activate or validate workspace access according to verification, invitation, and subscription status. | G10: The system updates access status and records setup logs if needed. | H10: UC12, UC13, UC04 | I10: BR-WS-02, BR-DEP-01 | J10: Workspace access is ready. | K10: Docker/container provisioning can remain local/demo for MVP.
A11: F1 | B11: Account Registration & Family Workspace Setup | C11: 10 | D11: End | E11: System | F11: Route the user to the correct Family Dashboard. | G11: The system routes the Family Manager to workspace home and invited members to the member dashboard. | H11: UC11, UC12, UC13 | I11: BR-AUTH-02, BR-WS-02 | J11: User has an account and belongs to a valid Family Workspace. | K11: Final state: authenticated user can access a workspace-specific dashboard.
A12: F2 | B12: Member, Relationship & Delegated Permission Management | C12: 1 | D12: Start | E12: Family Manager | F12: Open the member management screen. | G12: The system checks Family Manager permission. | H12: UC20 | I12: BR-AUTH-02, BR-ROLE-01 | J12: Member management screen is available if permission is valid. | K12: Only the primary Family Manager can manage member access directly.
A13: F2 | B13: Member, Relationship & Delegated Permission Management | C13: 2 | D13: User Action | E13: Family Manager | F13: Create an invitation link for a new member. | G13: The system generates an invitation code with family context. | H13: UC15 | I13: BR-INV-01 | J13: Invitation link is created. | K13: The invited user will not become another Family Manager by default.
... A106: SF3 | B106: Subscription Plan and Feature Access Management | C106: 7 | D106: End | E106: System | F106: Display updated plan, status, remaining days and available/locked features. | G106: The system keeps annual subscription status consistent with feature access across modules. | H106: UC76-UC78 | I106: BR-SUB-01, BR-SUB-05, BR-SUB-07, BR-SUB-10 | J106: Subscription management flow is completed. | K106: Final state: annual subscription is clear and separated from Family Fund Ledger.

Sheet VI - Dictionary
A1: English | B1: Vietnamese
A2: Must-have | B2: Bắt buộc
A3: Should-have | B3: Nên có
A4: Could-have | B4: Có thể có
A5: Not Started | B5: Chưa bắt đầu
A6: Keep | B6: Giữ trong scope
A7: Could-have / Do after core | B7: Có thể có / Làm sau core
A8: Core | B8: Luồng chính
A9: Supporting | B9: Luồng hỗ trợ
A10: Yes | B10: Có
A11: No | B11: Không
A12: N/A | B12: Không áp dụng
... A46: System | B46: Hệ thống

Sheet Subscription Plan Matrix
A1: Family Care - Subscription Plan Matrix (Annual Billing Only)
A3: Feature / Capability | B3: Free | C3: Plus Annual | D3: Premium Annual | E3: Related UC / Rule | F3: Notes
A4: Price | B4: 0đ | C4: 990.000đ/year | D4: 1.990.000đ/year | E4: BR-SUB-08 | F4: Example pricing; can be adjusted by Admin.
A5: Billing cycle | B5: No paid cycle | C5: Annual only | D5: Annual only | E5: BR-SUB-08 | F5: Monthly billing is out of scope for MVP.
A6: Family workspace | B6: Yes | C6: Yes | D6: Yes | E6: UC12, BR-SUB-02 | F6: Free plan starts by default after workspace creation.
A7: Member management | B7: Basic | C7: Full | D7: Full | E7: UC14-UC20 | F7: Member count is not the main selling point.
A8: Task management | B8: Basic | C8: Full | D8: Full | E8: UC37-UC49 | F8: Plus unlocks full recurring task/reward settlement management.
A9: Internal allowance / reward record | B9: Basic | C9: Full | D9: Full | E9: UC33, UC45-UC49, BR-FIN-07 | F9: Internal record only, no real cash-out.
A10: Basic finance tracking | B10: Yes | C10: Yes | D10: Yes | E10: UC21-UC29 | F10: Core finance should remain available at basic level.
A11: Budget planning | B11: Basic | C11: Full | D11: Full | E11: UC24-UC26 | F11: Plus is the main family management plan.
A12: Planned-vs-actual report | B12: No / Basic preview | C12: Yes | D12: Yes | E12: UC29, BR-SUB-03 | F12: Key value for Finance after Review 1.
A13: Budget alerts | B13: No | C13: Yes | D13: Yes | E13: UC30, BR-SUB-03 | F13: Raised to Must-have in core finance scope.
A14: Export finance report | B14: No | C14: Yes | D14: Yes / Advanced | E14: BR-SUB-03, BR-SUB-07 | F14: Can be implemented as PDF/Excel export later.
... A29: Main positioning | B29: Trial / Basic | C29: Family Management | D29: AI + Safety | E29: BR-SUB-02 to BR-SUB-04 | F29: Plans are differentiated by value and capability.

Sheet VI - Use Case Tracker
A1: Mã UC | B1: Tên Use Case | C1: Luồng chính | D1: Module | E1: Actor chính | F1: Mô tả / Mục tiêu | G1: Độ ưu tiên | H1: Trạng thái | I1: Người phụ trách | J1: Mã rule liên quan | K1: Ghi chú | L1: Quyết định scope cuối
A2: =IF('Use Case Tracker'!A2="","",'Use Case Tracker'!A2) -> UC01 | B2: =IFERROR(__xludf.DUMMYFUNCTION("IF('Use Case Tracker'!B2="""","""",IFERROR(GOOGLETRANSLATE('Use Case Tracker'!B2,""en"",""vi""),'Use Case Tracker'!B2))"),"Quản lý gói đăng ký và quyền truy cập tính năng") -> Quản lý gói đăng ký và quyền truy cập tính năng | C2: =IFERROR(__xludf.DUMMYFUNCTION("IF('Use Case Tracker'!C2="""","""",IFERROR(GOOGLETRANSLATE('Use Case Tracker'!C2,""en"",""vi""),'Use Case Tracker'!C2))"),"Hỗ trợ quản trị/Docker") -> Hỗ trợ quản trị/Docker | D2: =IFERROR(__xludf.DUMMYFUNCTION("IF('Use Case Tracker'!D2="""","""",IFERROR(GOOGLETRANSLATE('Use Case Tracker'!D2,""en"",""vi""),'Use Case Tracker'!D2))"),"Đăng ký") -> Đăng ký | E2: =IFERROR(__xludf.DUMMYFUNCTION("IF('Use Case Tracker'!E2="""","""",IFERROR(GOOGLETRANSLATE('Use Case Tracker'!E2,""en"",""vi""),'Use Case Tracker'!E2))"),"Quản trị viên") -> Quản trị viên | F2: =IFERROR(__xludf.DUMMYFUNCTION("IF('Use Case Tracker'!F2="""","""",IFERROR(GOOGLETRANSLATE('Use Case Tracker'!F2,""en"",""vi""),'Use Case Tracker'!F2))"),"Quản trị viên tạo/cập nhật/vô hiệu hóa các gói Miễn phí, Plus và Premium. Các gói trả phí chỉ được tính phí hàng năm. Mỗi gói xác định giá hàng năm và quyền truy cập vào các tính năng như báo cáo tài chính, phân tích AI, tính năng an toàn SOS, hỗ trợ thiế"&"t bị đeo, khả năng lưu trữ và xuất dữ liệu.") -> Quản trị viên tạo/cập nhật/vô hiệu hóa các gói Miễn phí, Plus và Premium. Các gói trả phí chỉ được tính phí hàng năm. Mỗi gói xác định giá hàng năm và quyền truy cập vào các tính năng như báo cáo tài chính, phân tích AI, tính năng an toàn SOS, hỗ trợ thiết bị đeo, khả năng lưu trữ và xuất dữ liệu. | G2: =IF('Use Case Tracker'!G2="","",SWITCH('Use Case Tracker'!G2,"Must-have","Bắt buộc","Should-have","Nên có","Could-have","Có thể có",'Use Case Tracker'!G2)) -> Bắt buộc | H2: =IF('Use Case Tracker'!H2="","",SWITCH('Use Case Tracker'!H2,"Not Started","Chưa bắt đầu","In Progress","Đang làm","Done","Hoàn thành",'Use Case Tracker'!H2)) -> Chưa bắt đầu | L2: =IF('Use Case Tracker'!L2="","",SWITCH('Use Case Tracker'!L2,"Keep","Giữ trong scope","Could-have / Do after core","Có thể có / Làm sau core",'Use Case Tracker'!L2)) -> Giữ trong scope
A3: =IF('Use Case Tracker'!A3="","",'Use Case Tracker'!A3) -> UC02 | B3: =IFERROR(__xludf.DUMMYFUNCTION("IF('Use Case Tracker'!B3="""","""",IFERROR(GOOGLETRANSLATE('Use Case Tracker'!B3,""en"",""vi""),'Use Case Tracker'!B3))"),"Quản lý không gian làm việc gia đình và trạng thái đăng ký") -> Quản lý không gian làm việc gia đình và trạng thái đăng ký | C3: =IFERROR(__xludf.DUMMYFUNCTION("IF('Use Case Tracker'!C3="""","""",IFERROR(GOOGLETRANSLATE('Use Case Tracker'!C3,""en"",""vi""),'Use Case Tracker'!C3))"),"Hỗ trợ quản trị/Docker") -> Hỗ trợ quản trị/Docker | D3: =IFERROR(__xludf.DUMMYFUNCTION("IF('Use Case Tracker'!D3="""","""",IFERROR(GOOGLETRANSLATE('Use Case Tracker'!D3,""en"",""vi""),'Use Case Tracker'!D3))"),"Quản trị viên") -> Quản trị viên | E3: =IFERROR(__xludf.DUMMYFUNCTION("IF('Use Case Tracker'!E3="""","""",IFERROR(GOOGLETRANSLATE('Use Case Tracker'!E3,""en"",""vi""),'Use Case Tracker'!E3))"),"Quản trị viên") -> Quản trị viên | F3: =IFERROR(__xludf.DUMMYFUNCTION("IF('Use Case Tracker'!F3="""","""",IFERROR(GOOGLETRANSLATE('Use Case Tracker'!F3,""en"",""vi""),'Use Case Tracker'!F3))"),"Quản trị viên xem không gian làm việc, Trình quản lý Gia đình chính, trạng thái đăng ký và kích hoạt.") -> Quản trị viên xem không gian làm việc, Trình quản lý Gia đình chính, trạng thái đăng ký và kích hoạt. | G3: =IF('Use Case Tracker'!G3="","",SWITCH('Use Case Tracker'!G3,"Must-have","Bắt buộc","Should-have","Nên có","Could-have","Có thể có",'Use Case Tracker'!G3)) -> Bắt buộc | H3: =IF('Use Case Tracker'!H3="","",SWITCH('Use Case Tracker'!H3,"Not Started","Chưa bắt đầu","In Progress","Đang làm","Done","Hoàn thành",'Use Case Tracker'!H3)) -> Chưa bắt đầu | I3: =IF('Use Case Tracker'!I3="","",'Use Case Tracker'!I3) | J3: =IF('Use Case Tracker'!J3="","",'Use Case Tracker'!J3) -> BR-SUB-01, BR-WS-02 | K3: =IFERROR(__xludf.DUMMYFUNCTION("IF('Use Case Tracker'!K3="""","""",IFERROR(GOOGLETRANSLATE('Use Case Tracker'!K3,""en"",""vi""),'Use Case Tracker'!K3))"),"") | L3: =IF('Use Case Tracker'!L3="","",SWITCH('Use Case Tracker'!L3,"Keep","Giữ trong scope","Could-have / Do after core","Có thể có / Làm sau core",'Use Case Tracker'!L3)) -> Giữ trong scope
A4: =IF('Use Case Tracker'!A4="","",'Use Case Tracker'!A4) -> UC03 | B4: =IFERROR(__xludf.DUMMYFUNCTION("IF('Use Case Tracker'!B4="""","""",IFERROR(GOOGLETRANSLATE('Use Case Tracker'!B4,""en"",""vi""),'Use Case Tracker'!B4))"),"Quản lý quyền truy cập tài khoản người dùng") -> Quản lý quyền truy cập tài khoản người dùng | C4: =IFERROR(__xludf.DUMMYFUNCTION("IF('Use Case Tracker'!C4="""","""",IFERROR(GOOGLETRANSLATE('Use Case Tracker'!C4,""en"",""vi""),'Use Case Tracker'!C4))"),"Hỗ trợ quản trị/Docker") -> Hỗ trợ quản trị/Docker | D4: =IFERROR(__xludf.DUMMYFUNCTION("IF('Use Case Tracker'!D4="""","""",IFERROR(GOOGLETRANSLATE('Use Case Tracker'!D4,""en"",""vi""),'Use Case Tracker'!D4))"),"Quản trị viên") -> Quản trị viên | E4: =IFERROR(__xludf.DUMMYFUNCTION("IF('Use Case Tracker'!E4="""","""",IFERROR(GOOGLETRANSLATE('Use Case Tracker'!E4,""en"",""vi""),'Use Case Tracker'!E4))"),"Quản trị viên") -> Quản trị viên | F4: =IFERROR(__xludf.DUMMYFUNCTION("IF('Use Case Tracker'!F4="""","""",IFERROR(GOOGLETRANSLATE('Use Case Tracker'!F4,""en"",""vi""),'Use Case Tracker'!F4))"),"Quản trị viên có thể khóa/mở khóa/hạn chế/khôi phục quyền truy cập của người dùng khi cần thiết.") -> Quản trị viên có thể khóa/mở khóa/hạn chế/khôi phục quyền truy cập của người dùng khi cần thiết. | G4: =IF('Use Case Tracker'!G4="","",SWITCH('Use Case Tracker'!G4,"Must-have","Bắt buộc","Should-have","Nên có","Could-have","Có thể có",'Use Case Tracker'!G4)) -> Bắt buộc | H4: =IF('Use Case Tracker'!H4="","",SWITCH('Use Case Tracker'!H4,"Not Started","Chưa bắt đầu","In Progress","Đang làm","Done","Hoàn thành",'Use Case Tracker'!H4)) -> Chưa bắt đầu | I4: =IF('Use Case Tracker'!I4="","",'Use Case Tracker'!I4) | J4: =IF('Use Case Tracker'!J4="","",'Use Case Tracker'!J4) -> BR-ADM-01, BR-AUTH-02 | K4: =IFERROR(__xludf.DUMMYFUNCTION("IF('Use Case Tracker'!K4="""","""",IFERROR(GOOGLETRANSLATE('Use Case Tracker'!K4,""en"",""vi""),'Use Case Tracker'!K4))"),"") | L4: =IF('Use Case Tracker'!L4="","",SWITCH('Use Case Tracker'!L4,"Keep","Giữ trong scope","Could-have / Do after core","Có thể có / Làm sau core",'Use Case Tracker'!L4)) -> Giữ trong scope
A5: =IF('Use Case Tracker'!A5="","",'Use Case Tracker'!A5) -> UC04 | B5: =IFERROR(__xludf.DUMMYFUNCTION("IF('Use Case Tracker'!B5="""","""",IFERROR(GOOGLETRANSLATE('Use Case Tracker'!B5,""en"",""vi""),'Use Case Tracker'!B5))"),"Giám sát trạng thái kích hoạt không gian làm việc") -> Giám sát trạng thái kích hoạt không gian làm việc | C5: =IFERROR(__xludf.DUMMYFUNCTION("IF('Use Case Tracker'!C5="""","""",IFERROR(GOOGLETRANSLATE('Use Case Tracker'!C5,""en"",""vi""),'Use Case Tracker'!C5))"),"Hỗ trợ quản trị/Docker") -> Hỗ trợ quản trị/Docker | D5: =IFERROR(__xludf.DUMMYFUNCTION("IF('Use Case Tracker'!D5="""","""",IFERROR(GOOGLETRANSLATE('Use Case Tracker'!D5,""en"",""vi""),'Use Case Tracker'!D5))"),"Quản trị viên") -> Quản trị viên | E5: =IFERROR(__xludf.DUMMYFUNCTION("IF('Use Case Tracker'!E5="""","""",IFERROR(GOOGLETRANSLATE('Use Case Tracker'!E5,""en"",""vi""),'Use Case Tracker'!E5))"),"Quản trị viên") -> Quản trị viên | F5: =IFERROR(__xludf.DUMMYFUNCTION("IF('Use Case Tracker'!F5="""","""",IFERROR(GOOGLETRANSLATE('Use Case Tracker'!F5,""en"",""vi""),'Use Case Tracker'!F5))"),"Quản trị viên kiểm tra trạng thái hoạt động/đang chờ xử lý/bị tạm dừng/thất bại/hết hạn của không gian làm việc.") -> Quản trị viên kiểm tra trạng thái hoạt động/đang chờ xử lý/bị tạm dừng/thất bại/hết hạn của không gian làm việc. | G5: =IF('Use Case Tracker'!G5="","",SWITCH('Use Case Tracker'!G5,"Must-have","Bắt buộc","Should-have","Nên có","Could-have","Có thể có",'Use Case Tracker'!G5)) -> Bắt buộc | H5: =IF('Use Case Tracker'!H5="","",SWITCH('Use Case Tracker'!H5,"Not Started","Chưa bắt đầu","In Progress","Đang làm","Done","Hoàn thành",'Use Case Tracker'!H5)) -> Chưa bắt đầu | I5: =IF('Use Case Tracker'!I5="","",'Use Case Tracker'!I5) | J5: =IF('Use Case Tracker'!J5="","",'Use Case Tracker'!J5) -> BR-WS-02, BR-DEP-01 | K5: =IFERROR(__xludf.DUMMYFUNCTION("IF('Use Case Tracker'!K5="""","""",IFERROR(GOOGLETRANSLATE('Use Case Tracker'!K5,""en"",""vi""),'Use Case Tracker'!K5))"),"") | L5: =IF('Use Case Tracker'!L5="","",SWITCH('Use Case Tracker'!L5,"Keep","Giữ trong scope","Could-have / Do after core","Có thể có / Làm sau core",'Use Case Tracker'!L5)) -> Giữ trong scope
A6: =IF('Use Case Tracker'!A6="","",'Use Case Tracker'!A6) -> UC05 | B6: =IFERROR(__xludf.DUMMYFUNCTION("IF('Use Case Tracker'!B6="""","""",IFERROR(GOOGLETRANSLATE('Use Case Tracker'!B6,""en"",""vi""),'Use Case Tracker'!B6))"),"Xem trạng thái dịch vụ cơ bản") -> Xem trạng thái dịch vụ cơ bản | C6: =IFERROR(__xludf.DUMMYFUNCTION("IF('Use Case Tracker'!C6="""","""",IFERROR(GOOGLETRANSLATE('Use Case Tracker'!C6,""en"",""vi""),'Use Case Tracker'!C6))"),"Hỗ trợ quản trị/Docker") -> Hỗ trợ quản trị/Docker | D6: =IFERROR(__xludf.DUMMYFUNCTION("IF('Use Case Tracker'!D6="""","""",IFERROR(GOOGLETRANSLATE('Use Case Tracker'!D6,""en"",""vi""),'Use Case Tracker'!D6))"),"Quản trị viên") -> Quản trị viên | E6: =IFERROR(__xludf.DUMMYFUNCTION("IF('Use Case Tracker'!E6="""","""",IFERROR(GOOGLETRANSLATE('Use Case Tracker'!E6,""en"",""vi""),'Use Case Tracker'!E6))"),"Quản trị viên") -> Quản trị viên | F6: =IFERROR(__xludf.DUMMYFUNCTION("IF('Use Case Tracker'!F6="""","""",IFERROR(GOOGLETRANSLATE('Use Case Tracker'!F6,""en"",""vi""),'Use Case Tracker'!F6))"),"Quản trị viên có thể xem trạng thái dịch vụ demo cơ bản như Backend, Admin Web, API và Database.") -> Quản trị viên có thể xem trạng thái dịch vụ demo cơ bản như Backend, Admin Web, API và Database. | G6: =IF('Use Case Tracker'!G6="","",SWITCH('Use Case Tracker'!G6,"Must-have","Bắt buộc","Should-have","Nên có","Could-have","Có thể có",'Use Case Tracker'!G6)) -> Nên có | H6: =IF('Use Case Tracker'!H6="","",SWITCH('Use Case Tracker'!H6,"Not Started","Chưa bắt đầu","In Progress","Đang làm","Done","Hoàn thành",'Use Case Tracker'!H6)) -> Chưa bắt đầu | I6: =IF('Use Case Tracker'!I6="","",'Use Case Tracker'!I6) | J6: =IF('Use Case Tracker'!J6="","",'Use Case Tracker'!J6) -> BR-DEP-01, BR-FUT-01 | K6: =IFERROR(__xludf.DUMMYFUNCTION("IF('Use Case Tracker'!K6="""","""",IFERROR(GOOGLETRANSLATE('Use Case Tracker'!K6,""en"",""vi""),'Use Case Tracker'!K6))"),"") | L6: =IF('Use Case Tracker'!L6="","",SWITCH('Use Case Tracker'!L6,"Keep","Giữ trong scope","Could-have / Do after core","Có thể có / Làm sau core",'Use Case Tracker'!L6)) -> Giữ trong scope
A7: =IF('Use Case Tracker'!A7="","",'Use Case Tracker'!A7) -> UC06 | B7: =IFERROR(__xludf.DUMMYFUNCTION("IF('Use Case Tracker'!B7="""","""",IFERROR(GOOGLETRANSLATE('Use Case Tracker'!B7,""en"",""vi""),'Use Case Tracker'!B7))"),"Xem nhật ký cấp phép không gian làm việc") -> Xem nhật ký cấp phép không gian làm việc | C7: =IFERROR(__xludf.DUMMYFUNCTION("IF('Use Case Tracker'!C7="""","""",IFERROR(GOOGLETRANSLATE('Use Case Tracker'!C7,""en"",""vi""),'Use Case Tracker'!C7))"),"Hỗ trợ quản trị/Docker") -> Hỗ trợ quản trị/Docker | D7: =IFERROR(__xludf.DUMMYFUNCTION("IF('Use Case Tracker'!D7="""","""",IFERROR(GOOGLETRANSLATE('Use Case Tracker'!D7,""en"",""vi""),'Use Case Tracker'!D7))"),"Quản trị viên") -> Quản trị viên | E7: =IFERROR(__xludf.DUMMYFUNCTION("IF('Use Case Tracker'!E7="""","""",IFERROR(GOOGLETRANSLATE('Use Case Tracker'!E7,""en"",""vi""),'Use Case Tracker'!E7))"),"Quản trị viên") -> Quản trị viên | F7: =IFERROR(__xludf.DUMMYFUNCTION("IF('Use Case Tracker'!F7="""","""",IFERROR(GOOGLETRANSLATE('Use Case Tracker'!F7,""en"",""vi""),'Use Case Tracker'!F7))"),"Quản trị viên xem nhật ký cấp phép cơ bản về các lỗi kích hoạt không gian làm việc/khởi động bản demo.") -> Quản trị viên xem nhật ký cấp phép cơ bản về các lỗi kích hoạt không gian làm việc/khởi động bản demo. | G7: =IF('Use Case Tracker'!G7="","",SWITCH('Use Case Tracker'!G7,"Must-have","Bắt buộc","Should-have","Nên có","Could-have","Có thể có",'Use Case Tracker'!G7)) -> Nên có | H7: =IF('Use Case Tracker'!H7="","",SWITCH('Use Case Tracker'!H7,"Not Started","Chưa bắt đầu","In Progress","Đang làm","Done","Hoàn thành",'Use Case Tracker'!H7)) -> Chưa bắt đầu | J7: =IF('Use Case Tracker'!J7="","",'Use Case Tracker'!J7) -> BR-DEP-01 | K7: =IFERROR(__xludf.DUMMYFUNCTION("IF('Use Case Tracker'!K7="""","""",IFERROR(GOOGLETRANSLATE('Use Case Tracker'!K7,""en"",""vi""),'Use Case Tracker'!K7))"),"") | L7: =IF('Use Case Tracker'!L7="","",SWITCH('Use Case Tracker'!L7,"Keep","Giữ trong scope","Could-have / Do after core","Có thể có / Làm sau core",'Use Case Tracker'!L7)) -> Giữ trong scope
A8: =IF('Use Case Tracker'!A8="","",'Use Case Tracker'!A8) -> UC07 | B8: =IFERROR(__xludf.DUMMYFUNCTION("IF('Use Case Tracker'!B8="""","""",IFERROR(GOOGLETRANSLATE('Use Case Tracker'!B8,""en"",""vi""),'Use Case Tracker'!B8))"),"Thử lại việc cấp phát không gian làm việc") -> Thử lại việc cấp phát không gian làm việc | C8: =IFERROR(__xludf.DUMMYFUNCTION("IF('Use Case Tracker'!C8="""","""",IFERROR(GOOGLETRANSLATE('Use Case Tracker'!C8,""en"",""vi""),'Use Case Tracker'!C8))"),"Hỗ trợ quản trị/Docker") -> Hỗ trợ quản trị/Docker | D8: =IFERROR(__xludf.DUMMYFUNCTION("IF('Use Case Tracker'!D8="""","""",IFERROR(GOOGLETRANSLATE('Use Case Tracker'!D8,""en"",""vi""),'Use Case Tracker'!D8))"),"Quản trị viên") -> Quản trị viên | E8: =IFERROR(__xludf.DUMMYFUNCTION("IF('Use Case Tracker'!E8="""","""",IFERROR(GOOGLETRANSLATE('Use Case Tracker'!E8,""en"",""vi""),'Use Case Tracker'!E8))"),"Quản trị viên") -> Quản trị viên | F8: =IFERROR(__xludf.DUMMYFUNCTION("IF('Use Case Tracker'!F8="""","""",IFERROR(GOOGLETRANSLATE('Use Case Tracker'!F8,""en"",""vi""),'Use Case Tracker'!F8))"),"Quản trị viên sẽ thử lại quá trình kích hoạt/cung cấp không gian làm việc khi thiết lập bản demo thất bại.") -> Quản trị viên sẽ thử lại quá trình kích hoạt/cung cấp không gian làm việc khi thiết lập bản demo thất bại. | G8: =IF('Use Case Tracker'!G8="","",SWITCH('Use Case Tracker'!G8,"Must-have","Bắt buộc","Should-have","Nên có","Could-have","Có thể có",'Use Case Tracker'!G8)) -> Nên có | H8: =IF('Use Case Tracker'!H8="","",SWITCH('Use Case Tracker'!H8,"Not Started","Chưa bắt đầu","In Progress","Đang làm","Done","Hoàn thành",'Use Case Tracker'!H8)) -> Chưa bắt đầu | J8: =IF('Use Case Tracker'!J8="","",'Use Case Tracker'!J8) -> BR-DEP-01 | K8: =IFERROR(__xludf.DUMMYFUNCTION("IF('Use Case Tracker'!K8="""","""",IFERROR(GOOGLETRANSLATE('Use Case Tracker'!K8,""en"",""vi""),'Use Case Tracker'!K8))"),"") | L8: =IF('Use Case Tracker'!L8="","",SWITCH('Use Case Tracker'!L8,"Keep","Giữ trong scope","Could-have / Do after core","Có thể có / Làm sau core",'Use Case Tracker'!L8)) -> Giữ trong scope
A9: =IF('Use Case Tracker'!A9="","",'Use Case Tracker'!A9) -> UC08 | B9: =IFERROR(__xludf.DUMMYFUNCTION("IF('Use Case Tracker'!B9="""","""",IFERROR(GOOGLETRANSLATE('Use Case Tracker'!B9,""en"",""vi""),'Use Case Tracker'!B9))"),"Xem tóm tắt gói đăng ký cơ bản") -> Xem tóm tắt gói đăng ký cơ bản | C9: =IFERROR(__xludf.DUMMYFUNCTION("IF('Use Case Tracker'!C9="""","""",IFERROR(GOOGLETRANSLATE('Use Case Tracker'!C9,""en"",""vi""),'Use Case Tracker'!C9))"),"Hỗ trợ quản trị/Docker") -> Hỗ trợ quản trị/Docker | D9: =IFERROR(__xludf.DUMMYFUNCTION("IF('Use Case Tracker'!D9="""","""",IFERROR(GOOGLETRANSLATE('Use Case Tracker'!D9,""en"",""vi""),'Use Case Tracker'!D9))"),"Quản trị viên") -> Quản trị viên | E9: =IFERROR(__xludf.DUMMYFUNCTION("IF('Use Case Tracker'!E9="""","""",IFERROR(GOOGLETRANSLATE('Use Case Tracker'!E9,""en"",""vi""),'Use Case Tracker'!E9))"),"Quản trị viên") -> Quản trị viên | F9: =IFERROR(__xludf.DUMMYFUNCTION("IF('Use Case Tracker'!F9="""","""",IFERROR(GOOGLETRANSLATE('Use Case Tracker'!F9,""en"",""vi""),'Use Case Tracker'!F9))"),"Quản trị viên chỉ xem được bản tóm tắt cơ bản về gói đăng ký; các biểu đồ/xuất dữ liệu nâng cao sẽ được bổ sung trong tương") -> Quản trị viên chỉ xem được bản tóm tắt cơ bản về gói đăng ký; các biểu đồ/xuất dữ liệu nâng cao sẽ được bổ sung trong tương | G9: =IF('Use Case Tracker'!G9="","",SWITCH('Use Case Tracker'!G9,"Must-have","Bắt buộc","Should-have","Nên có","Could-have","Có thể có",'Use Case Tracker'!G9)) -> Có thể có | H9: =IF('Use Case Tracker'!H9="","",SWITCH('Use Case Tracker'!H9,"Not Started","Chưa bắt đầu","In Progress","Đang làm","Done","Hoàn thành",'Use Case Tracker'!H9)) -> Chưa bắt đầu | J9: =IF('Use Case Tracker'!J9="","",'Use Case Tracker'!J9) -> BR-SUB-01, BR-FUT-01 | K9: =IFERROR(__xludf.DUMMYFUNCTION("IF('Use Case Tracker'!K9="""","""",IFERROR(GOOGLETRANSLATE('Use Case Tracker'!K9,""en"",""vi""),'Use Case Tracker'!K9))"),"") | L9: =IF('Use Case Tracker'!L9="","",SWITCH('Use Case Tracker'!L9,"Keep","Giữ trong scope","Could-have / Do after core","Có thể có / Làm sau core",'Use Case Tracker'!L9)) -> Có thể có / Làm sau core
A10: =IF('Use Case Tracker'!A10="","",'Use Case Tracker'!A10) -> UC09 | B10: =IFERROR(__xludf.DUMMYFUNCTION("IF('Use Case Tracker'!B10="""","""",IFERROR(GOOGLETRANSLATE('Use Case Tracker'!B10,""en"",""vi""),'Use Case Tracker'!B10))"),"Hoàn thành mẫu đăng ký gia đình - Thông tin tài khoản") -> Hoàn thành mẫu đăng ký gia đình - Thông tin tài khoản | C10: =IFERROR(__xludf.DUMMYFUNCTION("IF('Use Case Tracker'!C10="""","""",IFERROR(GOOGLETRANSLATE('Use Case Tracker'!C10,""en"",""vi""),'Use Case Tracker'!C10))"),"Luồng 1") -> Luồng 1 | D10: =IFERROR(__xludf.DUMMYFUNCTION("IF('Use Case Tracker'!D10="""","""",IFERROR(GOOGLETRANSLATE('Use Case Tracker'!D10,""en"",""vi""),'Use Case Tracker'!D10))"),"Xác thực") -> Xác thực | E10: =IFERROR(__xludf.DUMMYFUNCTION("IF('Use Case Tracker'!E10="""","""",IFERROR(GOOGLETRANSLATE('Use Case Tracker'!E10,""en"",""vi""),'Use Case Tracker'!E10))"),"Người đại diện gia đình/Người dùng mới") -> Người đại diện gia đình/Người dùng mới | F10: =IFERROR(__xludf.DUMMYFUNCTION("IF('Use Case Tracker'!F10="""","""",IFERROR(GOOGLETRANSLATE('Use Case Tracker'!F10,""en"",""vi""),'Use Case Tracker'!F10))"),"Nhập thông tin đăng ký tài khoản vào Biểu mẫu Gia đình. (Tạo thông tin tài khoản -> Tạo thông tin không gian làm việc cho gia đình)") -> Nhập thông tin đăng ký tài khoản vào Biểu mẫu Gia đình. (Tạo thông tin tài khoản -> Tạo thông tin không gian làm việc cho gia đình) | G10: =IF('Use Case Tracker'!G10="","",SWITCH('Use Case Tracker'!G10,"Must-have","Bắt buộc","Should-have","Nên có","Could-have","Có thể có",'Use Case Tracker'!G10)) -> Bắt buộc | H10: =IF('Use Case Tracker'!H10="","",SWITCH('Use Case Tracker'!H10,"Not Started","Chưa bắt đầu","In Progress","Đang làm","Done","Hoàn thành",'Use Case Tracker'!H10)) -> Chưa bắt đầu | J10: BR-AUTH-01, BR-AUTH-03 | K10: Thông tin tài khoản được xử lý trước bước thiết lập workspace. Nếu email/số điện thoại đã tồn tại, hệ thống chuyển người dùng sang đăng nhập/quên mật khẩu hoặc gửi lại mã xác minh nếu tài khoản chưa xác minh. | L10: =IF('Use Case Tracker'!L10="","",SWITCH('Use Case Tracker'!L10,"Keep","Giữ trong scope","Could-have / Do after core","Có thể có / Làm sau core",'Use Case Tracker'!L10)) -> Giữ trong scope
A11: =IF('Use Case Tracker'!A11="","",'Use Case Tracker'!A11) -> UC10 | B11: =IFERROR(__xludf.DUMMYFUNCTION("IF('Use Case Tracker'!B11="""","""",IFERROR(GOOGLETRANSLATE('Use Case Tracker'!B11,""en"",""vi""),'Use Case Tracker'!B11))"),"Xác minh tài khoản") -> Xác minh tài khoản | C11: =IFERROR(__xludf.DUMMYFUNCTION("IF('Use Case Tracker'!C11="""","""",IFERROR(GOOGLETRANSLATE('Use Case Tracker'!C11,""en"",""vi""),'Use Case Tracker'!C11))"),"Luồng 1") -> Luồng 1 | D11: =IFERROR(__xludf.DUMMYFUNCTION("IF('Use Case Tracker'!D11="""","""",IFERROR(GOOGLETRANSLATE('Use Case Tracker'!D11,""en"",""vi""),'Use Case Tracker'!D11))"),"Xác thực") -> Xác thực | E11: =IFERROR(__xludf.DUMMYFUNCTION("IF('Use Case Tracker'!E11="""","""",IFERROR(GOOGLETRANSLATE('Use Case Tracker'!E11,""en"",""vi""),'Use Case Tracker'!E11))"),"Người đại diện gia đình/Người dùng mới") -> Người đại diện gia đình/Người dùng mới | F11: =IFERROR(__xludf.DUMMYFUNCTION("IF('Use Case Tracker'!F11="""","""",IFERROR(GOOGLETRANSLATE('Use Case Tracker'!F11,""en"",""vi""),'Use Case Tracker'!F11))"),"Nếu việc xác minh tài khoản là bắt buộc trước khi kích hoạt đầy đủ không gian làm việc, hãy xác minh tài khoản sau khi hoàn tất thủ tục đăng ký.") -> Nếu việc xác minh tài khoản là bắt buộc trước khi kích hoạt đầy đủ không gian làm việc, hãy xác minh tài khoản sau khi hoàn tất thủ tục đăng ký. | G11: =IF('Use Case Tracker'!G11="","",SWITCH('Use Case Tracker'!G11,"Must-have","Bắt buộc","Should-have","Nên có","Could-have","Có thể có",'Use Case Tracker'!G11)) -> Bắt buộc | H11: =IF('Use Case Tracker'!H11="","",SWITCH('Use Case Tracker'!H11,"Not Started","Chưa bắt đầu","In Progress","Đang làm","Done","Hoàn thành",'Use Case Tracker'!H11)) -> Chưa bắt đầu | J11: =IF('Use Case Tracker'!J11="","",'Use Case Tracker'!J11) -> BR-AUTH-01 | K11: =IFERROR(__xludf.DUMMYFUNCTION("IF('Use Case Tracker'!K11="""","""",IFERROR(GOOGLETRANSLATE('Use Case Tracker'!K11,""en"",""vi""),'Use Case Tracker'!K11))"),"Việc xác minh có thể được thực hiện qua email/điện thoại/mã hoặc mô phỏng để minh họa.") -> Việc xác minh có thể được thực hiện qua email/điện thoại/mã hoặc mô phỏng để minh họa. | L11: =IF('Use Case Tracker'!L11="","",SWITCH('Use Case Tracker'!L11,"Keep","Giữ trong scope","Could-have / Do after core","Có thể có / Làm sau core",'Use Case Tracker'!L11)) -> Giữ trong scope
A12: =IF('Use Case Tracker'!A12="","",'Use Case Tracker'!A12) -> UC11 | B12: =IFERROR(__xludf.DUMMYFUNCTION("IF('Use Case Tracker'!B12="""","""",IFERROR(GOOGLETRANSLATE('Use Case Tracker'!B12,""en"",""vi""),'Use Case Tracker'!B12))"),"Đăng nhập / Đăng xuất") -> Đăng nhập / Đăng xuất | C12: =IFERROR(__xludf.DUMMYFUNCTION("IF('Use Case Tracker'!C12="""","""",IFERROR(GOOGLETRANSLATE('Use Case Tracker'!C12,""en"",""vi""),'Use Case Tracker'!C12))"),"Luồng 1") -> Luồng 1 | D12: =IFERROR(__xludf.DUMMYFUNCTION("IF('Use Case Tracker'!D12="""","""",IFERROR(GOOGLETRANSLATE('Use Case Tracker'!D12,""en"",""vi""),'Use Case Tracker'!D12))"),"Xác thực") -> Xác thực | E12: =IFERROR(__xludf.DUMMYFUNCTION("IF('Use Case Tracker'!E12="""","""",IFERROR(GOOGLETRANSLATE('Use Case Tracker'!E12,""en"",""vi""),'Use Case Tracker'!E12))"),"Tất cả người dùng") -> Tất cả người dùng | F12: =IFERROR(__xludf.DUMMYFUNCTION("IF('Use Case Tracker'!F12="""","""",IFERROR(GOOGLETRANSLATE('Use Case Tracker'!F12,""en"",""vi""),'Use Case Tracker'!F12))"),"Đăng nhập hoặc đăng xuất sau khi hoàn tất quá trình thiết lập tài khoản/không gian làm việc.") -> Đăng nhập hoặc đăng xuất sau khi hoàn tất quá trình thiết lập tài khoản/không gian làm việc. | G12: =IF('Use Case Tracker'!G12="","",SWITCH('Use Case Tracker'!G12,"Must-have","Bắt buộc","Should-have","Nên có","Could-have","Có thể có",'Use Case Tracker'!G12)) -> Bắt buộc | H12: =IF('Use Case Tracker'!H12="","",SWITCH('Use Case Tracker'!H12,"Not Started","Chưa bắt đầu","In Progress","Đang làm","Done","Hoàn thành",'Use Case Tracker'!H12)) -> Chưa bắt đầu | J12: =IF('Use Case Tracker'!J12="","",'Use Case Tracker'!J12) -> BR-AUTH-02 | K12: =IFERROR(__xludf.DUMMYFUNCTION("IF('Use Case Tracker'!K12="""","""",IFERROR(GOOGLETRANSLATE('Use Case Tracker'!K12,""en"",""vi""),'Use Case Tracker'!K12))"),"Việc đăng nhập có thể tự động sau khi hoàn tất quá trình đăng ký, tùy thuộc vào cách triển khai.") -> Việc đăng nhập có thể tự động sau khi hoàn tất quá trình đăng ký, tùy thuộc vào cách triển khai. | L12: =IF('Use Case Tracker'!L12="","",SWITCH('Use Case Tracker'!L12,"Keep","Giữ trong scope","Could-have / Do after core","Có thể có / Làm sau core",'Use Case Tracker'!L12)) -> Giữ trong scope
A13: =IF('Use Case Tracker'!A16="","",'Use Case Tracker'!A16) -> UC15 | B13: =IFERROR(__xludf.DUMMYFUNCTION("IF('Use Case Tracker'!B16="""","""",IFERROR(GOOGLETRANSLATE('Use Case Tracker'!B16,""en"",""vi""),'Use Case Tracker'!B16))"),"Mời thành viên gia đình") -> Mời thành viên gia đình | C13: =IFERROR(__xludf.DUMMYFUNCTION("IF('Use Case Tracker'!C16="""","""",IFERROR(GOOGLETRANSLATE('Use Case Tracker'!C16,""en"",""vi""),'Use Case Tracker'!C16))"),"Luồng 2") -> Luồng 2 | D13: =IFERROR(__xludf.DUMMYFUNCTION("IF('Use Case Tracker'!D16="""","""",IFERROR(GOOGLETRANSLATE('Use Case Tracker'!D16,""en"",""vi""),'Use Case Tracker'!D16))"),"Gia đình") -> Gia đình | E13: =IFERROR(__xludf.DUMMYFUNCTION("IF('Use Case Tracker'!E16="""","""",IFERROR(GOOGLETRANSLATE('Use Case Tracker'!E16,""en"",""vi""),'Use Case Tracker'!E16))"),"Quản lý gia đình") -> Quản lý gia đình | F13: =IFERROR(__xludf.DUMMYFUNCTION("IF('Use Case Tracker'!F16="""","""",IFERROR(GOOGLETRANSLATE('Use Case Tracker'!F16,""en"",""vi""),'Use Case Tracker'!F16))"),"Mời thành viên gia đình") -> Mời thành viên gia đình | G13: =IF('Use Case Tracker'!G16="","",SWITCH('Use Case Tracker'!G16,"Must-have","Bắt buộc","Should-have","Nên có","Could-have","Có thể có",'Use Case Tracker'!G16)) -> Bắt buộc | H13: =IF('Use Case Tracker'!H16="","",SWITCH('Use Case Tracker'!H16,"Not Started","Chưa bắt đầu","In Progress","Đang làm","Done","Hoàn thành",'Use Case Tracker'!H16)) -> Chưa bắt đầu | J13: =IF('Use Case Tracker'!J16="","",'Use Case Tracker'!J16) -> BR-INV-01, BR-ROLE-01 | K13: =IFERROR(__xludf.DUMMYFUNCTION("IF('Use Case Tracker'!K16="""","""",IFERROR(GOOGLETRANSLATE('Use Case Tracker'!K16,""en"",""vi""),'Use Case Tracker'!K16))"),"") | L13: =IF('Use Case Tracker'!L16="","",SWITCH('Use Case Tracker'!L16,"Keep","Giữ trong scope","Could-have / Do after core","Có thể có / Làm sau core",'Use Case Tracker'!L16)) -> Giữ trong scope
A14: =IF('Use Case Tracker'!A17="","",'Use Case Tracker'!A17) -> UC16 | B14: =IFERROR(__xludf.DUMMYFUNCTION("IF('Use Case Tracker'!B17="""","""",IFERROR(GOOGLETRANSLATE('Use Case Tracker'!B17,""en"",""vi""),'Use Case Tracker'!B17))"),"Quản lý lời mời gia đình") -> Quản lý lời mời gia đình | C14: =IFERROR(__xludf.DUMMYFUNCTION("IF('Use Case Tracker'!C17="""","""",IFERROR(GOOGLETRANSLATE('Use Case Tracker'!C17,""en"",""vi""),'Use Case Tracker'!C17))"),"Luồng 2") -> Luồng 2 | D14: =IFERROR(__xludf.DUMMYFUNCTION("IF('Use Case Tracker'!D17="""","""",IFERROR(GOOGLETRANSLATE('Use Case Tracker'!D17,""en"",""vi""),'Use Case Tracker'!D17))"),"Gia đình") -> Gia đình | E14: =IFERROR(__xludf.DUMMYFUNCTION("IF('Use Case Tracker'!E17="""","""",IFERROR(GOOGLETRANSLATE('Use Case Tracker'!E17,""en"",""vi""),'Use Case Tracker'!E17))"),"Quản lý gia đình") -> Quản lý gia đình | F14: =IFERROR(__xludf.DUMMYFUNCTION("IF('Use Case Tracker'!F17="""","""",IFERROR(GOOGLETRANSLATE('Use Case Tracker'!F17,""en"",""vi""),'Use Case Tracker'!F17))"),"Quản lý lời mời gia đình") -> Quản lý lời mời gia đình | G14: =IF('Use Case Tracker'!G17="","",SWITCH('Use Case Tracker'!G17,"Must-have","Bắt buộc","Should-have","Nên có","Could-have","Có thể có",'Use Case Tracker'!G17)) -> Nên có | H14: =IF('Use Case Tracker'!H17="","",SWITCH('Use Case Tracker'!H17,"Not Started","Chưa bắt đầu","In Progress","Đang làm","Done","Hoàn thành",'Use Case Tracker'!H17)) -> Chưa bắt đầu | J14: =IF('Use Case Tracker'!J17="","",'Use Case Tracker'!J17) -> BR-INV-01 | K14: =IFERROR(__xludf.DUMMYFUNCTION("IF('Use Case Tracker'!K17="""","""",IFERROR(GOOGLETRANSLATE('Use Case Tracker'!K17,""en"",""vi""),'Use Case Tracker'!K17))"),"") | L14: =IF('Use Case Tracker'!L17="","",SWITCH('Use Case Tracker'!L17,"Keep","Giữ trong scope","Could-have / Do after core","Có thể có / Làm sau core",'Use Case Tracker'!L17)) -> Giữ trong scope
A15: =IF('Use Case Tracker'!A18="","",'Use Case Tracker'!A18) -> UC17 | B15: =IFERROR(__xludf.DUMMYFUNCTION("IF('Use Case Tracker'!B18="""","""",IFERROR(GOOGLETRANSLATE('Use Case Tracker'!B18,""en"",""vi""),'Use Case Tracker'!B18))"),"Quản lý vai trò và mối quan hệ của thành viên") -> Quản lý vai trò và mối quan hệ của thành viên | C15: =IFERROR(__xludf.DUMMYFUNCTION("IF('Use Case Tracker'!C18="""","""",IFERROR(GOOGLETRANSLATE('Use Case Tracker'!C18,""en"",""vi""),'Use Case Tracker'!C18))"),"Luồng 2") -> Luồng 2 | D15: =IFERROR(__xludf.DUMMYFUNCTION("IF('Use Case Tracker'!D18="""","""",IFERROR(GOOGLETRANSLATE('Use Case Tracker'!D18,""en"",""vi""),'Use Case Tracker'!D18))"),"Gia đình") -> Gia đình | E15: =IFERROR(__xludf.DUMMYFUNCTION("IF('Use Case Tracker'!E18="""","""",IFERROR(GOOGLETRANSLATE('Use Case Tracker'!E18,""en"",""vi""),'Use Case Tracker'!E18))"),"Quản lý gia đình") -> Quản lý gia đình | F15: =IFERROR(__xludf.DUMMYFUNCTION("IF('Use Case Tracker'!F18="""","""",IFERROR(GOOGLETRANSLATE('Use Case Tracker'!F18,""en"",""vi""),'Use Case Tracker'!F18))"),"Quản lý vai trò và mối quan hệ của thành viên") -> Quản lý vai trò và mối quan hệ của thành viên | G15: =IF('Use Case Tracker'!G18="","",SWITCH('Use Case Tracker'!G18,"Must-have","Bắt buộc","Should-have","Nên có","Could-have","Có thể có",'Use Case Tracker'!G18)) -> Bắt buộc | H15: =IF('Use Case Tracker'!H18="","",SWITCH('Use Case Tracker'!H18,"Not Started","Chưa bắt đầu","In Progress","Đang làm","Done","Hoàn thành",'Use Case Tracker'!H18)) -> Chưa bắt đầu | J15: =IF('Use Case Tracker'!J18="","",'Use Case Tracker'!J18) -> BR-ROLE-03, BR-ROLE-04 | K15: =IFERROR(__xludf.DUMMYFUNCTION("IF('Use Case Tracker'!K18="""","""",IFERROR(GOOGLETRANSLATE('Use Case Tracker'!K18,""en"",""vi""),'Use Case Tracker'!K18))"),"") | L15: =IF('Use Case Tracker'!L18="","",SWITCH('Use Case Tracker'!L18,"Keep","Giữ trong scope","Could-have / Do after core","Có thể có / Làm sau core",'Use Case Tracker'!L18)) -> Giữ trong scope
A16: =IF('Use Case Tracker'!A19="","",'Use Case Tracker'!A19) -> UC18 | B16: =IFERROR(__xludf.DUMMYFUNCTION("IF('Use Case Tracker'!B19="""","""",IFERROR(GOOGLETRANSLATE('Use Case Tracker'!B19,""en"",""vi""),'Use Case Tracker'!B19))"),"Cấp hoặc thu hồi quyền thay mặt") -> Cấp hoặc thu hồi quyền thay mặt | C16: =IFERROR(__xludf.DUMMYFUNCTION("IF('Use Case Tracker'!C19="""","""",IFERROR(GOOGLETRANSLATE('Use Case Tracker'!C19,""en"",""vi""),'Use Case Tracker'!C19))"),"Luồng 2") -> Luồng 2 | D16: =IFERROR(__xludf.DUMMYFUNCTION("IF('Use Case Tracker'!D19="""","""",IFERROR(GOOGLETRANSLATE('Use Case Tracker'!D19,""en"",""vi""),'Use Case Tracker'!D19))"),"Gia đình") -> Gia đình | E16: =IFERROR(__xludf.DUMMYFUNCTION("IF('Use Case Tracker'!E19="""","""",IFERROR(GOOGLETRANSLATE('Use Case Tracker'!E19,""en"",""vi""),'Use Case Tracker'!E19))"),"Quản lý gia đình") -> Quản lý gia đình | F16: =IFERROR(__xludf.DUMMYFUNCTION("IF('Use Case Tracker'!F19="""","""",IFERROR(GOOGLETRANSLATE('Use Case Tracker'!F19,""en"",""vi""),'Use Case Tracker'!F19))"),"Cấp hoặc thu hồi quyền thay mặt") -> Cấp hoặc thu hồi quyền thay mặt | G16: =IF('Use Case Tracker'!G19="","",SWITCH('Use Case Tracker'!G19,"Must-have","Bắt buộc","Should-have","Nên có","Could-have","Có thể có",'Use Case Tracker'!G19)) -> Bắt buộc | H16: =IF('Use Case Tracker'!H19="","",SWITCH('Use Case Tracker'!H19,"Not Started","Chưa bắt đầu","In Progress","Đang làm","Done","Hoàn thành",'Use Case Tracker'!H19)) -> Chưa bắt đầu | J16: =IF('Use Case Tracker'!J19="","",'Use Case Tracker'!J19) -> BR-ROLE-02, BR-ROLE-01 | K16: =IFERROR(__xludf.DUMMYFUNCTION("IF('Use Case Tracker'!K19="""","""",IFERROR(GOOGLETRANSLATE('Use Case Tracker'!K19,""en"",""vi""),'Use Case Tracker'!K19))"),"") | L16: =IF('Use Case Tracker'!L19="","",SWITCH('Use Case Tracker'!L19,"Keep","Giữ trong scope","Could-have / Do after core","Có thể có / Làm sau core",'Use Case Tracker'!L19)) -> Giữ trong scope
A17: =IF('Use Case Tracker'!A20="","",'Use Case Tracker'!A20) -> UC19 | B17: =IFERROR(__xludf.DUMMYFUNCTION("IF('Use Case Tracker'!B20="""","""",IFERROR(GOOGLETRANSLATE('Use Case Tracker'!B20,""en"",""vi""),'Use Case Tracker'!B20))"),"Xóa hoặc vô hiệu hóa thành viên gia đình") -> Xóa hoặc vô hiệu hóa thành viên gia đình | C17: =IFERROR(__xludf.DUMMYFUNCTION("IF('Use Case Tracker'!C20="""","""",IFERROR(GOOGLETRANSLATE('Use Case Tracker'!C20,""en"",""vi""),'Use Case Tracker'!C20))"),"Luồng 2") -> Luồng 2 | D17: =IFERROR(__xludf.DUMMYFUNCTION("IF('Use Case Tracker'!D20="""","""",IFERROR(GOOGLETRANSLATE('Use Case Tracker'!D20,""en"",""vi""),'Use Case Tracker'!D20))"),"Gia đình") -> Gia đình | E17: =IFERROR(__xludf.DUMMYFUNCTION("IF('Use Case Tracker'!E20="""","""",IFERROR(GOOGLETRANSLATE('Use Case Tracker'!E20,""en"",""vi""),'Use Case Tracker'!E20))"),"Quản lý gia đình") -> Quản lý gia đình | F17: =IFERROR(__xludf.DUMMYFUNCTION("IF('Use Case Tracker'!F20="""","""",IFERROR(GOOGLETRANSLATE('Use Case Tracker'!F20,""en"",""vi""),'Use Case Tracker'!F20))"),"Xóa hoặc vô hiệu hóa thành viên gia đình") -> Xóa hoặc vô hiệu hóa thành viên gia đình | G17: =IF('Use Case Tracker'!G20="","",SWITCH('Use Case Tracker'!G20,"Must-have","Bắt buộc","Should-have","Nên có","Could-have","Có thể có",'Use Case Tracker'!G20)) -> Bắt buộc | H17: =IF('Use Case Tracker'!H20="","",SWITCH('Use Case Tracker'!H20,"Not Started","Chưa bắt đầu","In Progress","Đang làm","Done","Hoàn thành",'Use Case Tracker'!H20)) -> Chưa bắt đầu | J17: =IF('Use Case Tracker'!J20="","",'Use Case Tracker'!J20) -> BR-ROLE-01 | K17: =IFERROR(__xludf.DUMMYFUNCTION("IF('Use Case Tracker'!K20="""","""",IFERROR(GOOGLETRANSLATE('Use Case Tracker'!K20,""en"",""vi""),'Use Case Tracker'!K20))"),"") | L17: =IF('Use Case Tracker'!L20="","",SWITCH('Use Case Tracker'!L20,"Keep","Giữ trong scope","Could-have / Do after core","Có thể có / Làm sau core",'Use Case Tracker'!L20)) -> Giữ trong scope
A18: =IF('Use Case Tracker'!A21="","",'Use Case Tracker'!A21) -> UC20 | B18: =IFERROR(__xludf.DUMMYFUNCTION("IF('Use Case Tracker'!B21="""","""",IFERROR(GOOGLETRANSLATE('Use Case Tracker'!B21,""en"",""vi""),'Use Case Tracker'!B21))"),"Xem danh sách và thông tin chi tiết các thành viên gia đình") -> Xem danh sách và thông tin chi tiết các thành viên gia đình | C18: =IFERROR(__xludf.DUMMYFUNCTION("IF('Use Case Tracker'!C21="""","""",IFERROR(GOOGLETRANSLATE('Use Case Tracker'!C21,""en"",""vi""),'Use Case Tracker'!C21))"),"Luồng 2") -> Luồng 2 | D18: =IFERROR(__xludf.DUMMYFUNCTION("IF('Use Case Tracker'!D21="""","""",IFERROR(GOOGLETRANSLATE('Use Case Tracker'!D21,""en"",""vi""),'Use Case Tracker'!D21))"),"Gia đình") -> Gia đình | E18: =IFERROR(__xludf.DUMMYFUNCTION("IF('Use Case Tracker'!E21="""","""",IFERROR(GOOGLETRANSLATE('Use Case Tracker'!E21,""en"",""vi""),'Use Case Tracker'!E21))"),"Quản lý gia đình") -> Quản lý gia đình | F18: =IFERROR(__xludf.DUMMYFUNCTION("IF('Use Case Tracker'!F21="""","""",IFERROR(GOOGLETRANSLATE('Use Case Tracker'!F21,""en"",""vi""),'Use Case Tracker'!F21))"),"Xem danh sách và thông tin chi tiết các thành viên gia đình") -> Xem danh sách và thông tin chi tiết các thành viên gia đình | G18: =IF('Use Case Tracker'!G21="","",SWITCH('Use Case Tracker'!G21,"Must-have","Bắt buộc","Should-have","Nên có","Could-have","Có thể có",'Use Case Tracker'!G21)) -> Bắt buộc | H18: =IF('Use Case Tracker'!H21="","",SWITCH('Use Case Tracker'!H21,"Not Started","Chưa bắt đầu","In Progress","Đang làm","Done","Hoàn thành",'Use Case Tracker'!H21)) -> Chưa bắt đầu | J18: =IF('Use Case Tracker'!J21="","",'Use Case Tracker'!J21) -> BR-ROLE-03, BR-ROLE-04 | K18: =IFERROR(__xludf.DUMMYFUNCTION("IF('Use Case Tracker'!K21="""","""",IFERROR(GOOGLETRANSLATE('Use Case Tracker'!K21,""en"",""vi""),'Use Case Tracker'!K21))"),"") | L18: =IF('Use Case Tracker'!L21="","",SWITCH('Use Case Tracker'!L21,"Keep","Giữ trong scope","Could-have / Do after core","Có thể có / Làm sau core",'Use Case Tracker'!L21)) -> Giữ trong scope
A19: =IF('Use Case Tracker'!A22="","",'Use Case Tracker'!A22) -> UC21 | B19: =IFERROR(__xludf.DUMMYFUNCTION("IF('Use Case Tracker'!B22="""","""",IFERROR(GOOGLETRANSLATE('Use Case Tracker'!B22,""en"",""vi""),'Use Case Tracker'!B22))"),"Xem tóm tắt hồ sơ tài chính của thành viên") -> Xem tóm tắt hồ sơ tài chính của thành viên | C19: =IFERROR(__xludf.DUMMYFUNCTION("IF('Use Case Tracker'!C22="""","""",IFERROR(GOOGLETRANSLATE('Use Case Tracker'!C22,""en"",""vi""),'Use Case Tracker'!C22))"),"Luồng 3") -> Luồng 3 | D19: =IFERROR(__xludf.DUMMYFUNCTION("IF('Use Case Tracker'!D22="""","""",IFERROR(GOOGLETRANSLATE('Use Case Tracker'!D22,""en"",""vi""),'Use Case Tracker'!D22))"),"Tài chính") -> Tài chính | E19: =IFERROR(__xludf.DUMMYFUNCTION("IF('Use Case Tracker'!E22="""","""",IFERROR(GOOGLETRANSLATE('Use Case Tracker'!E22,""en"",""vi""),'Use Case Tracker'!E22))"),"Quản lý gia đình") -> Quản lý gia đình | F19: =IFERROR(__xludf.DUMMYFUNCTION("IF('Use Case Tracker'!F22="""","""",IFERROR(GOOGLETRANSLATE('Use Case Tracker'!F22,""en"",""vi""),'Use Case Tracker'!F22))"),"Xem tóm tắt hồ sơ tài chính của thành viên, chẳng hạn như tình trạng thu nhập và dữ liệu lập kế hoạch tổng hợp dựa trên quyền hạn; Theo mặc định, Family Manager không trực tiếp chỉnh sửa thu nhập/chi phí cá nhân của từng thành viên.") -> Xem tóm tắt hồ sơ tài chính của thành viên, chẳng hạn như tình trạng thu nhập và dữ liệu lập kế hoạch tổng hợp dựa trên quyền hạn; Theo mặc định, Family Manager không trực tiếp chỉnh sửa thu nhập/chi phí cá nhân của từng thành viên. | G19: =IF('Use Case Tracker'!G22="","",SWITCH('Use Case Tracker'!G22,"Must-have","Bắt buộc","Should-have","Nên có","Could-have","Có thể có",'Use Case Tracker'!G22)) -> Bắt buộc | H19: =IF('Use Case Tracker'!H22="","",SWITCH('Use Case Tracker'!H22,"Not Started","Chưa bắt đầu","In Progress","Đang làm","Done","Hoàn thành",'Use Case Tracker'!H22)) -> Chưa bắt đầu | J19: =IF('Use Case Tracker'!J22="","",'Use Case Tracker'!J22) -> BR-FIN-05, BR-FIN-06 | K19: =IFERROR(__xludf.DUMMYFUNCTION("IF('Use Case Tracker'!K22="""","""",IFERROR(GOOGLETRANSLATE('Use Case Tracker'!K22,""en"",""vi""),'Use Case Tracker'!K22))"),"Người quản lý xem bản tóm tắt để lập kế hoạch, không có quyền kiểm soát trực tiếp dữ liệu cá nhân.") -> Người quản lý xem bản tóm tắt để lập kế hoạch, không có quyền kiểm soát trực tiếp dữ liệu cá nhân. | L19: =IF('Use Case Tracker'!L22="","",SWITCH('Use Case Tracker'!L22,"Keep","Giữ trong scope","Could-have / Do after core","Có thể có / Làm sau core",'Use Case Tracker'!L22)) -> Giữ trong scope
A20: =IF('Use Case Tracker'!A23="","",'Use Case Tracker'!A23) -> UC22 | B20: =IFERROR(__xludf.DUMMYFUNCTION("IF('Use Case Tracker'!B23="""","""",IFERROR(GOOGLETRANSLATE('Use Case Tracker'!B23,""en"",""vi""),'Use Case Tracker'!B23))"),"Thiết lập thu nhập và chi tiêu cá nhân") -> Thiết lập thu nhập và chi tiêu cá nhân | C20: =IFERROR(__xludf.DUMMYFUNCTION("IF('Use Case Tracker'!C23="""","""",IFERROR(GOOGLETRANSLATE('Use Case Tracker'!C23,""en"",""vi""),'Use Case Tracker'!C23))"),"Luồng 3") -> Luồng 3 | D20: =IFERROR(__xludf.DUMMYFUNCTION("IF('Use Case Tracker'!D23="""","""",IFERROR(GOOGLETRANSLATE('Use Case Tracker'!D23,""en"",""vi""),'Use Case Tracker'!D23))"),"Tài chính") -> Tài chính | E20: =IFERROR(__xludf.DUMMYFUNCTION("IF('Use Case Tracker'!E23="""","""",IFERROR(GOOGLETRANSLATE('Use Case Tracker'!E23,""en"",""vi""),'Use Case Tracker'!E23))"),"Thành viên gia đình") -> Thành viên gia đình | F20: =IFERROR(__xludf.DUMMYFUNCTION("IF('Use Case Tracker'!F23="""","""",IFERROR(GOOGLETRANSLATE('Use Case Tracker'!F23,""en"",""vi""),'Use Case Tracker'!F23))"),"Thành viên gia đình thiết lập hoặc cập nhật trạng thái thu nhập cá nhân, thu nhập dự kiến, thu nhập thực tế, chi phí cá nhân dự kiến ​​và chi phí cá nhân thực tế.") -> Thành viên gia đình thiết lập hoặc cập nhật trạng thái thu nhập cá nhân, thu nhập dự kiến, thu nhập thực tế, chi phí cá nhân dự kiến ​​và chi phí cá nhân thực tế. | G20: =IF('Use Case Tracker'!G23="","",SWITCH('Use Case Tracker'!G23,"Must-have","Bắt buộc","Should-have","Nên có","Could-have","Có thể có",'Use Case Tracker'!G23)) -> Bắt buộc | H20: =IF('Use Case Tracker'!H23="","",SWITCH('Use Case Tracker'!H23,"Not Started","Chưa bắt đầu","In Progress","Đang làm","Done","Hoàn thành",'Use Case Tracker'!H23)) -> Chưa bắt đầu | J20: =IF('Use Case Tracker'!J23="","",'Use Case Tracker'!J23) -> BR-FIN-05, BR-FIN-06, BR-AUTH-02 | K20: =IFERROR(__xludf.DUMMYFUNCTION("IF('Use Case Tracker'!K23="""","""",IFERROR(GOOGLETRANSLATE('Use Case Tracker'!K23,""en"",""vi""),'Use Case Tracker'!K23))"),"Mỗi thành viên đều sở hữu bản kê khai tài chính cá nhân của riêng mình.") -> Mỗi thành viên đều sở hữu bản kê khai tài chính cá nhân của riêng mình. | L20: =IF('Use Case Tracker'!L23="","",SWITCH('Use Case Tracker'!L23,"Keep","Giữ trong scope","Could-have / Do after core","Có thể có / Làm sau core",'Use Case Tracker'!L23)) -> Giữ trong scope
A21: =IF('Use Case Tracker'!A24="","",'Use Case Tracker'!A24) -> UC23 | B21: =IFERROR(__xludf.DUMMYFUNCTION("IF('Use Case Tracker'!B24="""","""",IFERROR(GOOGLETRANSLATE('Use Case Tracker'!B24,""en"",""vi""),'Use Case Tracker'!B24))"),"Quản lý các danh mục chi phí chung") -> Quản lý các danh mục chi phí chung | C21: =IFERROR(__xludf.DUMMYFUNCTION("IF('Use Case Tracker'!C24="""","""",IFERROR(GOOGLETRANSLATE('Use Case Tracker'!C24,""en"",""vi""),'Use Case Tracker'!C24))"),"Luồng 3") -> Luồng 3 | D21: =IFERROR(__xludf.DUMMYFUNCTION("IF('Use Case Tracker'!D24="""","""",IFERROR(GOOGLETRANSLATE('Use Case Tracker'!D24,""en"",""vi""),'Use Case Tracker'!D24))"),"Tài chính") -> Tài chính | E21: =IFERROR(__xludf.DUMMYFUNCTION("IF('Use Case Tracker'!E24="""","""",IFERROR(GOOGLETRANSLATE('Use Case Tracker'!E24,""en"",""vi""),'Use Case Tracker'!E24))"),"Người quản lý gia đình / Thành viên gia đình được ủy quyền thay mặt") -> Người quản lý gia đình / Thành viên gia đình được ủy quyền thay mặt | F21: =IFERROR(__xludf.DUMMYFUNCTION("IF('Use Case Tracker'!F24="""","""",IFERROR(GOOGLETRANSLATE('Use Case Tracker'!F24,""en"",""vi""),'Use Case Tracker'!F24))"),"Quản lý các khoản chi tiêu chung của gia đình như tiền thuê nhà, điện, nước, thực phẩm và học phí.") -> Quản lý các khoản chi tiêu chung của gia đình như tiền thuê nhà, điện, nước, thực phẩm và học phí. | G21: =IF('Use Case Tracker'!G24="","",SWITCH('Use Case Tracker'!G24,"Must-have","Bắt buộc","Should-have","Nên có","Could-have","Có thể có",'Use Case Tracker'!G24)) -> Nên có | H21: =IF('Use Case Tracker'!H24="","",SWITCH('Use Case Tracker'!H24,"Not Started","Chưa bắt đầu","In Progress","Đang làm","Done","Hoàn thành",'Use Case Tracker'!H24)) -> Chưa bắt đầu | J21: =IF('Use Case Tracker'!J24="","",'Use Case Tracker'!J24) -> BR-FIN-05 | K21: =IFERROR(__xludf.DUMMYFUNCTION("IF('Use Case Tracker'!K24="""","""",IFERROR(GOOGLETRANSLATE('Use Case Tracker'!K24,""en"",""vi""),'Use Case Tracker'!K24))"),"Các danh mục được chia sẻ là ở cấp độ gia đình, không phải riêng tư của từng thành viên.") -> Các danh mục được chia sẻ là ở cấp độ gia đình, không phải riêng tư của từng thành viên. | L21: =IF('Use Case Tracker'!L24="","",SWITCH('Use Case Tracker'!L24,"Keep","Giữ trong scope","Could-have / Do after core","Có thể có / Làm sau core",'Use Case Tracker'!L24)) -> Giữ trong scope
A22: =IF('Use Case Tracker'!A25="","",'Use Case Tracker'!A25) -> UC24 | B22: =IFERROR(__xludf.DUMMYFUNCTION("IF('Use Case Tracker'!B25="""","""",IFERROR(GOOGLETRANSLATE('Use Case Tracker'!B25,""en"",""vi""),'Use Case Tracker'!B25))"),"Xác định thu nhập/quỹ chung dự kiến ​​của gia đình.") -> Xác định thu nhập/quỹ chung dự kiến ​​của gia đình. | C22: =IFERROR(__xludf.DUMMYFUNCTION("IF('Use Case Tracker'!C25="""","""",IFERROR(GOOGLETRANSLATE('Use Case Tracker'!C25,""en"",""vi""),'Use Case Tracker'!C25))"),"Luồng 3") -> Luồng 3 | D22: =IFERROR(__xludf.DUMMYFUNCTION("IF('Use Case Tracker'!D25="""","""",IFERROR(GOOGLETRANSLATE('Use Case Tracker'!D25,""en"",""vi""),'Use Case Tracker'!D25))"),"Tài chính") -> Tài chính | E22: =IFERROR(__xludf.DUMMYFUNCTION("IF('Use Case Tracker'!E25="""","""",IFERROR(GOOGLETRANSLATE('Use Case Tracker'!E25,""en"",""vi""),'Use Case Tracker'!E25))"),"Quản lý gia đình") -> Quản lý gia đình | F22: =IFERROR(__xludf.DUMMYFUNCTION("IF('Use Case Tracker'!F25="""","""",IFERROR(GOOGLETRANSLATE('Use Case Tracker'!F25,""en"",""vi""),'Use Case Tracker'!F25))"),"Đặt ra các giá trị dự kiến ​​về thu nhập chung của gia đình hoặc kế hoạch quỹ gia đình, không bao gồm thu nhập cá nhân mà các thành viên tự khai báo.") -> Đặt ra các giá trị dự kiến ​​về thu nhập chung của gia đình hoặc kế hoạch quỹ gia đình, không bao gồm thu nhập cá nhân mà các thành viên tự khai báo. | G22: =IF('Use Case Tracker'!G25="","",SWITCH('Use Case Tracker'!G25,"Must-have","Bắt buộc","Should-have","Nên có","Could-have","Có thể có",'Use Case Tracker'!G25)) -> Bắt buộc | H22: =IF('Use Case Tracker'!H25="","",SWITCH('Use Case Tracker'!H25,"Not Started","Chưa bắt đầu","In Progress","Đang làm","Done","Hoàn thành",'Use Case Tracker'!H25)) -> Chưa bắt đầu | J22: =IF('Use Case Tracker'!J25="","",'Use Case Tracker'!J25) -> BR-FIN-05, BR-FIN-06 | K22: =IFERROR(__xludf.DUMMYFUNCTION("IF('Use Case Tracker'!K25="""","""",IFERROR(GOOGLETRANSLATE('Use Case Tracker'!K25,""en"",""vi""),'Use Case Tracker'!K25))"),"Sử dụng cho quỹ chung, đóng góp chung hoặc lập kế hoạch thu nhập gia đình.") -> Sử dụng cho quỹ chung, đóng góp chung hoặc lập kế hoạch thu nhập gia đình. | L22: =IF('Use Case Tracker'!L25="","",SWITCH('Use Case Tracker'!L25,"Keep","Giữ trong scope","Could-have / Do after core","Có thể có / Làm sau core",'Use Case Tracker'!L25)) -> Giữ trong scope
A23: =IF('Use Case Tracker'!A26="","",'Use Case Tracker'!A26) -> UC25 | B23: =IFERROR(__xludf.DUMMYFUNCTION("IF('Use Case Tracker'!B26="""","""",IFERROR(GOOGLETRANSLATE('Use Case Tracker'!B26,""en"",""vi""),'Use Case Tracker'!B26))"),"Xác định các khoản chi tiêu chung dự kiến ​​của gia đình.") -> Xác định các khoản chi tiêu chung dự kiến ​​của gia đình. | C23: =IFERROR(__xludf.DUMMYFUNCTION("IF('Use Case Tracker'!C26="""","""",IFERROR(GOOGLETRANSLATE('Use Case Tracker'!C26,""en"",""vi""),'Use Case Tracker'!C26))"),"Luồng 3") -> Luồng 3 | D23: =IFERROR(__xludf.DUMMYFUNCTION("IF('Use Case Tracker'!D26="""","""",IFERROR(GOOGLETRANSLATE('Use Case Tracker'!D26,""en"",""vi""),'Use Case Tracker'!D26))"),"Tài chính") -> Tài chính | E23: =IFERROR(__xludf.DUMMYFUNCTION("IF('Use Case Tracker'!E26="""","""",IFERROR(GOOGLETRANSLATE('Use Case Tracker'!E26,""en"",""vi""),'Use Case Tracker'!E26))"),"Quản lý gia đình") -> Quản lý gia đình | F23: =IFERROR(__xludf.DUMMYFUNCTION("IF('Use Case Tracker'!F26="""","""",IFERROR(GOOGLETRANSLATE('Use Case Tracker'!F26,""en"",""vi""),'Use Case Tracker'!F26))"),"Xác định các khoản chi tiêu chung dự kiến ​​của gia đình như tiền thuê nhà, tiền điện nước, tiền ăn, học phí hoặc các chi phí sinh hoạt chung khác.") -> Xác định các khoản chi tiêu chung dự kiến ​​của gia đình như tiền thuê nhà, tiền điện nước, tiền ăn, học phí hoặc các chi phí sinh hoạt chung khác. | G23: =IF('Use Case Tracker'!G26="","",SWITCH('Use Case Tracker'!G26,"Must-have","Bắt buộc","Should-have","Nên có","Could-have","Có thể có",'Use Case Tracker'!G26)) -> Bắt buộc | H23: =IF('Use Case Tracker'!H26="","",SWITCH('Use Case Tracker'!H26,"Not Started","Chưa bắt đầu","In Progress","Đang làm","Done","Hoàn thành",'Use Case Tracker'!H26)) -> Chưa bắt đầu | J23: =IF('Use Case Tracker'!J26="","",'Use Case Tracker'!J26) -> BR-FIN-05 | K23: =IFERROR(__xludf.DUMMYFUNCTION("IF('Use Case Tracker'!K26="""","""",IFERROR(GOOGLETRANSLATE('Use Case Tracker'!K26,""en"",""vi""),'Use Case Tracker'!K26))"),"Người quản lý kiểm soát các khoản chi tiêu chung của gia đình.") -> Người quản lý kiểm soát các khoản chi tiêu chung của gia đình. | L23: =IF('Use Case Tracker'!L26="","",SWITCH('Use Case Tracker'!L26,"Keep","Giữ trong scope","Could-have / Do after core","Có thể có / Làm sau core",'Use Case Tracker'!L26)) -> Giữ trong scope
A24: =IF('Use Case Tracker'!A27="","",'Use Case Tracker'!A27) -> UC26 | B24: =IFERROR(__xludf.DUMMYFUNCTION("IF('Use Case Tracker'!B27="""","""",IFERROR(GOOGLETRANSLATE('Use Case Tracker'!B27,""en"",""vi""),'Use Case Tracker'!B27))"),"Xem ngân sách gia đình theo kế hoạch") -> Xem ngân sách gia đình theo kế hoạch | C24: =IFERROR(__xludf.DUMMYFUNCTION("IF('Use Case Tracker'!C27="""","""",IFERROR(GOOGLETRANSLATE('Use Case Tracker'!C27,""en"",""vi""),'Use Case Tracker'!C27))"),"Luồng 3") -> Luồng 3 | D24: =IFERROR(__xludf.DUMMYFUNCTION("IF('Use Case Tracker'!D27="""","""",IFERROR(GOOGLETRANSLATE('Use Case Tracker'!D27,""en"",""vi""),'Use Case Tracker'!D27))"),"Tài chính") -> Tài chính | E24: =IFERROR(__xludf.DUMMYFUNCTION("IF('Use Case Tracker'!E27="""","""",IFERROR(GOOGLETRANSLATE('Use Case Tracker'!E27,""en"",""vi""),'Use Case Tracker'!E27))"),"Quản lý gia đình") -> Quản lý gia đình | F24: =IFERROR(__xludf.DUMMYFUNCTION("IF('Use Case Tracker'!F27="""","""",IFERROR(GOOGLETRANSLATE('Use Case Tracker'!F27,""en"",""vi""),'Use Case Tracker'!F27))"),"Xem ngân sách gia đình dự kiến ​​được tính toán dựa trên thu nhập/chi tiêu cá nhân do thành viên khai báo và thu nhập/chi tiêu chung của gia đình do người quản lý xác định.") -> Xem ngân sách gia đình dự kiến ​​được tính toán dựa trên thu nhập/chi tiêu cá nhân do thành viên khai báo và thu nhập/chi tiêu chung của gia đình do người quản lý xác định. | G24: =IF('Use Case Tracker'!G27="","",SWITCH('Use Case Tracker'!G27,"Must-have","Bắt buộc","Should-have","Nên có","Could-have","Có thể có",'Use Case Tracker'!G27)) -> Bắt buộc | H24: =IF('Use Case Tracker'!H27="","",SWITCH('Use Case Tracker'!H27,"Not Started","Chưa bắt đầu","In Progress","Đang làm","Done","Hoàn thành",'Use Case Tracker'!H27)) -> Chưa bắt đầu | J24: =IF('Use Case Tracker'!J27="","",'Use Case Tracker'!J27) -> BR-FIN-05, BR-FIN-06 | K24: =IFERROR(__xludf.DUMMYFUNCTION("IF('Use Case Tracker'!K27="""","""",IFERROR(GOOGLETRANSLATE('Use Case Tracker'!K27,""en"",""vi""),'Use Case Tracker'!K27))"),"Hãy tôn trọng quyền riêng tư/sự cho phép khi hiển thị thông tin chi tiết.") -> Hãy tôn trọng quyền riêng tư/sự cho phép khi hiển thị thông tin chi tiết. | L24: =IF('Use Case Tracker'!L27="","",SWITCH('Use Case Tracker'!L27,"Keep","Giữ trong scope","Could-have / Do after core","Có thể có / Làm sau core",'Use Case Tracker'!L27)) -> Giữ trong scope
A25: =IF('Use Case Tracker'!A28="","",'Use Case Tracker'!A28) -> UC27 | B25: =IFERROR(__xludf.DUMMYFUNCTION("IF('Use Case Tracker'!B28="""","""",IFERROR(GOOGLETRANSLATE('Use Case Tracker'!B28,""en"",""vi""),'Use Case Tracker'!B28))"),"Ghi chép thu nhập và chi phí cá nhân thực tế") -> Ghi chép thu nhập và chi phí cá nhân thực tế | C25: =IFERROR(__xludf.DUMMYFUNCTION("IF('Use Case Tracker'!C28="""","""",IFERROR(GOOGLETRANSLATE('Use Case Tracker'!C28,""en"",""vi""),'Use Case Tracker'!C28))"),"Luồng 3") -> Luồng 3 | D25: =IFERROR(__xludf.DUMMYFUNCTION("IF('Use Case Tracker'!D28="""","""",IFERROR(GOOGLETRANSLATE('Use Case Tracker'!D28,""en"",""vi""),'Use Case Tracker'!D28))"),"Tài chính") -> Tài chính | E25: =IFERROR(__xludf.DUMMYFUNCTION("IF('Use Case Tracker'!E28="""","""",IFERROR(GOOGLETRANSLATE('Use Case Tracker'!E28,""en"",""vi""),'Use Case Tracker'!E28))"),"Thành viên gia đình") -> Thành viên gia đình | F25: =IFERROR(__xludf.DUMMYFUNCTION("IF('Use Case Tracker'!F28="""","""",IFERROR(GOOGLETRANSLATE('Use Case Tracker'!F28,""en"",""vi""),'Use Case Tracker'!F28))"),"Thành viên gia đình ghi lại thu nhập và chi tiêu cá nhân thực tế để theo dõi tài chính cá nhân nếu được phép.") -> Thành viên gia đình ghi lại thu nhập và chi tiêu cá nhân thực tế để theo dõi tài chính cá nhân nếu được phép. | G25: =IF('Use Case Tracker'!G28="","",SWITCH('Use Case Tracker'!G28,"Must-have","Bắt buộc","Should-have","Nên có","Could-have","Có thể có",'Use Case Tracker'!G28)) -> Bắt buộc | H25: =IF('Use Case Tracker'!H28="","",SWITCH('Use Case Tracker'!H28,"Not Started","Chưa bắt đầu","In Progress","Đang làm","Done","Hoàn thành",'Use Case Tracker'!H28)) -> Chưa bắt đầu | J25: =IF('Use Case Tracker'!J28="","",'Use Case Tracker'!J28) -> BR-FIN-05, BR-FIN-06 | K25: =IFERROR(__xludf.DUMMYFUNCTION("IF('Use Case Tracker'!K28="""","""",IFERROR(GOOGLETRANSLATE('Use Case Tracker'!K28,""en"",""vi""),'Use Case Tracker'!K28))"),"Phạm vi tài chính cốt lõi sau Đánh giá 1: lập kế hoạch ngân sách, theo dõi chi tiêu thực tế, so sánh kế hoạch với thực tế và cảnh báo ngân sách.") -> Phạm vi tài chính cốt lõi sau Đánh giá 1: lập kế hoạch ngân sách, theo dõi chi tiêu thực tế, so sánh kế hoạch với thực tế và cảnh báo ngân sách. | L25: =IF('Use Case Tracker'!L28="","",SWITCH('Use Case Tracker'!L28,"Keep","Giữ trong scope","Could-have / Do after core","Có thể có / Làm sau core",'Use Case Tracker'!L28)) -> Giữ trong scope
A26: =IF('Use Case Tracker'!A29="","",'Use Case Tracker'!A29) -> UC28 | B26: =IFERROR(__xludf.DUMMYFUNCTION("IF('Use Case Tracker'!B29="""","""",IFERROR(GOOGLETRANSLATE('Use Case Tracker'!B29,""en"",""vi""),'Use Case Tracker'!B29))"),"Ghi lại chi phí thực tế chung của gia đình") -> Ghi lại chi phí thực tế chung của gia đình | C26: =IFERROR(__xludf.DUMMYFUNCTION("IF('Use Case Tracker'!C29="""","""",IFERROR(GOOGLETRANSLATE('Use Case Tracker'!C29,""en"",""vi""),'Use Case Tracker'!C29))"),"Luồng 3") -> Luồng 3 | D26: =IFERROR(__xludf.DUMMYFUNCTION("IF('Use Case Tracker'!D29="""","""",IFERROR(GOOGLETRANSLATE('Use Case Tracker'!D29,""en"",""vi""),'Use Case Tracker'!D29))"),"Tài chính") -> Tài chính | E26: =IFERROR(__xludf.DUMMYFUNCTION("IF('Use Case Tracker'!E29="""","""",IFERROR(GOOGLETRANSLATE('Use Case Tracker'!E29,""en"",""vi""),'Use Case Tracker'!E29))"),"Người quản lý gia đình / Thành viên gia đình được ủy quyền thay mặt") -> Người quản lý gia đình / Thành viên gia đình được ủy quyền thay mặt | F26: =IFERROR(__xludf.DUMMYFUNCTION("IF('Use Case Tracker'!F29="""","""",IFERROR(GOOGLETRANSLATE('Use Case Tracker'!F29,""en"",""vi""),'Use Case Tracker'!F29))"),"Ghi lại các khoản chi tiêu chung thực tế của gia đình vào sổ quỹ gia đình để theo dõi/báo cáo so sánh kế hoạch và thực tế. Hệ thống không giữ hoặc thanh toán tiền thật.") -> Ghi lại các khoản chi tiêu chung thực tế của gia đình vào sổ quỹ gia đình để theo dõi/báo cáo so sánh kế hoạch và thực tế. Hệ thống không giữ hoặc thanh toán tiền thật. | G26: =IF('Use Case Tracker'!G29="","",SWITCH('Use Case Tracker'!G29,"Must-have","Bắt buộc","Should-have","Nên có","Could-have","Có thể có",'Use Case Tracker'!G29)) -> Bắt buộc | H26: =IF('Use Case Tracker'!H29="","",SWITCH('Use Case Tracker'!H29,"Not Started","Chưa bắt đầu","In Progress","Đang làm","Done","Hoàn thành",'Use Case Tracker'!H29)) -> Chưa bắt đầu | J26: =IF('Use Case Tracker'!J29="","",'Use Case Tracker'!J29) -> BR-FIN-01, BR-FIN-04, BR-FIN-07 | K26: =IFERROR(__xludf.DUMMYFUNCTION("IF('Use Case Tracker'!K29="""","""",IFERROR(GOOGLETRANSLATE('Use Case Tracker'!K29,""en"",""vi""),'Use Case Tracker'!K29))"),"Các khoản chi phí thực tế được chia sẻ chỉ được ghi vào sổ quỹ gia đình; hệ thống không nắm giữ tiền mặt thực tế nào.") -> Các khoản chi phí thực tế được chia sẻ chỉ được ghi vào sổ quỹ gia đình; hệ thống không nắm giữ tiền mặt thực tế nào. | L26: =IF('Use Case Tracker'!L29="","",SWITCH('Use Case Tracker'!L29,"Keep","Giữ trong scope","Could-have / Do after core","Có thể có / Làm sau core",'Use Case Tracker'!L29)) -> Giữ trong scope
A27: =IF('Use Case Tracker'!A30="","",'Use Case Tracker'!A30) -> UC29 | B27: =IFERROR(__xludf.DUMMYFUNCTION("IF('Use Case Tracker'!B30="""","""",IFERROR(GOOGLETRANSLATE('Use Case Tracker'!B30,""en"",""vi""),'Use Case Tracker'!B30))"),"Xem báo cáo tài chính và quỹ gia đình thực tế") -> Xem báo cáo tài chính và quỹ gia đình thực tế | C27: =IFERROR(__xludf.DUMMYFUNCTION("IF('Use Case Tracker'!C30="""","""",IFERROR(GOOGLETRANSLATE('Use Case Tracker'!C30,""en"",""vi""),'Use Case Tracker'!C30))"),"Luồng 3") -> Luồng 3 | D27: =IFERROR(__xludf.DUMMYFUNCTION("IF('Use Case Tracker'!D30="""","""",IFERROR(GOOGLETRANSLATE('Use Case Tracker'!D30,""en"",""vi""),'Use Case Tracker'!D30))"),"Tài chính") -> Tài chính | E27: =IFERROR(__xludf.DUMMYFUNCTION("IF('Use Case Tracker'!E30="""","""",IFERROR(GOOGLETRANSLATE('Use Case Tracker'!E30,""en"",""vi""),'Use Case Tracker'!E30))"),"Người quản lý gia đình / Thành viên gia đình được ủy quyền thay mặt") -> Người quản lý gia đình / Thành viên gia đình được ủy quyền thay mặt | F27: =IFERROR(__xludf.DUMMYFUNCTION("IF('Use Case Tracker'!F30="""","""",IFERROR(GOOGLETRANSLATE('Use Case Tracker'!F30,""en"",""vi""),'Use Case Tracker'!F30))"),"Xem tình hình tài chính chung thực tế, số dư quỹ gia đình và so sánh giữa kế hoạch và thực tế; thông tin cá nhân chỉ được hiển thị theo quy định về quyền riêng tư/quyền cho phép.") -> Xem tình hình tài chính chung thực tế, số dư quỹ gia đình và so sánh giữa kế hoạch và thực tế; thông tin cá nhân chỉ được hiển thị theo quy định về quyền riêng tư/quyền cho phép. | G27: =IF('Use Case Tracker'!G30="","",SWITCH('Use Case Tracker'!G30,"Must-have","Bắt buộc","Should-have","Nên có","Could-have","Có thể có",'Use Case Tracker'!G30)) -> Bắt buộc | H27: =IF('Use Case Tracker'!H30="","",SWITCH('Use Case Tracker'!H30,"Not Started","Chưa bắt đầu","In Progress","Đang làm","Done","Hoàn thành",'Use Case Tracker'!H30)) -> Chưa bắt đầu | J27: =IF('Use Case Tracker'!J30="","",'Use Case Tracker'!J30) -> BR-FIN-01, BR-FIN-05, BR-FIN-06, BR-FIN-07 | K27: =IFERROR(__xludf.DUMMYFUNCTION("IF('Use Case Tracker'!K30="""","""",IFERROR(GOOGLETRANSLATE('Use Case Tracker'!K30,""en"",""vi""),'Use Case Tracker'!K30))"),"Báo cáo tập trung vào so sánh kế hoạch với thực tế, số dư sổ cái quỹ và tóm tắt tài chính đảm bảo tính bảo mật.") -> Báo cáo tập trung vào so sánh kế hoạch với thực tế, số dư sổ cái quỹ và tóm tắt tài chính đảm bảo tính bảo mật. | L27: =IF('Use Case Tracker'!L30="","",SWITCH('Use Case Tracker'!L30,"Keep","Giữ trong scope","Could-have / Do after core","Có thể có / Làm sau core",'Use Case Tracker'!L30)) -> Giữ trong scope
A28: =IF('Use Case Tracker'!A31="","",'Use Case Tracker'!A31) -> UC30 | B28: =IFERROR(__xludf.DUMMYFUNCTION("IF('Use Case Tracker'!B31="""","""",IFERROR(GOOGLETRANSLATE('Use Case Tracker'!B31,""en"",""vi""),'Use Case Tracker'!B31))"),"Xem cảnh báo ngân sách") -> Xem cảnh báo ngân sách | C28: =IFERROR(__xludf.DUMMYFUNCTION("IF('Use Case Tracker'!C31="""","""",IFERROR(GOOGLETRANSLATE('Use Case Tracker'!C31,""en"",""vi""),'Use Case Tracker'!C31))"),"Luồng 3") -> Luồng 3 | D28: =IFERROR(__xludf.DUMMYFUNCTION("IF('Use Case Tracker'!D31="""","""",IFERROR(GOOGLETRANSLATE('Use Case Tracker'!D31,""en"",""vi""),'Use Case Tracker'!D31))"),"Tài chính") -> Tài chính | E28: =IFERROR(__xludf.DUMMYFUNCTION("IF('Use Case Tracker'!E31="""","""",IFERROR(GOOGLETRANSLATE('Use Case Tracker'!E31,""en"",""vi""),'Use Case Tracker'!E31))"),"Người quản lý gia đình / Thành viên gia đình được ủy quyền thay mặt") -> Người quản lý gia đình / Thành viên gia đình được ủy quyền thay mặt | F28: =IFERROR(__xludf.DUMMYFUNCTION("IF('Use Case Tracker'!F31="""","""",IFERROR(GOOGLETRANSLATE('Use Case Tracker'!F31,""en"",""vi""),'Use Case Tracker'!F31))"),"Nhận thông báo khi chi phí chung thực tế vượt quá kế hoạch hoặc quỹ gia đình có nguy cơ thiếu hụt.") -> Nhận thông báo khi chi phí chung thực tế vượt quá kế hoạch hoặc quỹ gia đình có nguy cơ thiếu hụt. | G28: =IF('Use Case Tracker'!G31="","",SWITCH('Use Case Tracker'!G31,"Must-have","Bắt buộc","Should-have","Nên có","Could-have","Có thể có",'Use Case Tracker'!G31)) -> Bắt buộc | H28: =IF('Use Case Tracker'!H31="","",SWITCH('Use Case Tracker'!H31,"Not Started","Chưa bắt đầu","In Progress","Đang làm","Done","Hoàn thành",'Use Case Tracker'!H31)) -> Chưa bắt đầu | J28: =IF('Use Case Tracker'!J31="","",'Use Case Tracker'!J31) -> BR-FIN-05, BR-FIN-06 | K28: =IFERROR(__xludf.DUMMYFUNCTION("IF('Use Case Tracker'!K31="""","""",IFERROR(GOOGLETRANSLATE('Use Case Tracker'!K31,""en"",""vi""),'Use Case Tracker'!K31))"),"Các cảnh báo về ngân sách là một phần giá trị tài chính cốt lõi sau Đánh giá 1.") -> Các cảnh báo về ngân sách là một phần giá trị tài chính cốt lõi sau Đánh giá 1. | L28: =IF('Use Case Tracker'!L31="","",SWITCH('Use Case Tracker'!L31,"Keep","Giữ trong scope","Could-have / Do after core","Có thể có / Làm sau core",'Use Case Tracker'!L31)) -> Giữ trong scope
A29: =IF('Use Case Tracker'!A32="","",'Use Case Tracker'!A32) -> UC31 | B29: =IFERROR(__xludf.DUMMYFUNCTION("IF('Use Case Tracker'!B32="""","""",IFERROR(GOOGLETRANSLATE('Use Case Tracker'!B32,""en"",""vi""),'Use Case Tracker'!B32))"),"Quản lý sổ quỹ gia đình") -> Quản lý sổ quỹ gia đình | C29: =IFERROR(__xludf.DUMMYFUNCTION("IF('Use Case Tracker'!C32="""","""",IFERROR(GOOGLETRANSLATE('Use Case Tracker'!C32,""en"",""vi""),'Use Case Tracker'!C32))"),"Luồng 3") -> Luồng 3 | D29: =IFERROR(__xludf.DUMMYFUNCTION("IF('Use Case Tracker'!D32="""","""",IFERROR(GOOGLETRANSLATE('Use Case Tracker'!D32,""en"",""vi""),'Use Case Tracker'!D32))"),"Tài chính / Quỹ gia đình") -> Tài chính / Quỹ gia đình | E29: =IFERROR(__xludf.DUMMYFUNCTION("IF('Use Case Tracker'!E32="""","""",IFERROR(GOOGLETRANSLATE('Use Case Tracker'!E32,""en"",""vi""),'Use Case Tracker'!E32))"),"Người quản lý gia đình / Thành viên gia đình được ủy quyền thay mặt") -> Người quản lý gia đình / Thành viên gia đình được ủy quyền thay mặt | F29: =IFERROR(__xludf.DUMMYFUNCTION("IF('Use Case Tracker'!F32="""","""",IFERROR(GOOGLETRANSLATE('Use Case Tracker'!F32,""en"",""vi""),'Use Case Tracker'!F32))"),"Quản lý sổ sách kế toán nội bộ quỹ gia đình để theo dõi kế hoạch gia đình, tiền tiêu vặt và phần thưởng. Đây không phải là ví điện tử thực sự.") -> Quản lý sổ sách kế toán nội bộ quỹ gia đình để theo dõi kế hoạch gia đình, tiền tiêu vặt và phần thưởng. Đây không phải là ví điện tử thực sự. | G29: =IF('Use Case Tracker'!G32="","",SWITCH('Use Case Tracker'!G32,"Must-have","Bắt buộc","Should-have","Nên có","Could-have","Có thể có",'Use Case Tracker'!G32)) -> Bắt buộc | H29: =IF('Use Case Tracker'!H32="","",SWITCH('Use Case Tracker'!H32,"Not Started","Chưa bắt đầu","In Progress","Đang làm","Done","Hoàn thành",'Use Case Tracker'!H32)) -> Chưa bắt đầu | J29: =IF('Use Case Tracker'!J32="","",'Use Case Tracker'!J32) -> BR-FIN-01, BR-FIN-04, BR-FIN-07, BR-FIN-08 | K29: =IFERROR(__xludf.DUMMYFUNCTION("IF('Use Case Tracker'!K32="""","""",IFERROR(GOOGLETRANSLATE('Use Case Tracker'!K32,""en"",""vi""),'Use Case Tracker'!K32))"),"Điều này thay thế khái niệm nạp tiền vào ví cũ. Đây là một bản ghi sổ cái, không phải là một giao dịch thanh toán.") -> Điều này thay thế khái niệm nạp tiền vào ví cũ. Đây là một bản ghi sổ cái, không phải là một giao dịch thanh toán. | L29: =IF('Use Case Tracker'!L32="","",SWITCH('Use Case Tracker'!L32,"Keep","Giữ trong scope","Could-have / Do after core","Có thể có / Làm sau core",'Use Case Tracker'!L32)) -> Keep, standardized as internal ledger scope after Review 1
A30: =IF('Use Case Tracker'!A33="","",'Use Case Tracker'!A33) -> UC32 | B30: =IFERROR(__xludf.DUMMYFUNCTION("IF('Use Case Tracker'!B33="""","""",IFERROR(GOOGLETRANSLATE('Use Case Tracker'!B33,""en"",""vi""),'Use Case Tracker'!B33))"),"Ghi nhận khoản đóng góp vào Quỹ Gia đình") -> Ghi nhận khoản đóng góp vào Quỹ Gia đình | C30: =IFERROR(__xludf.DUMMYFUNCTION("IF('Use Case Tracker'!C33="""","""",IFERROR(GOOGLETRANSLATE('Use Case Tracker'!C33,""en"",""vi""),'Use Case Tracker'!C33))"),"Luồng 3") -> Luồng 3 | D30: =IFERROR(__xludf.DUMMYFUNCTION("IF('Use Case Tracker'!D33="""","""",IFERROR(GOOGLETRANSLATE('Use Case Tracker'!D33,""en"",""vi""),'Use Case Tracker'!D33))"),"Tài chính / Quỹ gia đình") -> Tài chính / Quỹ gia đình | E30: =IFERROR(__xludf.DUMMYFUNCTION("IF('Use Case Tracker'!E33="""","""",IFERROR(GOOGLETRANSLATE('Use Case Tracker'!E33,""en"",""vi""),'Use Case Tracker'!E33))"),"Người quản lý gia đình / Thành viên gia đình được ủy quyền thay mặt") -> Người quản lý gia đình / Thành viên gia đình được ủy quyền thay mặt | F30: =IFERROR(__xludf.DUMMYFUNCTION("IF('Use Case Tracker'!F33="""","""",IFERROR(GOOGLETRANSLATE('Use Case Tracker'!F33,""en"",""vi""),'Use Case Tracker'!F33))"),"Ghi nhận khoản đóng góp vào sổ cái quỹ gia đình chỉ nhằm mục đích lập kế hoạch và theo dõi.") -> Ghi nhận khoản đóng góp vào sổ cái quỹ gia đình chỉ nhằm mục đích lập kế hoạch và theo dõi. | G30: =IF('Use Case Tracker'!G33="","",SWITCH('Use Case Tracker'!G33,"Must-have","Bắt buộc","Should-have","Nên có","Could-have","Có thể có",'Use Case Tracker'!G33)) -> Bắt buộc | H30: =IF('Use Case Tracker'!H33="","",SWITCH('Use Case Tracker'!H33,"Not Started","Chưa bắt đầu","In Progress","Đang làm","Done","Hoàn thành",'Use Case Tracker'!H33)) -> Chưa bắt đầu | J30: =IF('Use Case Tracker'!J33="","",'Use Case Tracker'!J33) -> BR-FIN-01, BR-FIN-04, BR-FIN-07, BR-FIN-08 | K30: =IFERROR(__xludf.DUMMYFUNCTION("IF('Use Case Tracker'!K33="""","""",IFERROR(GOOGLETRANSLATE('Use Case Tracker'!K33,""en"",""vi""),'Use Case Tracker'!K33))"),"Mục này thay thế mục Ghi nhận khoản đóng góp vào Quỹ Gia đình. Đây là một bản ghi sổ cái, không phải là giao dịch thanh toán.") -> Mục này thay thế mục Ghi nhận khoản đóng góp vào Quỹ Gia đình. Đây là một bản ghi sổ cái, không phải là giao dịch thanh toán. | L30: =IF('Use Case Tracker'!L33="","",SWITCH('Use Case Tracker'!L33,"Keep","Giữ trong scope","Could-have / Do after core","Có thể có / Làm sau core",'Use Case Tracker'!L33)) -> Keep, standardized as internal ledger scope after Review 1
A31: =IF('Use Case Tracker'!A34="","",'Use Case Tracker'!A34) -> UC33 | B31: =IFERROR(__xludf.DUMMYFUNCTION("IF('Use Case Tracker'!B34="""","""",IFERROR(GOOGLETRANSLATE('Use Case Tracker'!B34,""en"",""vi""),'Use Case Tracker'!B34))"),"Phân bổ phụ cấp/thưởng nội bộ") -> Phân bổ phụ cấp/thưởng nội bộ | C31: =IFERROR(__xludf.DUMMYFUNCTION("IF('Use Case Tracker'!C34="""","""",IFERROR(GOOGLETRANSLATE('Use Case Tracker'!C34,""en"",""vi""),'Use Case Tracker'!C34))"),"Luồng 3") -> Luồng 3 | D31: =IFERROR(__xludf.DUMMYFUNCTION("IF('Use Case Tracker'!D34="""","""",IFERROR(GOOGLETRANSLATE('Use Case Tracker'!D34,""en"",""vi""),'Use Case Tracker'!D34))"),"Tài chính / Thưởng") -> Tài chính / Thưởng | E31: =IFERROR(__xludf.DUMMYFUNCTION("IF('Use Case Tracker'!E34="""","""",IFERROR(GOOGLETRANSLATE('Use Case Tracker'!E34,""en"",""vi""),'Use Case Tracker'!E34))"),"Người quản lý gia đình / Thành viên gia đình được ủy quyền thay mặt") -> Người quản lý gia đình / Thành viên gia đình được ủy quyền thay mặt | F31: =IFERROR(__xludf.DUMMYFUNCTION("IF('Use Case Tracker'!F34="""","""",IFERROR(GOOGLETRANSLATE('Use Case Tracker'!F34,""en"",""vi""),'Use Case Tracker'!F34))"),"Phân bổ khoản phụ cấp nội bộ hoặc phần thưởng nhiệm vụ cho một thành viên trong gia đình để theo dõi tiến độ.") -> Phân bổ khoản phụ cấp nội bộ hoặc phần thưởng nhiệm vụ cho một thành viên trong gia đình để theo dõi tiến độ. | G31: =IF('Use Case Tracker'!G34="","",SWITCH('Use Case Tracker'!G34,"Must-have","Bắt buộc","Should-have","Nên có","Could-have","Có thể có",'Use Case Tracker'!G34)) -> Bắt buộc | H31: =IF('Use Case Tracker'!H34="","",SWITCH('Use Case Tracker'!H34,"Not Started","Chưa bắt đầu","In Progress","Đang làm","Done","Hoàn thành",'Use Case Tracker'!H34)) -> Chưa bắt đầu | J31: =IF('Use Case Tracker'!J34="","",'Use Case Tracker'!J34) -> BR-FIN-01, BR-FIN-04, BR-FIN-07 | K31: =IFERROR(__xludf.DUMMYFUNCTION("IF('Use Case Tracker'!K34="""","""",IFERROR(GOOGLETRANSLATE('Use Case Tracker'!K34,""en"",""vi""),'Use Case Tracker'!K34))"),"Khoản phụ cấp/thưởng chỉ là hồ sơ nội bộ; không thể rút tiền mặt thực tế.") -> Khoản phụ cấp/thưởng chỉ là hồ sơ nội bộ; không thể rút tiền mặt thực tế. | L31: =IF('Use Case Tracker'!L34="","",SWITCH('Use Case Tracker'!L34,"Keep","Giữ trong scope","Could-have / Do after core","Có thể có / Làm sau core",'Use Case Tracker'!L34)) -> Keep, standardized as spending support request after Review 1
A32: =IF('Use Case Tracker'!A35="","",'Use Case Tracker'!A35) -> UC34 | B32: =IFERROR(__xludf.DUMMYFUNCTION("IF('Use Case Tracker'!B35="""","""",IFERROR(GOOGLETRANSLATE('Use Case Tracker'!B35,""en"",""vi""),'Use Case Tracker'!B35))"),"Gửi yêu cầu hỗ trợ chi tiêu") -> Gửi yêu cầu hỗ trợ chi tiêu | C32: =IFERROR(__xludf.DUMMYFUNCTION("IF('Use Case Tracker'!C35="""","""",IFERROR(GOOGLETRANSLATE('Use Case Tracker'!C35,""en"",""vi""),'Use Case Tracker'!C35))"),"Luồng 3") -> Luồng 3 | D32: =IFERROR(__xludf.DUMMYFUNCTION("IF('Use Case Tracker'!D35="""","""",IFERROR(GOOGLETRANSLATE('Use Case Tracker'!D35,""en"",""vi""),'Use Case Tracker'!D35))"),"Tài chính / Yêu cầu") -> Tài chính / Yêu cầu | E32: =IFERROR(__xludf.DUMMYFUNCTION("IF('Use Case Tracker'!E35="""","""",IFERROR(GOOGLETRANSLATE('Use Case Tracker'!E35,""en"",""vi""),'Use Case Tracker'!E35))"),"Thành viên gia đình") -> Thành viên gia đình | F32: =IFERROR(__xludf.DUMMYFUNCTION("IF('Use Case Tracker'!F35="""","""",IFERROR(GOOGLETRANSLATE('Use Case Tracker'!F35,""en"",""vi""),'Use Case Tracker'!F35))"),"Thành viên gia đình gửi yêu cầu hỗ trợ chi tiêu để người quản lý gia đình hoặc người được ủy quyền xem xét.") -> Thành viên gia đình gửi yêu cầu hỗ trợ chi tiêu để người quản lý gia đình hoặc người được ủy quyền xem xét. | G32: =IF('Use Case Tracker'!G35="","",SWITCH('Use Case Tracker'!G35,"Must-have","Bắt buộc","Should-have","Nên có","Could-have","Có thể có",'Use Case Tracker'!G35)) -> Bắt buộc | H32: =IF('Use Case Tracker'!H35="","",SWITCH('Use Case Tracker'!H35,"Not Started","Chưa bắt đầu","In Progress","Đang làm","Done","Hoàn thành",'Use Case Tracker'!H35)) -> Chưa bắt đầu | J32: =IF('Use Case Tracker'!J35="","",'Use Case Tracker'!J35) -> BR-FIN-02, BR-FIN-07 | K32: =IFERROR(__xludf.DUMMYFUNCTION("IF('Use Case Tracker'!K35="""","""",IFERROR(GOOGLETRANSLATE('Use Case Tracker'!K35,""en"",""vi""),'Use Case Tracker'!K35))"),"Yêu cầu này chỉ tạo ra quy trình phê duyệt và ghi lại thông tin, không trực tiếp rút tiền mặt.") -> Yêu cầu này chỉ tạo ra quy trình phê duyệt và ghi lại thông tin, không trực tiếp rút tiền mặt. | L32: =IF('Use Case Tracker'!L35="","",SWITCH('Use Case Tracker'!L35,"Keep","Giữ trong scope","Could-have / Do after core","Có thể có / Làm sau core",'Use Case Tracker'!L35)) -> Keep, standardized as spending support request after Review 1
A33: =IF('Use Case Tracker'!A36="","",'Use Case Tracker'!A36) -> UC35 | B33: =IFERROR(__xludf.DUMMYFUNCTION("IF('Use Case Tracker'!B36="""","""",IFERROR(GOOGLETRANSLATE('Use Case Tracker'!B36,""en"",""vi""),'Use Case Tracker'!B36))"),"Phê duyệt hoặc từ chối yêu cầu hỗ trợ chi tiêu") -> Phê duyệt hoặc từ chối yêu cầu hỗ trợ chi tiêu | C33: =IFERROR(__xludf.DUMMYFUNCTION("IF('Use Case Tracker'!C36="""","""",IFERROR(GOOGLETRANSLATE('Use Case Tracker'!C36,""en"",""vi""),'Use Case Tracker'!C36))"),"Luồng 3") -> Luồng 3 | D33: =IFERROR(__xludf.DUMMYFUNCTION("IF('Use Case Tracker'!D36="""","""",IFERROR(GOOGLETRANSLATE('Use Case Tracker'!D36,""en"",""vi""),'Use Case Tracker'!D36))"),"Tài chính / Yêu cầu") -> Tài chính / Yêu cầu | E33: =IFERROR(__xludf.DUMMYFUNCTION("IF('Use Case Tracker'!E36="""","""",IFERROR(GOOGLETRANSLATE('Use Case Tracker'!E36,""en"",""vi""),'Use Case Tracker'!E36))"),"Người quản lý gia đình / Thành viên gia đình được ủy quyền thay mặt") -> Người quản lý gia đình / Thành viên gia đình được ủy quyền thay mặt | F33: =IFERROR(__xludf.DUMMYFUNCTION("IF('Use Case Tracker'!F36="""","""",IFERROR(GOOGLETRANSLATE('Use Case Tracker'!F36,""en"",""vi""),'Use Case Tracker'!F36))"),"Phê duyệt hoặc từ chối yêu cầu hỗ trợ chi tiêu và tạo các bản ghi sổ quỹ gia đình liên quan nếu được phê duyệt.") -> Phê duyệt hoặc từ chối yêu cầu hỗ trợ chi tiêu và tạo các bản ghi sổ quỹ gia đình liên quan nếu được phê duyệt. | G33: =IF('Use Case Tracker'!G36="","",SWITCH('Use Case Tracker'!G36,"Must-have","Bắt buộc","Should-have","Nên có","Could-have","Có thể có",'Use Case Tracker'!G36)) -> Bắt buộc | H33: =IF('Use Case Tracker'!H36="","",SWITCH('Use Case Tracker'!H36,"Not Started","Chưa bắt đầu","In Progress","Đang làm","Done","Hoàn thành",'Use Case Tracker'!H36)) -> Chưa bắt đầu | J33: =IF('Use Case Tracker'!J36="","",'Use Case Tracker'!J36) -> BR-FIN-02, BR-FIN-03, BR-FIN-04, BR-FIN-07 | K33: =IFERROR(__xludf.DUMMYFUNCTION("IF('Use Case Tracker'!K36="""","""",IFERROR(GOOGLETRANSLATE('Use Case Tracker'!K36,""en"",""vi""),'Use Case Tracker'!K36))"),"Việc phê duyệt chỉ cập nhật sổ cái nội bộ/bản ghi trợ cấp.") -> Việc phê duyệt chỉ cập nhật sổ cái nội bộ/bản ghi trợ cấp. | L33: =IF('Use Case Tracker'!L36="","",SWITCH('Use Case Tracker'!L36,"Keep","Giữ trong scope","Could-have / Do after core","Có thể có / Làm sau core",'Use Case Tracker'!L36)) -> Keep, standardized as internal ledger history after Review 1
A34: =IF('Use Case Tracker'!A37="","",'Use Case Tracker'!A37) -> UC36 | B34: =IFERROR(__xludf.DUMMYFUNCTION("IF('Use Case Tracker'!B37="""","""",IFERROR(GOOGLETRANSLATE('Use Case Tracker'!B37,""en"",""vi""),'Use Case Tracker'!B37))"),"Xem lịch sử quỹ gia đình và trợ cấp") -> Xem lịch sử quỹ gia đình và trợ cấp | C34: =IFERROR(__xludf.DUMMYFUNCTION("IF('Use Case Tracker'!C37="""","""",IFERROR(GOOGLETRANSLATE('Use Case Tracker'!C37,""en"",""vi""),'Use Case Tracker'!C37))"),"Luồng 3") -> Luồng 3 | D34: =IFERROR(__xludf.DUMMYFUNCTION("IF('Use Case Tracker'!D37="""","""",IFERROR(GOOGLETRANSLATE('Use Case Tracker'!D37,""en"",""vi""),'Use Case Tracker'!D37))"),"Tài chính / Quỹ gia đình") -> Tài chính / Quỹ gia đình | E34: =IFERROR(__xludf.DUMMYFUNCTION("IF('Use Case Tracker'!E37="""","""",IFERROR(GOOGLETRANSLATE('Use Case Tracker'!E37,""en"",""vi""),'Use Case Tracker'!E37))"),"Người quản lý gia đình / Thành viên gia đình") -> Người quản lý gia đình / Thành viên gia đình | F34: =IFERROR(__xludf.DUMMYFUNCTION("IF('Use Case Tracker'!F37="""","""",IFERROR(GOOGLETRANSLATE('Use Case Tracker'!F37,""en"",""vi""),'Use Case Tracker'!F37))"),"Xem sổ quỹ gia đình, trợ cấp nội bộ, lịch sử yêu cầu hỗ trợ tiền thưởng và chi tiêu theo quyền hạn.") -> Xem sổ quỹ gia đình, trợ cấp nội bộ, lịch sử yêu cầu hỗ trợ tiền thưởng và chi tiêu theo quyền hạn. | G34: =IF('Use Case Tracker'!G37="","",SWITCH('Use Case Tracker'!G37,"Must-have","Bắt buộc","Should-have","Nên có","Could-have","Có thể có",'Use Case Tracker'!G37)) -> Bắt buộc | H34: =IF('Use Case Tracker'!H37="","",SWITCH('Use Case Tracker'!H37,"Not Started","Chưa bắt đầu","In Progress","Đang làm","Done","Hoàn thành",'Use Case Tracker'!H37)) -> Chưa bắt đầu | J34: =IF('Use Case Tracker'!J37="","",'Use Case Tracker'!J37) -> BR-FIN-04, BR-FIN-06, BR-FIN-07 | K34: =IFERROR(__xludf.DUMMYFUNCTION("IF('Use Case Tracker'!K37="""","""",IFERROR(GOOGLETRANSLATE('Use Case Tracker'!K37,""en"",""vi""),'Use Case Tracker'!K37))"),"Lịch sử giao dịch ở đây đề cập đến lịch sử sổ cái nội bộ, chứ không phải lịch sử giao dịch ngân hàng/thanh toán.") -> Lịch sử giao dịch ở đây đề cập đến lịch sử sổ cái nội bộ, chứ không phải lịch sử giao dịch ngân hàng/thanh toán. | L34: =IF('Use Case Tracker'!L37="","",SWITCH('Use Case Tracker'!L37,"Keep","Giữ trong scope","Could-have / Do after core","Có thể có / Làm sau core",'Use Case Tracker'!L37)) -> Keep, renamed from Family Fund Ledger history
A35: =IF('Use Case Tracker'!A38="","",'Use Case Tracker'!A38) -> UC37 | B35: =IFERROR(__xludf.DUMMYFUNCTION("IF('Use Case Tracker'!B38="""","""",IFERROR(GOOGLETRANSLATE('Use Case Tracker'!B38,""en"",""vi""),'Use Case Tracker'!B38))"),"Quản lý các danh mục công việc gia đình") -> Quản lý các danh mục công việc gia đình | C35: =IFERROR(__xludf.DUMMYFUNCTION("IF('Use Case Tracker'!C38="""","""",IFERROR(GOOGLETRANSLATE('Use Case Tracker'!C38,""en"",""vi""),'Use Case Tracker'!C38))"),"Luồng 4") -> Luồng 4 | D35: =IFERROR(__xludf.DUMMYFUNCTION("IF('Use Case Tracker'!D38="""","""",IFERROR(GOOGLETRANSLATE('Use Case Tracker'!D38,""en"",""vi""),'Use Case Tracker'!D38))"),"Nhiệm vụ") -> Nhiệm vụ | E35: =IFERROR(__xludf.DUMMYFUNCTION("IF('Use Case Tracker'!E38="""","""",IFERROR(GOOGLETRANSLATE('Use Case Tracker'!E38,""en"",""vi""),'Use Case Tracker'!E38))"),"Người quản lý gia đình / Thành viên gia đình được ủy quyền thay mặt") -> Người quản lý gia đình / Thành viên gia đình được ủy quyền thay mặt | F35: =IFERROR(__xludf.DUMMYFUNCTION("IF('Use Case Tracker'!F38="""","""",IFERROR(GOOGLETRANSLATE('Use Case Tracker'!F38,""en"",""vi""),'Use Case Tracker'!F38))"),"Quản lý các danh mục công việc gia đình") -> Quản lý các danh mục công việc gia đình | G35: =IF('Use Case Tracker'!G38="","",SWITCH('Use Case Tracker'!G38,"Must-have","Bắt buộc","Should-have","Nên có","Could-have","Có thể có",'Use Case Tracker'!G38)) -> Nên có | H35: =IF('Use Case Tracker'!H38="","",SWITCH('Use Case Tracker'!H38,"Not Started","Chưa bắt đầu","In Progress","Đang làm","Done","Hoàn thành",'Use Case Tracker'!H38)) -> Chưa bắt đầu | J35: =IF('Use Case Tracker'!J38="","",'Use Case Tracker'!J38) -> BR-TASK-01 | K35: =IFERROR(__xludf.DUMMYFUNCTION("IF('Use Case Tracker'!K38="""","""",IFERROR(GOOGLETRANSLATE('Use Case Tracker'!K38,""en"",""vi""),'Use Case Tracker'!K38))"),"") | L35: =IF('Use Case Tracker'!L38="","",SWITCH('Use Case Tracker'!L38,"Keep","Giữ trong scope","Could-have / Do after core","Có thể có / Làm sau core",'Use Case Tracker'!L38)) -> Giữ trong scope
A36: =IF('Use Case Tracker'!A39="","",'Use Case Tracker'!A39) -> UC38 | B36: =IFERROR(__xludf.DUMMYFUNCTION("IF('Use Case Tracker'!B39="""","""",IFERROR(GOOGLETRANSLATE('Use Case Tracker'!B39,""en"",""vi""),'Use Case Tracker'!B39))"),"Tạo tác vụ Ad-hoc") -> Tạo tác vụ Ad-hoc | C36: =IFERROR(__xludf.DUMMYFUNCTION("IF('Use Case Tracker'!C39="""","""",IFERROR(GOOGLETRANSLATE('Use Case Tracker'!C39,""en"",""vi""),'Use Case Tracker'!C39))"),"Luồng 4") -> Luồng 4 | D36: =IFERROR(__xludf.DUMMYFUNCTION("IF('Use Case Tracker'!D39="""","""",IFERROR(GOOGLETRANSLATE('Use Case Tracker'!D39,""en"",""vi""),'Use Case Tracker'!D39))"),"Nhiệm vụ") -> Nhiệm vụ | E36: =IFERROR(__xludf.DUMMYFUNCTION("IF('Use Case Tracker'!E39="""","""",IFERROR(GOOGLETRANSLATE('Use Case Tracker'!E39,""en"",""vi""),'Use Case Tracker'!E39))"),"Người quản lý gia đình / Thành viên gia đình được ủy quyền thay mặt") -> Người quản lý gia đình / Thành viên gia đình được ủy quyền thay mặt | F36: =IFERROR(__xludf.DUMMYFUNCTION("IF('Use Case Tracker'!F39="""","""",IFERROR(GOOGLETRANSLATE('Use Case Tracker'!F39,""en"",""vi""),'Use Case Tracker'!F39))"),"Tạo tác vụ Ad-hoc") -> Tạo tác vụ Ad-hoc | G36: =IF('Use Case Tracker'!G39="","",SWITCH('Use Case Tracker'!G39,"Must-have","Bắt buộc","Should-have","Nên có","Could-have","Có thể có",'Use Case Tracker'!G39)) -> Bắt buộc | H36: =IF('Use Case Tracker'!H39="","",SWITCH('Use Case Tracker'!H39,"Not Started","Chưa bắt đầu","In Progress","Đang làm","Done","Hoàn thành",'Use Case Tracker'!H39)) -> Chưa bắt đầu | J36: =IF('Use Case Tracker'!J39="","",'Use Case Tracker'!J39) -> BR-TASK-01 | K36: =IFERROR(__xludf.DUMMYFUNCTION("IF('Use Case Tracker'!K39="""","""",IFERROR(GOOGLETRANSLATE('Use Case Tracker'!K39,""en"",""vi""),'Use Case Tracker'!K39))"),"") | L36: =IF('Use Case Tracker'!L39="","",SWITCH('Use Case Tracker'!L39,"Keep","Giữ trong scope","Could-have / Do after core","Có thể có / Làm sau core",'Use Case Tracker'!L39)) -> Giữ trong scope
A37: =IF('Use Case Tracker'!A40="","",'Use Case Tracker'!A40) -> UC39 | B37: =IFERROR(__xludf.DUMMYFUNCTION("IF('Use Case Tracker'!B40="""","""",IFERROR(GOOGLETRANSLATE('Use Case Tracker'!B40,""en"",""vi""),'Use Case Tracker'!B40))"),"Tạo nhiệm vụ bắt buộc định kỳ") -> Tạo nhiệm vụ bắt buộc định kỳ | C37: =IFERROR(__xludf.DUMMYFUNCTION("IF('Use Case Tracker'!C40="""","""",IFERROR(GOOGLETRANSLATE('Use Case Tracker'!C40,""en"",""vi""),'Use Case Tracker'!C40))"),"Luồng 4") -> Luồng 4 | D37: =IFERROR(__xludf.DUMMYFUNCTION("IF('Use Case Tracker'!D40="""","""",IFERROR(GOOGLETRANSLATE('Use Case Tracker'!D40,""en"",""vi""),'Use Case Tracker'!D40))"),"Nhiệm vụ") -> Nhiệm vụ | E37: =IFERROR(__xludf.DUMMYFUNCTION("IF('Use Case Tracker'!E40="""","""",IFERROR(GOOGLETRANSLATE('Use Case Tracker'!E40,""en"",""vi""),'Use Case Tracker'!E40))"),"Người quản lý gia đình / Thành viên gia đình được ủy quyền thay mặt") -> Người quản lý gia đình / Thành viên gia đình được ủy quyền thay mặt | F37: =IFERROR(__xludf.DUMMYFUNCTION("IF('Use Case Tracker'!F40="""","""",IFERROR(GOOGLETRANSLATE('Use Case Tracker'!F40,""en"",""vi""),'Use Case Tracker'!F40))"),"Tạo nhiệm vụ bắt buộc định kỳ") -> Tạo nhiệm vụ bắt buộc định kỳ | G37: =IF('Use Case Tracker'!G40="","",SWITCH('Use Case Tracker'!G40,"Must-have","Bắt buộc","Should-have","Nên có","Could-have","Có thể có",'Use Case Tracker'!G40)) -> Bắt buộc | H37: =IF('Use Case Tracker'!H40="","",SWITCH('Use Case Tracker'!H40,"Not Started","Chưa bắt đầu","In Progress","Đang làm","Done","Hoàn thành",'Use Case Tracker'!H40)) -> Chưa bắt đầu | J37: =IF('Use Case Tracker'!J40="","",'Use Case Tracker'!J40) -> BR-TASK-01, BR-TASK-02 | K37: =IFERROR(__xludf.DUMMYFUNCTION("IF('Use Case Tracker'!K40="""","""",IFERROR(GOOGLETRANSLATE('Use Case Tracker'!K40,""en"",""vi""),'Use Case Tracker'!K40))"),"") | L37: =IF('Use Case Tracker'!L40="","",SWITCH('Use Case Tracker'!L40,"Keep","Giữ trong scope","Could-have / Do after core","Có thể có / Làm sau core",'Use Case Tracker'!L40)) -> Giữ trong scope
A38: =IF('Use Case Tracker'!A51="","",'Use Case Tracker'!A51) -> UC50 | B38: =IFERROR(__xludf.DUMMYFUNCTION("IF('Use Case Tracker'!B51="""","""",IFERROR(GOOGLETRANSLATE('Use Case Tracker'!B51,""en"",""vi""),'Use Case Tracker'!B51))"),"Kích hoạt cảnh báo SOS từ ứng dụng di động") -> Kích hoạt cảnh báo SOS từ ứng dụng di động | C38: =IFERROR(__xludf.DUMMYFUNCTION("IF('Use Case Tracker'!C51="""","""",IFERROR(GOOGLETRANSLATE('Use Case Tracker'!C51,""en"",""vi""),'Use Case Tracker'!C51))"),"Luồng 5") -> Luồng 5 | D38: =IFERROR(__xludf.DUMMYFUNCTION("IF('Use Case Tracker'!D51="""","""",IFERROR(GOOGLETRANSLATE('Use Case Tracker'!D51,""en"",""vi""),'Use Case Tracker'!D51))"),"SOS") -> SOS | E38: =IFERROR(__xludf.DUMMYFUNCTION("IF('Use Case Tracker'!E51="""","""",IFERROR(GOOGLETRANSLATE('Use Case Tracker'!E51,""en"",""vi""),'Use Case Tracker'!E51))"),"Thành viên gia đình") -> Thành viên gia đình | F38: =IFERROR(__xludf.DUMMYFUNCTION("IF('Use Case Tracker'!F51="""","""",IFERROR(GOOGLETRANSLATE('Use Case Tracker'!F51,""en"",""vi""),'Use Case Tracker'!F51))"),"Thành viên gia đình kích hoạt chức năng SOS từ ứng dụng trên điện thoại di động và gửi cảnh báo ưu tiên cao kèm thông tin vị trí khi có sẵn.") -> Thành viên gia đình kích hoạt chức năng SOS từ ứng dụng trên điện thoại di động và gửi cảnh báo ưu tiên cao kèm thông tin vị trí khi có sẵn. | G38: =IF('Use Case Tracker'!G51="","",SWITCH('Use Case Tracker'!G51,"Must-have","Bắt buộc","Should-have","Nên có","Could-have","Có thể có",'Use Case Tracker'!G51)) -> Bắt buộc | H38: =IF('Use Case Tracker'!H51="","",SWITCH('Use Case Tracker'!H51,"Not Started","Chưa bắt đầu","In Progress","Đang làm","Done","Hoàn thành",'Use Case Tracker'!H51)) -> Chưa bắt đầu | J38: =IF('Use Case Tracker'!J51="","",'Use Case Tracker'!J51) -> BR-SOS-01, BR-SOS-02, BR-SOS-05 | K38: =IFERROR(__xludf.DUMMYFUNCTION("IF('Use Case Tracker'!K51="""","""",IFERROR(GOOGLETRANSLATE('Use Case Tracker'!K51,""en"",""vi""),'Use Case Tracker'!K51))"),"Chức năng SOS trên thiết bị di động vẫn là tính năng cốt lõi; chức năng SOS trên thiết bị đeo được được thêm vào như một tính năng UC riêng biệt.") -> Chức năng SOS trên thiết bị di động vẫn là tính năng cốt lõi; chức năng SOS trên thiết bị đeo được được thêm vào như một tính năng UC riêng biệt. | L38: =IF('Use Case Tracker'!L51="","",SWITCH('Use Case Tracker'!L51,"Keep","Giữ trong scope","Could-have / Do after core","Có thể có / Làm sau core",'Use Case Tracker'!L51)) -> Giữ trong scope
A39: =IF('Use Case Tracker'!A52="","",'Use Case Tracker'!A52) -> UC51 | B39: =IFERROR(__xludf.DUMMYFUNCTION("IF('Use Case Tracker'!B52="""","""",IFERROR(GOOGLETRANSLATE('Use Case Tracker'!B52,""en"",""vi""),'Use Case Tracker'!B52))"),"Xem và phản hồi cảnh báo SOS") -> Xem và phản hồi cảnh báo SOS | C39: =IFERROR(__xludf.DUMMYFUNCTION("IF('Use Case Tracker'!C52="""","""",IFERROR(GOOGLETRANSLATE('Use Case Tracker'!C52,""en"",""vi""),'Use Case Tracker'!C52))"),"Luồng 5") -> Luồng 5 | D39: =IFERROR(__xludf.DUMMYFUNCTION("IF('Use Case Tracker'!D52="""","""",IFERROR(GOOGLETRANSLATE('Use Case Tracker'!D52,""en"",""vi""),'Use Case Tracker'!D52))"),"SOS") -> SOS | E39: =IFERROR(__xludf.DUMMYFUNCTION("IF('Use Case Tracker'!E52="""","""",IFERROR(GOOGLETRANSLATE('Use Case Tracker'!E52,""en"",""vi""),'Use Case Tracker'!E52))"),"Tất cả các thành viên trong gia đình") -> Tất cả các thành viên trong gia đình | F39: =IFERROR(__xludf.DUMMYFUNCTION("IF('Use Case Tracker'!F52="""","""",IFERROR(GOOGLETRANSLATE('Use Case Tracker'!F52,""en"",""vi""),'Use Case Tracker'!F52))"),"Xem chi tiết tín hiệu SOS, nguồn gốc, vị trí và các hành động phản hồi.") -> Xem chi tiết tín hiệu SOS, nguồn gốc, vị trí và các hành động phản hồi. | G39: =IF('Use Case Tracker'!G52="","",SWITCH('Use Case Tracker'!G52,"Must-have","Bắt buộc","Should-have","Nên có","Could-have","Có thể có",'Use Case Tracker'!G52)) -> Bắt buộc | H39: =IF('Use Case Tracker'!H52="","",SWITCH('Use Case Tracker'!H52,"Not Started","Chưa bắt đầu","In Progress","Đang làm","Done","Hoàn thành",'Use Case Tracker'!H52)) -> Chưa bắt đầu | J39: =IF('Use Case Tracker'!J52="","",'Use Case Tracker'!J52) -> BR-SOS-02 | K39: =IFERROR(__xludf.DUMMYFUNCTION("IF('Use Case Tracker'!K52="""","""",IFERROR(GOOGLETRANSLATE('Use Case Tracker'!K52,""en"",""vi""),'Use Case Tracker'!K52))"),"Các thành viên trong gia đình có thể biết ai đã kích hoạt SOS và phản hồi nhanh chóng.") -> Các thành viên trong gia đình có thể biết ai đã kích hoạt SOS và phản hồi nhanh chóng. | L39: =IF('Use Case Tracker'!L52="","",SWITCH('Use Case Tracker'!L52,"Keep","Giữ trong scope","Could-have / Do after core","Có thể có / Làm sau core",'Use Case Tracker'!L52)) -> Giữ trong scope
A40: =IF('Use Case Tracker'!A53="","",'Use Case Tracker'!A53) -> UC52 | B40: =IFERROR(__xludf.DUMMYFUNCTION("IF('Use Case Tracker'!B53="""","""",IFERROR(GOOGLETRANSLATE('Use Case Tracker'!B53,""en"",""vi""),'Use Case Tracker'!B53))"),"Xác nhận an toàn") -> Xác nhận an toàn | C40: =IFERROR(__xludf.DUMMYFUNCTION("IF('Use Case Tracker'!C53="""","""",IFERROR(GOOGLETRANSLATE('Use Case Tracker'!C53,""en"",""vi""),'Use Case Tracker'!C53))"),"Luồng 5") -> Luồng 5 | D40: =IFERROR(__xludf.DUMMYFUNCTION("IF('Use Case Tracker'!D53="""","""",IFERROR(GOOGLETRANSLATE('Use Case Tracker'!D53,""en"",""vi""),'Use Case Tracker'!D53))"),"SOS") -> SOS | E40: =IFERROR(__xludf.DUMMYFUNCTION("IF('Use Case Tracker'!E53="""","""",IFERROR(GOOGLETRANSLATE('Use Case Tracker'!E53,""en"",""vi""),'Use Case Tracker'!E53))"),"Thành viên gia đình") -> Thành viên gia đình | F40: =IFERROR(__xludf.DUMMYFUNCTION("IF('Use Case Tracker'!F53="""","""",IFERROR(GOOGLETRANSLATE('Use Case Tracker'!F53,""en"",""vi""),'Use Case Tracker'!F53))"),"Xác nhận an toàn sau khi sự cố SOS được xử lý hoặc báo động giả được giải quyết.") -> Xác nhận an toàn sau khi sự cố SOS được xử lý hoặc báo động giả được giải quyết. | G40: =IF('Use Case Tracker'!G53="","",SWITCH('Use Case Tracker'!G53,"Must-have","Bắt buộc","Should-have","Nên có","Could-have","Có thể có",'Use Case Tracker'!G53)) -> Bắt buộc | H40: =IF('Use Case Tracker'!H53="","",SWITCH('Use Case Tracker'!H53,"Not Started","Chưa bắt đầu","In Progress","Đang làm","Done","Hoàn thành",'Use Case Tracker'!H53)) -> Chưa bắt đầu | J40: =IF('Use Case Tracker'!J53="","",'Use Case Tracker'!J53) -> BR-SOS-03 | K40: =IFERROR(__xludf.DUMMYFUNCTION("IF('Use Case Tracker'!K53="""","""",IFERROR(GOOGLETRANSLATE('Use Case Tracker'!K53,""en"",""vi""),'Use Case Tracker'!K53))"),"Việc xác nhận an toàn là bắt buộc trước khi đưa ra quyết định cuối cùng (nếu có).") -> Việc xác nhận an toàn là bắt buộc trước khi đưa ra quyết định cuối cùng (nếu có). | L40: =IF('Use Case Tracker'!L53="","",SWITCH('Use Case Tracker'!L53,"Keep","Giữ trong scope","Could-have / Do after core","Có thể có / Làm sau core",'Use Case Tracker'!L53)) -> Giữ trong scope
A41: =IF('Use Case Tracker'!A54="","",'Use Case Tracker'!A54) -> UC53 | B41: =IFERROR(__xludf.DUMMYFUNCTION("IF('Use Case Tracker'!B54="""","""",IFERROR(GOOGLETRANSLATE('Use Case Tracker'!B54,""en"",""vi""),'Use Case Tracker'!B54))"),"Giải quyết hoặc hủy cảnh báo SOS") -> Giải quyết hoặc hủy cảnh báo SOS | C41: =IFERROR(__xludf.DUMMYFUNCTION("IF('Use Case Tracker'!C54="""","""",IFERROR(GOOGLETRANSLATE('Use Case Tracker'!C54,""en"",""vi""),'Use Case Tracker'!C54))"),"Luồng 5") -> Luồng 5 | D41: =IFERROR(__xludf.DUMMYFUNCTION("IF('Use Case Tracker'!D54="""","""",IFERROR(GOOGLETRANSLATE('Use Case Tracker'!D54,""en"",""vi""),'Use Case Tracker'!D54))"),"SOS") -> SOS | E41: =IFERROR(__xludf.DUMMYFUNCTION("IF('Use Case Tracker'!E54="""","""",IFERROR(GOOGLETRANSLATE('Use Case Tracker'!E54,""en"",""vi""),'Use Case Tracker'!E54))"),"Người quản lý gia đình / Thành viên gia đình được ủy quyền thay mặt") -> Người quản lý gia đình / Thành viên gia đình được ủy quyền thay mặt | F41: =IFERROR(__xludf.DUMMYFUNCTION("IF('Use Case Tracker'!F54="""","""",IFERROR(GOOGLETRANSLATE('Use Case Tracker'!F54,""en"",""vi""),'Use Case Tracker'!F54))"),"Giải quyết hoặc hủy bỏ cảnh báo SOS với xác nhận an toàn hoặc lý do xử lý rõ ràng.") -> Giải quyết hoặc hủy bỏ cảnh báo SOS với xác nhận an toàn hoặc lý do xử lý rõ ràng. | G41: =IF('Use Case Tracker'!G54="","",SWITCH('Use Case Tracker'!G54,"Must-have","Bắt buộc","Should-have","Nên có","Could-have","Có thể có",'Use Case Tracker'!G54)) -> Bắt buộc | H41: =IF('Use Case Tracker'!H54="","",SWITCH('Use Case Tracker'!H54,"Not Started","Chưa bắt đầu","In Progress","Đang làm","Done","Hoàn thành",'Use Case Tracker'!H54)) -> Chưa bắt đầu | J41: =IF('Use Case Tracker'!J54="","",'Use Case Tracker'!J54) -> BR-SOS-03 | K41: =IFERROR(__xludf.DUMMYFUNCTION("IF('Use Case Tracker'!K54="""","""",IFERROR(GOOGLETRANSLATE('Use Case Tracker'!K54,""en"",""vi""),'Use Case Tracker'!K54))"),"Việc đóng cửa SOS phải có thể truy vết được.") -> Việc đóng cửa SOS phải có thể truy vết được. | L41: =IF('Use Case Tracker'!L54="","",SWITCH('Use Case Tracker'!L54,"Keep","Giữ trong scope","Could-have / Do after core","Có thể có / Làm sau core",'Use Case Tracker'!L54)) -> Giữ trong scope
A42: =IF('Use Case Tracker'!A55="","",'Use Case Tracker'!A55) -> UC54 | B42: =IFERROR(__xludf.DUMMYFUNCTION("IF('Use Case Tracker'!B55="""","""",IFERROR(GOOGLETRANSLATE('Use Case Tracker'!B55,""en"",""vi""),'Use Case Tracker'!B55))"),"Xem vị trí SOS cơ bản hoặc lịch sử tuyến đường") -> Xem vị trí SOS cơ bản hoặc lịch sử tuyến đường | C42: =IFERROR(__xludf.DUMMYFUNCTION("IF('Use Case Tracker'!C55="""","""",IFERROR(GOOGLETRANSLATE('Use Case Tracker'!C55,""en"",""vi""),'Use Case Tracker'!C55))"),"Luồng 5") -> Luồng 5 | D42: =IFERROR(__xludf.DUMMYFUNCTION("IF('Use Case Tracker'!D55="""","""",IFERROR(GOOGLETRANSLATE('Use Case Tracker'!D55,""en"",""vi""),'Use Case Tracker'!D55))"),"SOS") -> SOS | E42: =IFERROR(__xludf.DUMMYFUNCTION("IF('Use Case Tracker'!E55="""","""",IFERROR(GOOGLETRANSLATE('Use Case Tracker'!E55,""en"",""vi""),'Use Case Tracker'!E55))"),"Người quản lý gia đình / Thành viên gia đình được ủy quyền thay mặt / Thành viên gia đình") -> Người quản lý gia đình / Thành viên gia đình được ủy quyền thay mặt / Thành viên gia đình | F42: =IFERROR(__xludf.DUMMYFUNCTION("IF('Use Case Tracker'!F55="""","""",IFERROR(GOOGLETRANSLATE('Use Case Tracker'!F55,""en"",""vi""),'Use Case Tracker'!F55))"),"Xem vị trí SOS cơ bản hoặc lịch sử lộ trình khi có sẵn và được cho phép.") -> Xem vị trí SOS cơ bản hoặc lịch sử lộ trình khi có sẵn và được cho phép. | G42: =IF('Use Case Tracker'!G55="","",SWITCH('Use Case Tracker'!G55,"Must-have","Bắt buộc","Should-have","Nên có","Could-have","Có thể có",'Use Case Tracker'!G55)) -> Nên có | H42: =IF('Use Case Tracker'!H55="","",SWITCH('Use Case Tracker'!H55,"Not Started","Chưa bắt đầu","In Progress","Đang làm","Done","Hoàn thành",'Use Case Tracker'!H55)) -> Chưa bắt đầu | J42: =IF('Use Case Tracker'!J55="","",'Use Case Tracker'!J55) -> BR-SOS-04 | K42: =IFERROR(__xludf.DUMMYFUNCTION("IF('Use Case Tracker'!K55="""","""",IFERROR(GOOGLETRANSLATE('Use Case Tracker'!K55,""en"",""vi""),'Use Case Tracker'!K55))"),"Chỉ hỗ trợ lịch sử lộ trình/vị trí SOS cơ bản; định vị GPS liên tục nâng cao sẽ có trong tương lai.") -> Chỉ hỗ trợ lịch sử lộ trình/vị trí SOS cơ bản; định vị GPS liên tục nâng cao sẽ có trong tương lai. | L42: =IF('Use Case Tracker'!L55="","",SWITCH('Use Case Tracker'!L55,"Keep","Giữ trong scope","Could-have / Do after core","Có thể có / Làm sau core",'Use Case Tracker'!L55)) -> Giữ trong scope
A43: =IF('Use Case Tracker'!A56="","",'Use Case Tracker'!A56) -> UC55 | B43: =IFERROR(__xludf.DUMMYFUNCTION("IF('Use Case Tracker'!B56="""","""",IFERROR(GOOGLETRANSLATE('Use Case Tracker'!B56,""en"",""vi""),'Use Case Tracker'!B56))"),"Cấu hình danh bạ và cài đặt SOS") -> Cấu hình danh bạ và cài đặt SOS | C43: =IFERROR(__xludf.DUMMYFUNCTION("IF('Use Case Tracker'!C56="""","""",IFERROR(GOOGLETRANSLATE('Use Case Tracker'!C56,""en"",""vi""),'Use Case Tracker'!C56))"),"Luồng 5") -> Luồng 5 | D43: =IFERROR(__xludf.DUMMYFUNCTION("IF('Use Case Tracker'!D56="""","""",IFERROR(GOOGLETRANSLATE('Use Case Tracker'!D56,""en"",""vi""),'Use Case Tracker'!D56))"),"SOS") -> SOS | E43: =IFERROR(__xludf.DUMMYFUNCTION("IF('Use Case Tracker'!E56="""","""",IFERROR(GOOGLETRANSLATE('Use Case Tracker'!E56,""en"",""vi""),'Use Case Tracker'!E56))"),"Quản lý gia đình") -> Quản lý gia đình | F43: =IFERROR(__xludf.DUMMYFUNCTION("IF('Use Case Tracker'!F56="""","""",IFERROR(GOOGLETRANSLATE('Use Case Tracker'!F56,""en"",""vi""),'Use Case Tracker'!F56))"),"Family Manager cấu hình các số liên lạc khẩn cấp SOS và cài đặt cảnh báo cho không gian làm việc của gia đình.") -> Family Manager cấu hình các số liên lạc khẩn cấp SOS và cài đặt cảnh báo cho không gian làm việc của gia đình. | G43: =IF('Use Case Tracker'!G56="","",SWITCH('Use Case Tracker'!G56,"Must-have","Bắt buộc","Should-have","Nên có","Could-have","Có thể có",'Use Case Tracker'!G56)) -> Bắt buộc | H43: =IF('Use Case Tracker'!H56="","",SWITCH('Use Case Tracker'!H56,"Not Started","Chưa bắt đầu","In Progress","Đang làm","Done","Hoàn thành",'Use Case Tracker'!H56)) -> Chưa bắt đầu | J43: =IF('Use Case Tracker'!J56="","",'Use Case Tracker'!J56) -> BR-SOS-01, BR-SOS-05 | K43: =IFERROR(__xludf.DUMMYFUNCTION("IF('Use Case Tracker'!K56="""","""",IFERROR(GOOGLETRANSLATE('Use Case Tracker'!K56,""en"",""vi""),'Use Case Tracker'!K56))"),"Các thiết lập xác định ai nhận được tín hiệu SOS và cách thức hoạt động của cảnh báo an toàn.") -> Các thiết lập xác định ai nhận được tín hiệu SOS và cách thức hoạt động của cảnh báo an toàn. | L43: =IF('Use Case Tracker'!L56="","",SWITCH('Use Case Tracker'!L56,"Keep","Giữ trong scope","Could-have / Do after core","Có thể có / Làm sau core",'Use Case Tracker'!L56)) -> Giữ trong scope
A44: =IF('Use Case Tracker'!A57="","",'Use Case Tracker'!A57) -> UC56 | B44: =IFERROR(__xludf.DUMMYFUNCTION("IF('Use Case Tracker'!B57="""","""",IFERROR(GOOGLETRANSLATE('Use Case Tracker'!B57,""en"",""vi""),'Use Case Tracker'!B57))"),"Thiết bị đeo/an toàn Pair SOS") -> Thiết bị đeo/an toàn Pair SOS | C44: =IFERROR(__xludf.DUMMYFUNCTION("IF('Use Case Tracker'!C57="""","""",IFERROR(GOOGLETRANSLATE('Use Case Tracker'!C57,""en"",""vi""),'Use Case Tracker'!C57))"),"Luồng 5") -> Luồng 5 | D44: =IFERROR(__xludf.DUMMYFUNCTION("IF('Use Case Tracker'!D57="""","""",IFERROR(GOOGLETRANSLATE('Use Case Tracker'!D57,""en"",""vi""),'Use Case Tracker'!D57))"),"SOS / Thiết bị đeo được") -> SOS / Thiết bị đeo được | E44: =IFERROR(__xludf.DUMMYFUNCTION("IF('Use Case Tracker'!E57="""","""",IFERROR(GOOGLETRANSLATE('Use Case Tracker'!E57,""en"",""vi""),'Use Case Tracker'!E57))"),"Người quản lý gia đình / Thành viên gia đình") -> Người quản lý gia đình / Thành viên gia đình | F44: =IFERROR(__xludf.DUMMYFUNCTION("IF('Use Case Tracker'!F57="""","""",IFERROR(GOOGLETRANSLATE('Use Case Tracker'!F57,""en"",""vi""),'Use Case Tracker'!F57))"),"Ghép nối hoặc đăng ký thiết bị đeo/thiết bị an toàn để hỗ trợ kích hoạt SOS và mô phỏng cảnh báo an toàn.") -> Ghép nối hoặc đăng ký thiết bị đeo/thiết bị an toàn để hỗ trợ kích hoạt SOS và mô phỏng cảnh báo an toàn. | G44: =IF('Use Case Tracker'!G57="","",SWITCH('Use Case Tracker'!G57,"Must-have","Bắt buộc","Should-have","Nên có","Could-have","Có thể có",'Use Case Tracker'!G57)) -> Bắt buộc | H44: =IF('Use Case Tracker'!H57="","",SWITCH('Use Case Tracker'!H57,"Not Started","Chưa bắt đầu","In Progress","Đang làm","Done","Hoàn thành",'Use Case Tracker'!H57)) -> Chưa bắt đầu | J44: =IF('Use Case Tracker'!J57="","",'Use Case Tracker'!J57) -> BR-SOS-05, BR-SOS-06 | K44: =IFERROR(__xludf.DUMMYFUNCTION("IF('Use Case Tracker'!K57="""","""",IFERROR(GOOGLETRANSLATE('Use Case Tracker'!K57,""en"",""vi""),'Use Case Tracker'!K57))"),"Có thể mô phỏng thiết bị đeo được để trình diễn nếu việc tích hợp đồng hồ thông minh thực tế không ổn định.") -> Có thể mô phỏng thiết bị đeo được để trình diễn nếu việc tích hợp đồng hồ thông minh thực tế không ổn định. | L44: =IF('Use Case Tracker'!L57="","",SWITCH('Use Case Tracker'!L57,"Keep","Giữ trong scope","Could-have / Do after core","Có thể có / Làm sau core",'Use Case Tracker'!L57)) -> Keep for demo/simulation
A45: =IF('Use Case Tracker'!A58="","",'Use Case Tracker'!A58) -> UC57 | B45: =IFERROR(__xludf.DUMMYFUNCTION("IF('Use Case Tracker'!B58="""","""",IFERROR(GOOGLETRANSLATE('Use Case Tracker'!B58,""en"",""vi""),'Use Case Tracker'!B58))"),"Kích hoạt SOS từ thiết bị đeo được") -> Kích hoạt SOS từ thiết bị đeo được | C45: =IFERROR(__xludf.DUMMYFUNCTION("IF('Use Case Tracker'!C58="""","""",IFERROR(GOOGLETRANSLATE('Use Case Tracker'!C58,""en"",""vi""),'Use Case Tracker'!C58))"),"Luồng 5") -> Luồng 5 | D45: =IFERROR(__xludf.DUMMYFUNCTION("IF('Use Case Tracker'!D58="""","""",IFERROR(GOOGLETRANSLATE('Use Case Tracker'!D58,""en"",""vi""),'Use Case Tracker'!D58))"),"SOS / Thiết bị đeo được") -> SOS / Thiết bị đeo được | E45: =IFERROR(__xludf.DUMMYFUNCTION("IF('Use Case Tracker'!E58="""","""",IFERROR(GOOGLETRANSLATE('Use Case Tracker'!E58,""en"",""vi""),'Use Case Tracker'!E58))"),"Thành viên gia đình") -> Thành viên gia đình | F45: =IFERROR(__xludf.DUMMYFUNCTION("IF('Use Case Tracker'!F58="""","""",IFERROR(GOOGLETRANSLATE('Use Case Tracker'!F58,""en"",""vi""),'Use Case Tracker'!F58))"),"Kích hoạt tín hiệu SOS từ thiết bị đeo được hoặc thiết bị mô phỏng an toàn và thông báo cho các thành viên gia đình kèm theo vị trí khi có sẵn.") -> Kích hoạt tín hiệu SOS từ thiết bị đeo được hoặc thiết bị mô phỏng an toàn và thông báo cho các thành viên gia đình kèm theo vị trí khi có sẵn. | G45: =IF('Use Case Tracker'!G58="","",SWITCH('Use Case Tracker'!G58,"Must-have","Bắt buộc","Should-have","Nên có","Could-have","Có thể có",'Use Case Tracker'!G58)) -> Bắt buộc | H45: =IF('Use Case Tracker'!H58="","",SWITCH('Use Case Tracker'!H58,"Not Started","Chưa bắt đầu","In Progress","Đang làm","Done","Hoàn thành",'Use Case Tracker'!H58)) -> Chưa bắt đầu | J45: =IF('Use Case Tracker'!J58="","",'Use Case Tracker'!J58) -> BR-SOS-01, BR-SOS-02, BR-SOS-05, BR-SOS-06 | K45: =IFERROR(__xludf.DUMMYFUNCTION("IF('Use Case Tracker'!K58="""","""",IFERROR(GOOGLETRANSLATE('Use Case Tracker'!K58,""en"",""vi""),'Use Case Tracker'!K58))"),"Mục tiêu chính là chứng minh rằng tín hiệu SOS có thể được kích hoạt từ thiết bị, chứ không chỉ từ ứng dụng di động.") -> Mục tiêu chính là chứng minh rằng tín hiệu SOS có thể được kích hoạt từ thiết bị, chứ không chỉ từ ứng dụng di động. | L45: =IF('Use Case Tracker'!L58="","",SWITCH('Use Case Tracker'!L58,"Keep","Giữ trong scope","Could-have / Do after core","Có thể có / Làm sau core",'Use Case Tracker'!L58)) -> Giữ trong scope
A46: =IF('Use Case Tracker'!A63="","",'Use Case Tracker'!A63) -> UC62 | B46: =IFERROR(__xludf.DUMMYFUNCTION("IF('Use Case Tracker'!B63="""","""",IFERROR(GOOGLETRANSLATE('Use Case Tracker'!B63,""en"",""vi""),'Use Case Tracker'!B63))"),"Sử dụng tính năng trò chuyện riêng tư cơ bản") -> Sử dụng tính năng trò chuyện riêng tư cơ bản | C46: =IFERROR(__xludf.DUMMYFUNCTION("IF('Use Case Tracker'!C63="""","""",IFERROR(GOOGLETRANSLATE('Use Case Tracker'!C63,""en"",""vi""),'Use Case Tracker'!C63))"),"Hỗ trợ giao tiếp") -> Hỗ trợ giao tiếp | D46: =IFERROR(__xludf.DUMMYFUNCTION("IF('Use Case Tracker'!D63="""","""",IFERROR(GOOGLETRANSLATE('Use Case Tracker'!D63,""en"",""vi""),'Use Case Tracker'!D63))"),"Giao tiếp") -> Giao tiếp | E46: =IFERROR(__xludf.DUMMYFUNCTION("IF('Use Case Tracker'!E63="""","""",IFERROR(GOOGLETRANSLATE('Use Case Tracker'!E63,""en"",""vi""),'Use Case Tracker'!E63))"),"Thành viên gia đình") -> Thành viên gia đình | F46: =IFERROR(__xludf.DUMMYFUNCTION("IF('Use Case Tracker'!F63="""","""",IFERROR(GOOGLETRANSLATE('Use Case Tracker'!F63,""en"",""vi""),'Use Case Tracker'!F63))"),"Gửi và nhận tin nhắn trực tiếp với một thành viên khác trong gia đình cùng làm việc trong cùng một không gian.") -> Gửi và nhận tin nhắn trực tiếp với một thành viên khác trong gia đình cùng làm việc trong cùng một không gian. | G46: =IF('Use Case Tracker'!G63="","",SWITCH('Use Case Tracker'!G63,"Must-have","Bắt buộc","Should-have","Nên có","Could-have","Có thể có",'Use Case Tracker'!G63)) -> Có thể có | H46: =IF('Use Case Tracker'!H63="","",SWITCH('Use Case Tracker'!H63,"Not Started","Chưa bắt đầu","In Progress","Đang làm","Done","Hoàn thành",'Use Case Tracker'!H63)) -> Chưa bắt đầu | J46: =IF('Use Case Tracker'!J63="","",'Use Case Tracker'!J63) -> BR-COM-02 | K46: =IFERROR(__xludf.DUMMYFUNCTION("IF('Use Case Tracker'!K63="""","""",IFERROR(GOOGLETRANSLATE('Use Case Tracker'!K63,""en"",""vi""),'Use Case Tracker'!K63))"),"Có thể làm sau buổi trò chuyện nhóm nếu còn thời gian.") -> Có thể làm sau buổi trò chuyện nhóm nếu còn thời gian. | L46: =IF('Use Case Tracker'!L63="","",SWITCH('Use Case Tracker'!L63,"Keep","Giữ trong scope","Could-have / Do after core","Có thể có / Làm sau core",'Use Case Tracker'!L63)) -> Giữ trong scope
A47: =IF('Use Case Tracker'!A64="","",'Use Case Tracker'!A64) -> UC63 | B47: =IFERROR(__xludf.DUMMYFUNCTION("IF('Use Case Tracker'!B64="""","""",IFERROR(GOOGLETRANSLATE('Use Case Tracker'!B64,""en"",""vi""),'Use Case Tracker'!B64))"),"Gửi thông báo cho gia đình") -> Gửi thông báo cho gia đình | C47: =IFERROR(__xludf.DUMMYFUNCTION("IF('Use Case Tracker'!C64="""","""",IFERROR(GOOGLETRANSLATE('Use Case Tracker'!C64,""en"",""vi""),'Use Case Tracker'!C64))"),"Hỗ trợ giao tiếp") -> Hỗ trợ giao tiếp | D47: =IFERROR(__xludf.DUMMYFUNCTION("IF('Use Case Tracker'!D64="""","""",IFERROR(GOOGLETRANSLATE('Use Case Tracker'!D64,""en"",""vi""),'Use Case Tracker'!D64))"),"Giao tiếp") -> Giao tiếp | E47: =IFERROR(__xludf.DUMMYFUNCTION("IF('Use Case Tracker'!E64="""","""",IFERROR(GOOGLETRANSLATE('Use Case Tracker'!E64,""en"",""vi""),'Use Case Tracker'!E64))"),"Người quản lý gia đình / Thành viên gia đình được ủy quyền thay mặt") -> Người quản lý gia đình / Thành viên gia đình được ủy quyền thay mặt | F47: =IFERROR(__xludf.DUMMYFUNCTION("IF('Use Case Tracker'!F64="""","""",IFERROR(GOOGLETRANSLATE('Use Case Tracker'!F64,""en"",""vi""),'Use Case Tracker'!F64))"),"Gửi thông báo quan trọng đến tất cả thành viên trong Nhóm làm việc gia đình.") -> Gửi thông báo quan trọng đến tất cả thành viên trong Nhóm làm việc gia đình. | G47: =IF('Use Case Tracker'!G64="","",SWITCH('Use Case Tracker'!G64,"Must-have","Bắt buộc","Should-have","Nên có","Could-have","Có thể có",'Use Case Tracker'!G64)) -> Nên có | H47: =IF('Use Case Tracker'!H64="","",SWITCH('Use Case Tracker'!H64,"Not Started","Chưa bắt đầu","In Progress","Đang làm","Done","Hoàn thành",'Use Case Tracker'!H64)) -> Chưa bắt đầu | J47: =IF('Use Case Tracker'!J64="","",'Use Case Tracker'!J64) -> BR-COM-03 | K47: =IFERROR(__xludf.DUMMYFUNCTION("IF('Use Case Tracker'!K64="""","""",IFERROR(GOOGLETRANSLATE('Use Case Tracker'!K64,""en"",""vi""),'Use Case Tracker'!K64))"),"Hữu ích cho việc cập nhật thông tin trong toàn gia đình; hãy giữ mọi thứ đơn giản.") -> Hữu ích cho việc cập nhật thông tin trong toàn gia đình; hãy giữ mọi thứ đơn giản. | L47: =IF('Use Case Tracker'!L64="","",SWITCH('Use Case Tracker'!L64,"Keep","Giữ trong scope","Could-have / Do after core","Có thể có / Làm sau core",'Use Case Tracker'!L64)) -> Giữ trong scope
A48: =IF('Use Case Tracker'!A65="","",'Use Case Tracker'!A65) -> UC64 | B48: =IFERROR(__xludf.DUMMYFUNCTION("IF('Use Case Tracker'!B65="""","""",IFERROR(GOOGLETRANSLATE('Use Case Tracker'!B65,""en"",""vi""),'Use Case Tracker'!B65))"),"Sử dụng hệ thống liên lạc an toàn nhanh chóng") -> Sử dụng hệ thống liên lạc an toàn nhanh chóng | C48: =IFERROR(__xludf.DUMMYFUNCTION("IF('Use Case Tracker'!C65="""","""",IFERROR(GOOGLETRANSLATE('Use Case Tracker'!C65,""en"",""vi""),'Use Case Tracker'!C65))"),"Hỗ trợ giao tiếp") -> Hỗ trợ giao tiếp | D48: =IFERROR(__xludf.DUMMYFUNCTION("IF('Use Case Tracker'!D65="""","""",IFERROR(GOOGLETRANSLATE('Use Case Tracker'!D65,""en"",""vi""),'Use Case Tracker'!D65))"),"Liên lạc / SOS") -> Liên lạc / SOS | E48: =IFERROR(__xludf.DUMMYFUNCTION("IF('Use Case Tracker'!E65="""","""",IFERROR(GOOGLETRANSLATE('Use Case Tracker'!E65,""en"",""vi""),'Use Case Tracker'!E65))"),"Tất cả các thành viên trong gia đình") -> Tất cả các thành viên trong gia đình | F48: =IFERROR(__xludf.DUMMYFUNCTION("IF('Use Case Tracker'!F65="""","""",IFERROR(GOOGLETRANSLATE('Use Case Tracker'!F65,""en"",""vi""),'Use Case Tracker'!F65))"),"Hãy sử dụng phím tắt nhắn tin nhanh hoặc gọi hỗ trợ trong các tình huống liên quan đến an toàn.") -> Hãy sử dụng phím tắt nhắn tin nhanh hoặc gọi hỗ trợ trong các tình huống liên quan đến an toàn. | G48: =IF('Use Case Tracker'!G65="","",SWITCH('Use Case Tracker'!G65,"Must-have","Bắt buộc","Should-have","Nên có","Could-have","Có thể có",'Use Case Tracker'!G65)) -> Có thể có | H48: =IF('Use Case Tracker'!H65="","",SWITCH('Use Case Tracker'!H65,"Not Started","Chưa bắt đầu","In Progress","Đang làm","Done","Hoàn thành",'Use Case Tracker'!H65)) -> Chưa bắt đầu | J48: =IF('Use Case Tracker'!J65="","",'Use Case Tracker'!J65) -> BR-COM-04, BR-SOS-02 | K48: =IFERROR(__xludf.DUMMYFUNCTION("IF('Use Case Tracker'!K65="""","""",IFERROR(GOOGLETRANSLATE('Use Case Tracker'!K65,""en"",""vi""),'Use Case Tracker'!K65))"),"Có thể hiển thị dưới dạng nút/phím tắt giao diện người dùng; không cần tích hợp cuộc gọi thực sự.") -> Có thể hiển thị dưới dạng nút/phím tắt giao diện người dùng; không cần tích hợp cuộc gọi thực sự. | L48: =IF('Use Case Tracker'!L65="","",SWITCH('Use Case Tracker'!L65,"Keep","Giữ trong scope","Could-have / Do after core","Có thể có / Làm sau core",'Use Case Tracker'!L65)) -> Could-have
A49: =IF('Use Case Tracker'!A66="","",'Use Case Tracker'!A66) -> UC65 | B49: =IFERROR(__xludf.DUMMYFUNCTION("IF('Use Case Tracker'!B66="""","""",IFERROR(GOOGLETRANSLATE('Use Case Tracker'!B66,""en"",""vi""),'Use Case Tracker'!B66))"),"Hỏi trợ lý AI") -> Hỏi trợ lý AI | C49: =IFERROR(__xludf.DUMMYFUNCTION("IF('Use Case Tracker'!C66="""","""",IFERROR(GOOGLETRANSLATE('Use Case Tracker'!C66,""en"",""vi""),'Use Case Tracker'!C66))"),"Hỗ trợ thông tin chi tiết về AI") -> Hỗ trợ thông tin chi tiết về AI | D49: =IFERROR(__xludf.DUMMYFUNCTION("IF('Use Case Tracker'!D66="""","""",IFERROR(GOOGLETRANSLATE('Use Case Tracker'!D66,""en"",""vi""),'Use Case Tracker'!D66))"),"Trí tuệ nhân tạo") -> Trí tuệ nhân tạo | E49: =IFERROR(__xludf.DUMMYFUNCTION("IF('Use Case Tracker'!E66="""","""",IFERROR(GOOGLETRANSLATE('Use Case Tracker'!E66,""en"",""vi""),'Use Case Tracker'!E66))"),"Tất cả các thành viên trong gia đình") -> Tất cả các thành viên trong gia đình | F49: =IFERROR(__xludf.DUMMYFUNCTION("IF('Use Case Tracker'!F66="""","""",IFERROR(GOOGLETRANSLATE('Use Case Tracker'!F66,""en"",""vi""),'Use Case Tracker'!F66))"),"Người dùng đặt câu hỏi cho Trợ lý AI về tài chính gia đình, tình trạng công việc, nhắc nhở, gợi ý tiết kiệm hoặc các hoạt động chung của gia đình dựa trên dữ liệu và quyền hạn hiện có.") -> Người dùng đặt câu hỏi cho Trợ lý AI về tài chính gia đình, tình trạng công việc, nhắc nhở, gợi ý tiết kiệm hoặc các hoạt động chung của gia đình dựa trên dữ liệu và quyền hạn hiện có. | G49: =IF('Use Case Tracker'!G66="","",SWITCH('Use Case Tracker'!G66,"Must-have","Bắt buộc","Should-have","Nên có","Could-have","Có thể có",'Use Case Tracker'!G66)) -> Nên có | H49: =IF('Use Case Tracker'!H66="","",SWITCH('Use Case Tracker'!H66,"Not Started","Chưa bắt đầu","In Progress","Đang làm","Done","Hoàn thành",'Use Case Tracker'!H66)) -> Chưa bắt đầu | J49: =IF('Use Case Tracker'!J66="","",'Use Case Tracker'!J66) -> BR-AI-01, BR-AI-02 | K49: =IFERROR(__xludf.DUMMYFUNCTION("IF('Use Case Tracker'!K66="""","""",IFERROR(GOOGLETRANSLATE('Use Case Tracker'!K66,""en"",""vi""),'Use Case Tracker'!K66))"),"Trí tuệ nhân tạo (AI) là một tính năng hỗ trợ, không phải là một luồng hoạt động cốt lõi. Nó phải tôn trọng quyền hạn của người dùng và ngữ cảnh không gian làm việc.") -> Trí tuệ nhân tạo (AI) là một tính năng hỗ trợ, không phải là một luồng hoạt động cốt lõi. Nó phải tôn trọng quyền hạn của người dùng và ngữ cảnh không gian làm việc. | L49: =IF('Use Case Tracker'!L66="","",SWITCH('Use Case Tracker'!L66,"Keep","Giữ trong scope","Could-have / Do after core","Có thể có / Làm sau core",'Use Case Tracker'!L66)) -> Keep / Supporting
A50: =IF('Use Case Tracker'!A67="","",'Use Case Tracker'!A67) -> UC66 | B50: =IFERROR(__xludf.DUMMYFUNCTION("IF('Use Case Tracker'!B67="""","""",IFERROR(GOOGLETRANSLATE('Use Case Tracker'!B67,""en"",""vi""),'Use Case Tracker'!B67))"),"Xem tóm tắt về Tài chính AI") -> Xem tóm tắt về Tài chính AI | C50: =IFERROR(__xludf.DUMMYFUNCTION("IF('Use Case Tracker'!C67="""","""",IFERROR(GOOGLETRANSLATE('Use Case Tracker'!C67,""en"",""vi""),'Use Case Tracker'!C67))"),"Hỗ trợ thông tin chi tiết về AI") -> Hỗ trợ thông tin chi tiết về AI | D50: =IFERROR(__xludf.DUMMYFUNCTION("IF('Use Case Tracker'!D67="""","""",IFERROR(GOOGLETRANSLATE('Use Case Tracker'!D67,""en"",""vi""),'Use Case Tracker'!D67))"),"Trí tuệ nhân tạo / Tài chính") -> Trí tuệ nhân tạo / Tài chính | E50: =IFERROR(__xludf.DUMMYFUNCTION("IF('Use Case Tracker'!E67="""","""",IFERROR(GOOGLETRANSLATE('Use Case Tracker'!E67,""en"",""vi""),'Use Case Tracker'!E67))"),"Người quản lý gia đình / Thành viên gia đình được ủy quyền thay mặt") -> Người quản lý gia đình / Thành viên gia đình được ủy quyền thay mặt | F50: =IFERROR(__xludf.DUMMYFUNCTION("IF('Use Case Tracker'!F67="""","""",IFERROR(GOOGLETRANSLATE('Use Case Tracker'!F67,""en"",""vi""),'Use Case Tracker'!F67))"),"AI tóm tắt tình hình tài chính gia đình, số dư quỹ gia đình, tình trạng chi tiêu, so sánh kế hoạch với thực tế và cảnh báo ngân sách dựa trên dữ liệu mà người dùng được phép xem.") -> AI tóm tắt tình hình tài chính gia đình, số dư quỹ gia đình, tình trạng chi tiêu, so sánh kế hoạch với thực tế và cảnh báo ngân sách dựa trên dữ liệu mà người dùng được phép xem. | G50: =IF('Use Case Tracker'!G67="","",SWITCH('Use Case Tracker'!G67,"Must-have","Bắt buộc","Should-have","Nên có","Could-have","Có thể có",'Use Case Tracker'!G67)) -> Nên có | H50: =IF('Use Case Tracker'!H67="","",SWITCH('Use Case Tracker'!H67,"Not Started","Chưa bắt đầu","In Progress","Đang làm","Done","Hoàn thành",'Use Case Tracker'!H67)) -> Chưa bắt đầu | J50: =IF('Use Case Tracker'!J67="","",'Use Case Tracker'!J67) -> BR-AI-01, BR-AI-03, BR-FIN-05, BR-FIN-06 | K50: =IFERROR(__xludf.DUMMYFUNCTION("IF('Use Case Tracker'!K67="""","""",IFERROR(GOOGLETRANSLATE('Use Case Tracker'!K67,""en"",""vi""),'Use Case Tracker'!K67))"),"Dữ liệu tài chính nhạy cảm không được phép tiết lộ cho các thành viên gia đình không được ủy quyền.") -> Dữ liệu tài chính nhạy cảm không được phép tiết lộ cho các thành viên gia đình không được ủy quyền. | L50: =IF('Use Case Tracker'!L67="","",SWITCH('Use Case Tracker'!L67,"Keep","Giữ trong scope","Could-have / Do after core","Có thể có / Làm sau core",'Use Case Tracker'!L67)) -> Keep / Supporting
A51: =IF('Use Case Tracker'!A68="","",'Use Case Tracker'!A68) -> UC67 | B51: =IFERROR(__xludf.DUMMYFUNCTION("IF('Use Case Tracker'!B68="""","""",IFERROR(GOOGLETRANSLATE('Use Case Tracker'!B68,""en"",""vi""),'Use Case Tracker'!B68))"),"Xem tóm tắt nhiệm vụ AI") -> Xem tóm tắt nhiệm vụ AI | C51: =IFERROR(__xludf.DUMMYFUNCTION("IF('Use Case Tracker'!C68="""","""",IFERROR(GOOGLETRANSLATE('Use Case Tracker'!C68,""en"",""vi""),'Use Case Tracker'!C68))"),"Hỗ trợ thông tin chi tiết về AI") -> Hỗ trợ thông tin chi tiết về AI | D51: =IFERROR(__xludf.DUMMYFUNCTION("IF('Use Case Tracker'!D68="""","""",IFERROR(GOOGLETRANSLATE('Use Case Tracker'!D68,""en"",""vi""),'Use Case Tracker'!D68))"),"Trí tuệ nhân tạo / Nhiệm vụ") -> Trí tuệ nhân tạo / Nhiệm vụ | E51: =IFERROR(__xludf.DUMMYFUNCTION("IF('Use Case Tracker'!E68="""","""",IFERROR(GOOGLETRANSLATE('Use Case Tracker'!E68,""en"",""vi""),'Use Case Tracker'!E68))"),"Người quản lý gia đình / Thành viên gia đình") -> Người quản lý gia đình / Thành viên gia đình | F51: =IFERROR(__xludf.DUMMYFUNCTION("IF('Use Case Tracker'!F68="""","""",IFERROR(GOOGLETRANSLATE('Use Case Tracker'!F68,""en"",""vi""),'Use Case Tracker'!F68))"),"AI tóm tắt các nhiệm vụ đã được giao, nhiệm vụ đang chờ xử lý, nhiệm vụ định kỳ không khả dụng, nhiệm vụ đã hoàn thành và trạng thái thanh toán phần thưởng dựa trên vai trò và quyền hạn thực hiện nhiệm vụ.") -> AI tóm tắt các nhiệm vụ đã được giao, nhiệm vụ đang chờ xử lý, nhiệm vụ định kỳ không khả dụng, nhiệm vụ đã hoàn thành và trạng thái thanh toán phần thưởng dựa trên vai trò và quyền hạn thực hiện nhiệm vụ. | G51: =IF('Use Case Tracker'!G68="","",SWITCH('Use Case Tracker'!G68,"Must-have","Bắt buộc","Should-have","Nên có","Could-have","Có thể có",'Use Case Tracker'!G68)) -> Nên có | H51: =IF('Use Case Tracker'!H68="","",SWITCH('Use Case Tracker'!H68,"Not Started","Chưa bắt đầu","In Progress","Đang làm","Done","Hoàn thành",'Use Case Tracker'!H68)) -> Chưa bắt đầu | J51: =IF('Use Case Tracker'!J68="","",'Use Case Tracker'!J68) -> BR-AI-01, BR-AI-02, BR-TASK-02, BR-TASK-04, BR-REW-02 | K51: =IFERROR(__xludf.DUMMYFUNCTION("IF('Use Case Tracker'!K68="""","""",IFERROR(GOOGLETRANSLATE('Use Case Tracker'!K68,""en"",""vi""),'Use Case Tracker'!K68))"),"Trí tuệ nhân tạo (AI) chỉ tóm tắt trạng thái nhiệm vụ/phần thưởng và lời nhắc; nó không tự động chỉ định, phê duyệt hoặc thanh toán phần thưởng.") -> Trí tuệ nhân tạo (AI) chỉ tóm tắt trạng thái nhiệm vụ/phần thưởng và lời nhắc; nó không tự động chỉ định, phê duyệt hoặc thanh toán phần thưởng. | L51: =IF('Use Case Tracker'!L68="","",SWITCH('Use Case Tracker'!L68,"Keep","Giữ trong scope","Could-have / Do after core","Có thể có / Làm sau core",'Use Case Tracker'!L68)) -> Keep / Supporting
A52: =IF('Use Case Tracker'!A69="","",'Use Case Tracker'!A69) -> UC68 | B52: =IFERROR(__xludf.DUMMYFUNCTION("IF('Use Case Tracker'!B69="""","""",IFERROR(GOOGLETRANSLATE('Use Case Tracker'!B69,""en"",""vi""),'Use Case Tracker'!B69))"),"Nhận các đề xuất về ngân sách và tiết kiệm dựa trên trí tuệ nhân tạo") -> Nhận các đề xuất về ngân sách và tiết kiệm dựa trên trí tuệ nhân tạo | C52: =IFERROR(__xludf.DUMMYFUNCTION("IF('Use Case Tracker'!C69="""","""",IFERROR(GOOGLETRANSLATE('Use Case Tracker'!C69,""en"",""vi""),'Use Case Tracker'!C69))"),"Hỗ trợ thông tin chi tiết về AI") -> Hỗ trợ thông tin chi tiết về AI | D52: =IFERROR(__xludf.DUMMYFUNCTION("IF('Use Case Tracker'!D69="""","""",IFERROR(GOOGLETRANSLATE('Use Case Tracker'!D69,""en"",""vi""),'Use Case Tracker'!D69))"),"Trí tuệ nhân tạo / Tài chính") -> Trí tuệ nhân tạo / Tài chính | E52: =IFERROR(__xludf.DUMMYFUNCTION("IF('Use Case Tracker'!E69="""","""",IFERROR(GOOGLETRANSLATE('Use Case Tracker'!E69,""en"",""vi""),'Use Case Tracker'!E69))"),"Quản lý gia đình") -> Quản lý gia đình | F52: =IFERROR(__xludf.DUMMYFUNCTION("IF('Use Case Tracker'!F69="""","""",IFERROR(GOOGLETRANSLATE('Use Case Tracker'!F69,""en"",""vi""),'Use Case Tracker'!F69))"),"Trí tuệ nhân tạo (AI) đưa ra các đề xuất về ngân sách và tiết kiệm dựa trên ngân sách đã ghi nhận, chi phí thực tế, phần thưởng cho nhiệm vụ và dữ liệu tài chính gia đình được cho phép.") -> Trí tuệ nhân tạo (AI) đưa ra các đề xuất về ngân sách và tiết kiệm dựa trên ngân sách đã ghi nhận, chi phí thực tế, phần thưởng cho nhiệm vụ và dữ liệu tài chính gia đình được cho phép. | G52: =IF('Use Case Tracker'!G69="","",SWITCH('Use Case Tracker'!G69,"Must-have","Bắt buộc","Should-have","Nên có","Could-have","Có thể có",'Use Case Tracker'!G69)) -> Nên có | H52: =IF('Use Case Tracker'!H69="","",SWITCH('Use Case Tracker'!H69,"Not Started","Chưa bắt đầu","In Progress","Đang làm","Done","Hoàn thành",'Use Case Tracker'!H69)) -> Chưa bắt đầu | J52: =IF('Use Case Tracker'!J69="","",'Use Case Tracker'!J69) -> BR-AI-01, BR-AI-02, BR-AI-04, BR-FIN-05, BR-FIN-06 | K52: =IFERROR(__xludf.DUMMYFUNCTION("IF('Use Case Tracker'!K69="""","""",IFERROR(GOOGLETRANSLATE('Use Case Tracker'!K69,""en"",""vi""),'Use Case Tracker'!K69))"),"Trí tuệ nhân tạo (AI) chỉ đưa ra tóm tắt và gợi ý. Nó không tự động đưa ra quyết định tài chính hoặc tự động thay đổi dữ liệu.") -> Trí tuệ nhân tạo (AI) chỉ đưa ra tóm tắt và gợi ý. Nó không tự động đưa ra quyết định tài chính hoặc tự động thay đổi dữ liệu. | L52: =IF('Use Case Tracker'!L69="","",SWITCH('Use Case Tracker'!L69,"Keep","Giữ trong scope","Could-have / Do after core","Có thể có / Làm sau core",'Use Case Tracker'!L69)) -> Keep / Supporting
A53: =IF('Use Case Tracker'!A70="","",'Use Case Tracker'!A70) -> UC69 | B53: =IFERROR(__xludf.DUMMYFUNCTION("IF('Use Case Tracker'!B70="""","""",IFERROR(GOOGLETRANSLATE('Use Case Tracker'!B70,""en"",""vi""),'Use Case Tracker'!B70))"),"Yêu cầu đặt lại mật khẩu") -> Yêu cầu đặt lại mật khẩu | C53: =IFERROR(__xludf.DUMMYFUNCTION("IF('Use Case Tracker'!C70="""","""",IFERROR(GOOGLETRANSLATE('Use Case Tracker'!C70,""en"",""vi""),'Use Case Tracker'!C70))"),"Luồng 1") -> Luồng 1 | D53: =IFERROR(__xludf.DUMMYFUNCTION("IF('Use Case Tracker'!D70="""","""",IFERROR(GOOGLETRANSLATE('Use Case Tracker'!D70,""en"",""vi""),'Use Case Tracker'!D70))"),"Xác thực") -> Xác thực | E53: =IFERROR(__xludf.DUMMYFUNCTION("IF('Use Case Tracker'!E70="""","""",IFERROR(GOOGLETRANSLATE('Use Case Tracker'!E70,""en"",""vi""),'Use Case Tracker'!E70))"),"Khách/Người dùng") -> Khách/Người dùng | F53: =IFERROR(__xludf.DUMMYFUNCTION("IF('Use Case Tracker'!F70="""","""",IFERROR(GOOGLETRANSLATE('Use Case Tracker'!F70,""en"",""vi""),'Use Case Tracker'!F70))"),"Khách hoặc Người dùng yêu cầu liên kết đặt lại mật khẩu để lấy lại quyền truy cập vào tài khoản của họ.") -> Khách hoặc Người dùng yêu cầu liên kết đặt lại mật khẩu để lấy lại quyền truy cập vào tài khoản của họ. | G53: =IF('Use Case Tracker'!G70="","",SWITCH('Use Case Tracker'!G70,"Must-have","Bắt buộc","Should-have","Nên có","Could-have","Có thể có",'Use Case Tracker'!G70)) -> Bắt buộc | H53: =IF('Use Case Tracker'!H70="","",SWITCH('Use Case Tracker'!H70,"Not Started","Chưa bắt đầu","In Progress","Đang làm","Done","Hoàn thành",'Use Case Tracker'!H70)) -> Chưa bắt đầu | J53: =IF('Use Case Tracker'!J70="","",'Use Case Tracker'!J70) -> BR-AUTH-02 | K53: =IFERROR(__xludf.DUMMYFUNCTION("IF('Use Case Tracker'!K70="""","""",IFERROR(GOOGLETRANSLATE('Use Case Tracker'!K70,""en"",""vi""),'Use Case Tracker'!K70))"),"") | L53: =IF('Use Case Tracker'!L70="","",SWITCH('Use Case Tracker'!L70,"Keep","Giữ trong scope","Could-have / Do after core","Có thể có / Làm sau core",'Use Case Tracker'!L70)) -> Giữ trong scope
A54: =IF('Use Case Tracker'!A71="","",'Use Case Tracker'!A71) -> UC70 | B54: =IFERROR(__xludf.DUMMYFUNCTION("IF('Use Case Tracker'!B71="""","""",IFERROR(GOOGLETRANSLATE('Use Case Tracker'!B71,""en"",""vi""),'Use Case Tracker'!B71))"),"Tạo sự kiện lịch gia đình") -> Tạo sự kiện lịch gia đình | C54: =IFERROR(__xludf.DUMMYFUNCTION("IF('Use Case Tracker'!C71="""","""",IFERROR(GOOGLETRANSLATE('Use Case Tracker'!C71,""en"",""vi""),'Use Case Tracker'!C71))"),"Lịch hỗ trợ") -> Lịch hỗ trợ | D54: =IFERROR(__xludf.DUMMYFUNCTION("IF('Use Case Tracker'!D71="""","""",IFERROR(GOOGLETRANSLATE('Use Case Tracker'!D71,""en"",""vi""),'Use Case Tracker'!D71))"),"Lịch") -> Lịch | E54: =IFERROR(__xludf.DUMMYFUNCTION("IF('Use Case Tracker'!E71="""","""",IFERROR(GOOGLETRANSLATE('Use Case Tracker'!E71,""en"",""vi""),'Use Case Tracker'!E71))"),"Quản gia/Phó quản gia") -> Quản gia/Phó quản gia | F54: =IFERROR(__xludf.DUMMYFUNCTION("IF('Use Case Tracker'!F71="""","""",IFERROR(GOOGLETRANSLATE('Use Case Tracker'!F71,""en"",""vi""),'Use Case Tracker'!F71))"),"Quản lý hoặc Phó quản lý gia đình tạo một sự kiện mới trong lịch chung của gia đình.") -> Quản lý hoặc Phó quản lý gia đình tạo một sự kiện mới trong lịch chung của gia đình. | G54: =IF('Use Case Tracker'!G71="","",SWITCH('Use Case Tracker'!G71,"Must-have","Bắt buộc","Should-have","Nên có","Could-have","Có thể có",'Use Case Tracker'!G71)) -> Bắt buộc | H54: =IF('Use Case Tracker'!H71="","",SWITCH('Use Case Tracker'!H71,"Not Started","Chưa bắt đầu","In Progress","Đang làm","Done","Hoàn thành",'Use Case Tracker'!H71)) -> Chưa bắt đầu | J54: =IF('Use Case Tracker'!J71="","",'Use Case Tracker'!J71) -> BR-CAL-01 | K54: =IFERROR(__xludf.DUMMYFUNCTION("IF('Use Case Tracker'!K71="""","""",IFERROR(GOOGLETRANSLATE('Use Case Tracker'!K71,""en"",""vi""),'Use Case Tracker'!K71))"),"") | L54: =IF('Use Case Tracker'!L71="","",SWITCH('Use Case Tracker'!L71,"Keep","Giữ trong scope","Could-have / Do after core","Có thể có / Làm sau core",'Use Case Tracker'!L71)) -> Giữ trong scope
A55: =IF('Use Case Tracker'!A72="","",'Use Case Tracker'!A72) -> UC71 | B55: =IFERROR(__xludf.DUMMYFUNCTION("IF('Use Case Tracker'!B72="""","""",IFERROR(GOOGLETRANSLATE('Use Case Tracker'!B72,""en"",""vi""),'Use Case Tracker'!B72))"),"Xem các sự kiện trong lịch gia đình") -> Xem các sự kiện trong lịch gia đình | C55: =IFERROR(__xludf.DUMMYFUNCTION("IF('Use Case Tracker'!C72="""","""",IFERROR(GOOGLETRANSLATE('Use Case Tracker'!C72,""en"",""vi""),'Use Case Tracker'!C72))"),"Lịch hỗ trợ") -> Lịch hỗ trợ | D55: =IFERROR(__xludf.DUMMYFUNCTION("IF('Use Case Tracker'!D72="""","""",IFERROR(GOOGLETRANSLATE('Use Case Tracker'!D72,""en"",""vi""),'Use Case Tracker'!D72))"),"Lịch") -> Lịch | E55: =IFERROR(__xludf.DUMMYFUNCTION("IF('Use Case Tracker'!E72="""","""",IFERROR(GOOGLETRANSLATE('Use Case Tracker'!E72,""en"",""vi""),'Use Case Tracker'!E72))"),"Tất cả các thành viên trong gia đình") -> Tất cả các thành viên trong gia đình | F55: =IFERROR(__xludf.DUMMYFUNCTION("IF('Use Case Tracker'!F72="""","""",IFERROR(GOOGLETRANSLATE('Use Case Tracker'!F72,""en"",""vi""),'Use Case Tracker'!F72))"),"Tất cả các thành viên trong gia đình đều có thể xem các sự kiện sắp tới và lời nhắc nhở trong lịch chung của gia đình.") -> Tất cả các thành viên trong gia đình đều có thể xem các sự kiện sắp tới và lời nhắc nhở trong lịch chung của gia đình. | G55: =IF('Use Case Tracker'!G72="","",SWITCH('Use Case Tracker'!G72,"Must-have","Bắt buộc","Should-have","Nên có","Could-have","Có thể có",'Use Case Tracker'!G72)) -> Bắt buộc | H55: =IF('Use Case Tracker'!H72="","",SWITCH('Use Case Tracker'!H72,"Not Started","Chưa bắt đầu","In Progress","Đang làm","Done","Hoàn thành",'Use Case Tracker'!H72)) -> Chưa bắt đầu | J55: =IF('Use Case Tracker'!J72="","",'Use Case Tracker'!J72) -> BR-CAL-01 | K55: =IFERROR(__xludf.DUMMYFUNCTION("IF('Use Case Tracker'!K72="""","""",IFERROR(GOOGLETRANSLATE('Use Case Tracker'!K72,""en"",""vi""),'Use Case Tracker'!K72))"),"") | L55: =IF('Use Case Tracker'!L72="","",SWITCH('Use Case Tracker'!L72,"Keep","Giữ trong scope","Could-have / Do after core","Có thể có / Làm sau core",'Use Case Tracker'!L72)) -> Giữ trong scope
A56: =IF('Use Case Tracker'!A73="","",'Use Case Tracker'!A73) -> UC72 | B56: =IFERROR(__xludf.DUMMYFUNCTION("IF('Use Case Tracker'!B73="""","""",IFERROR(GOOGLETRANSLATE('Use Case Tracker'!B73,""en"",""vi""),'Use Case Tracker'!B73))"),"Tải phương tiện lên Album gia đình dùng chung") -> Tải phương tiện lên Album gia đình dùng chung | C56: =IFERROR(__xludf.DUMMYFUNCTION("IF('Use Case Tracker'!C73="""","""",IFERROR(GOOGLETRANSLATE('Use Case Tracker'!C73,""en"",""vi""),'Use Case Tracker'!C73))"),"Album hỗ trợ") -> Album hỗ trợ | D56: =IFERROR(__xludf.DUMMYFUNCTION("IF('Use Case Tracker'!D73="""","""",IFERROR(GOOGLETRANSLATE('Use Case Tracker'!D73,""en"",""vi""),'Use Case Tracker'!D73))"),"Album") -> Album | E56: =IFERROR(__xludf.DUMMYFUNCTION("IF('Use Case Tracker'!E73="""","""",IFERROR(GOOGLETRANSLATE('Use Case Tracker'!E73,""en"",""vi""),'Use Case Tracker'!E73))"),"Tất cả các thành viên trong gia đình") -> Tất cả các thành viên trong gia đình | F56: =IFERROR(__xludf.DUMMYFUNCTION("IF('Use Case Tracker'!F73="""","""",IFERROR(GOOGLETRANSLATE('Use Case Tracker'!F73,""en"",""vi""),'Use Case Tracker'!F73))"),"Tất cả các thành viên trong gia đình đều tải ảnh và video lên album ảnh chung của gia đình.") -> Tất cả các thành viên trong gia đình đều tải ảnh và video lên album ảnh chung của gia đình. | G56: =IF('Use Case Tracker'!G73="","",SWITCH('Use Case Tracker'!G73,"Must-have","Bắt buộc","Should-have","Nên có","Could-have","Có thể có",'Use Case Tracker'!G73)) -> Bắt buộc | H56: =IF('Use Case Tracker'!H73="","",SWITCH('Use Case Tracker'!H73,"Not Started","Chưa bắt đầu","In Progress","Đang làm","Done","Hoàn thành",'Use Case Tracker'!H73)) -> Chưa bắt đầu | J56: =IF('Use Case Tracker'!J73="","",'Use Case Tracker'!J73) -> BR-ALB-01 | K56: =IFERROR(__xludf.DUMMYFUNCTION("IF('Use Case Tracker'!K73="""","""",IFERROR(GOOGLETRANSLATE('Use Case Tracker'!K73,""en"",""vi""),'Use Case Tracker'!K73))"),"Chức năng tải/xem album cơ bản vẫn chỉ mang tính hỗ trợ, không phải là chức năng cốt lõi.") -> Chức năng tải/xem album cơ bản vẫn chỉ mang tính hỗ trợ, không phải là chức năng cốt lõi. | L56: =IF('Use Case Tracker'!L73="","",SWITCH('Use Case Tracker'!L73,"Keep","Giữ trong scope","Could-have / Do after core","Có thể có / Làm sau core",'Use Case Tracker'!L73)) -> Giữ trong scope
A57: =IF('Use Case Tracker'!A74="","",'Use Case Tracker'!A74) -> UC73 | B57: =IFERROR(__xludf.DUMMYFUNCTION("IF('Use Case Tracker'!B74="""","""",IFERROR(GOOGLETRANSLATE('Use Case Tracker'!B74,""en"",""vi""),'Use Case Tracker'!B74))"),"Xem Album ảnh gia đình được chia sẻ") -> Xem Album ảnh gia đình được chia sẻ | C57: =IFERROR(__xludf.DUMMYFUNCTION("IF('Use Case Tracker'!C74="""","""",IFERROR(GOOGLETRANSLATE('Use Case Tracker'!C74,""en"",""vi""),'Use Case Tracker'!C74))"),"Album hỗ trợ") -> Album hỗ trợ | D57: =IFERROR(__xludf.DUMMYFUNCTION("IF('Use Case Tracker'!D74="""","""",IFERROR(GOOGLETRANSLATE('Use Case Tracker'!D74,""en"",""vi""),'Use Case Tracker'!D74))"),"Album") -> Album | E57: =IFERROR(__xludf.DUMMYFUNCTION("IF('Use Case Tracker'!E74="""","""",IFERROR(GOOGLETRANSLATE('Use Case Tracker'!E74,""en"",""vi""),'Use Case Tracker'!E74))"),"Tất cả các thành viên trong gia đình") -> Tất cả các thành viên trong gia đình | F57: =IFERROR(__xludf.DUMMYFUNCTION("IF('Use Case Tracker'!F74="""","""",IFERROR(GOOGLETRANSLATE('Use Case Tracker'!F74,""en"",""vi""),'Use Case Tracker'!F74))"),"Tất cả các thành viên trong gia đình đều có thể xem và tương tác với ảnh và video trong album gia đình được chia sẻ.") -> Tất cả các thành viên trong gia đình đều có thể xem và tương tác với ảnh và video trong album gia đình được chia sẻ. | G57: =IF('Use Case Tracker'!G74="","",SWITCH('Use Case Tracker'!G74,"Must-have","Bắt buộc","Should-have","Nên có","Could-have","Có thể có",'Use Case Tracker'!G74)) -> Bắt buộc | H57: =IF('Use Case Tracker'!H74="","",SWITCH('Use Case Tracker'!H74,"Not Started","Chưa bắt đầu","In Progress","Đang làm","Done","Hoàn thành",'Use Case Tracker'!H74)) -> Chưa bắt đầu | I57: =IF('Use Case Tracker'!I74="","",'Use Case Tracker'!I74) | J57: =IF('Use Case Tracker'!J74="","",'Use Case Tracker'!J74) -> BR-ALB-01 | K57: =IFERROR(__xludf.DUMMYFUNCTION("IF('Use Case Tracker'!K74="""","""",IFERROR(GOOGLETRANSLATE('Use Case Tracker'!K74,""en"",""vi""),'Use Case Tracker'!K74))"),"Tính năng chia sẻ album cơ bản vẫn được duy trì.") -> Tính năng chia sẻ album cơ bản vẫn được duy trì. | L57: =IF('Use Case Tracker'!L74="","",SWITCH('Use Case Tracker'!L74,"Keep","Giữ trong scope","Could-have / Do after core","Có thể có / Làm sau core",'Use Case Tracker'!L74)) -> Giữ trong scope
A58: =IF('Use Case Tracker'!A75="","",'Use Case Tracker'!A75) -> UC74 | B58: =IFERROR(__xludf.DUMMYFUNCTION("IF('Use Case Tracker'!B75="""","""",IFERROR(GOOGLETRANSLATE('Use Case Tracker'!B75,""en"",""vi""),'Use Case Tracker'!B75))"),"Gắn thẻ các thành viên gia đình trong Album ảnh") -> Gắn thẻ các thành viên gia đình trong Album ảnh | C58: =IFERROR(__xludf.DUMMYFUNCTION("IF('Use Case Tracker'!C75="""","""",IFERROR(GOOGLETRANSLATE('Use Case Tracker'!C75,""en"",""vi""),'Use Case Tracker'!C75))"),"Album hỗ trợ") -> Album hỗ trợ | D58: =IFERROR(__xludf.DUMMYFUNCTION("IF('Use Case Tracker'!D75="""","""",IFERROR(GOOGLETRANSLATE('Use Case Tracker'!D75,""en"",""vi""),'Use Case Tracker'!D75))"),"Album") -> Album | E58: =IFERROR(__xludf.DUMMYFUNCTION("IF('Use Case Tracker'!E75="""","""",IFERROR(GOOGLETRANSLATE('Use Case Tracker'!E75,""en"",""vi""),'Use Case Tracker'!E75))"),"Tất cả các thành viên trong gia đình") -> Tất cả các thành viên trong gia đình | F58: =IFERROR(__xludf.DUMMYFUNCTION("IF('Use Case Tracker'!F75="""","""",IFERROR(GOOGLETRANSLATE('Use Case Tracker'!F75,""en"",""vi""),'Use Case Tracker'!F75))"),"Người dùng tự gắn thẻ các thành viên gia đình vào ảnh/video trong album được chia sẻ để làm cho album gia đình thêm ý nghĩa.") -> Người dùng tự gắn thẻ các thành viên gia đình vào ảnh/video trong album được chia sẻ để làm cho album gia đình thêm ý nghĩa. | G58: =IF('Use Case Tracker'!G75="","",SWITCH('Use Case Tracker'!G75,"Must-have","Bắt buộc","Should-have","Nên có","Could-have","Có thể có",'Use Case Tracker'!G75)) -> Có thể có | H58: =IF('Use Case Tracker'!H75="","",SWITCH('Use Case Tracker'!H75,"Not Started","Chưa bắt đầu","In Progress","Đang làm","Done","Hoàn thành",'Use Case Tracker'!H75)) -> Chưa bắt đầu | I58: =IF('Use Case Tracker'!I75="","",'Use Case Tracker'!I75) | J58: =IF('Use Case Tracker'!J75="","",'Use Case Tracker'!J75) -> BR-ALB-01, BR-ALB-02 | K58: =IFERROR(__xludf.DUMMYFUNCTION("IF('Use Case Tracker'!K75="""","""",IFERROR(GOOGLETRANSLATE('Use Case Tracker'!K75,""en"",""vi""),'Use Case Tracker'!K75))"),"Gắn thẻ thủ công an toàn hơn cho MVP so với việc phân cụm khuôn mặt hoàn toàn bằng AI.") -> Gắn thẻ thủ công an toàn hơn cho MVP so với việc phân cụm khuôn mặt hoàn toàn bằng AI. | L58: =IF('Use Case Tracker'!L75="","",SWITCH('Use Case Tracker'!L75,"Keep","Giữ trong scope","Could-have / Do after core","Có thể có / Làm sau core",'Use Case Tracker'!L75)) -> Do after core
A59: =IF('Use Case Tracker'!A76="","",'Use Case Tracker'!A76) -> UC75 | B59: =IFERROR(__xludf.DUMMYFUNCTION("IF('Use Case Tracker'!B76="""","""",IFERROR(GOOGLETRANSLATE('Use Case Tracker'!B76,""en"",""vi""),'Use Case Tracker'!B76))"),"Đề xuất nhóm album theo khuôn mặt") -> Đề xuất nhóm album theo khuôn mặt | C59: =IFERROR(__xludf.DUMMYFUNCTION("IF('Use Case Tracker'!C76="""","""",IFERROR(GOOGLETRANSLATE('Use Case Tracker'!C76,""en"",""vi""),'Use Case Tracker'!C76))"),"Album hỗ trợ / AI") -> Album hỗ trợ / AI | D59: =IFERROR(__xludf.DUMMYFUNCTION("IF('Use Case Tracker'!D76="""","""",IFERROR(GOOGLETRANSLATE('Use Case Tracker'!D76,""en"",""vi""),'Use Case Tracker'!D76))"),"Album / AI") -> Album / AI | E59: =IFERROR(__xludf.DUMMYFUNCTION("IF('Use Case Tracker'!E76="""","""",IFERROR(GOOGLETRANSLATE('Use Case Tracker'!E76,""en"",""vi""),'Use Case Tracker'!E76))"),"Hệ thống / Tất cả các thành viên gia đình") -> Hệ thống / Tất cả các thành viên gia đình | F59: =IFERROR(__xludf.DUMMYFUNCTION("IF('Use Case Tracker'!F76="""","""",IFERROR(GOOGLETRANSLATE('Use Case Tracker'!F76,""en"",""vi""),'Use Case Tracker'!F76))"),"Hệ thống đề xuất nhóm các bức ảnh dựa trên các khuôn mặt tương tự được phát hiện, nhưng người dùng cần xác nhận trước khi gắn thẻ hoặc sắp xếp.") -> Hệ thống đề xuất nhóm các bức ảnh dựa trên các khuôn mặt tương tự được phát hiện, nhưng người dùng cần xác nhận trước khi gắn thẻ hoặc sắp xếp. | G59: =IF('Use Case Tracker'!G76="","",SWITCH('Use Case Tracker'!G76,"Must-have","Bắt buộc","Should-have","Nên có","Could-have","Có thể có",'Use Case Tracker'!G76)) -> Có thể có | H59: =IF('Use Case Tracker'!H76="","",SWITCH('Use Case Tracker'!H76,"Not Started","Chưa bắt đầu","In Progress","Đang làm","Done","Hoàn thành",'Use Case Tracker'!H76)) -> Chưa bắt đầu | I59: =IF('Use Case Tracker'!I76="","",'Use Case Tracker'!I76) | J59: =IF('Use Case Tracker'!J76="","",'Use Case Tracker'!J76) -> BR-ALB-02, BR-AI-01 | K59: =IFERROR(__xludf.DUMMYFUNCTION("IF('Use Case Tracker'!K76="""","""",IFERROR(GOOGLETRANSLATE('Use Case Tracker'!K76,""en"",""vi""),'Use Case Tracker'!K76))"),"Phân cụm khuôn mặt là tính năng được cải tiến trong tương lai hoặc chỉ dành cho bản demo, không phải là tính năng cốt lõi của sản phẩm tối thiểu (MVP).") -> Phân cụm khuôn mặt là tính năng được cải tiến trong tương lai hoặc chỉ dành cho bản demo, không phải là tính năng cốt lõi của sản phẩm tối thiểu (MVP). | L59: =IF('Use Case Tracker'!L76="","",SWITCH('Use Case Tracker'!L76,"Keep","Giữ trong scope","Could-have / Do after core","Có thể có / Làm sau core",'Use Case Tracker'!L76)) -> Future / AI Enhancement
A60: =IF('Use Case Tracker'!A77="","",'Use Case Tracker'!A77) -> UC76 | B60: =IFERROR(__xludf.DUMMYFUNCTION("IF('Use Case Tracker'!B77="""","""",IFERROR(GOOGLETRANSLATE('Use Case Tracker'!B77,""en"",""vi""),'Use Case Tracker'!B77))"),"Xem thông tin về gói đăng ký và quyền truy cập tính năng hiện tại.") -> Xem thông tin về gói đăng ký và quyền truy cập tính năng hiện tại. | C60: =IFERROR(__xludf.DUMMYFUNCTION("IF('Use Case Tracker'!C77="""","""",IFERROR(GOOGLETRANSLATE('Use Case Tracker'!C77,""en"",""vi""),'Use Case Tracker'!C77))"),"Đăng ký hỗ trợ") -> Đăng ký hỗ trợ | D60: =IFERROR(__xludf.DUMMYFUNCTION("IF('Use Case Tracker'!D77="""","""",IFERROR(GOOGLETRANSLATE('Use Case Tracker'!D77,""en"",""vi""),'Use Case Tracker'!D77))"),"Đăng ký") -> Đăng ký | E60: =IFERROR(__xludf.DUMMYFUNCTION("IF('Use Case Tracker'!E77="""","""",IFERROR(GOOGLETRANSLATE('Use Case Tracker'!E77,""en"",""vi""),'Use Case Tracker'!E77))"),"Quản lý gia đình") -> Quản lý gia đình | F60: =IFERROR(__xludf.DUMMYFUNCTION("IF('Use Case Tracker'!F77="""","""",IFERROR(GOOGLETRANSLATE('Use Case Tracker'!F77,""en"",""vi""),'Use Case Tracker'!F77))"),"Family Manager hiển thị gói cước hiện tại, trạng thái thanh toán hàng năm, giá hàng năm, ngày bắt đầu, ngày hết hạn, số ngày còn lại, các tính năng đang hoạt động và các chức năng bị khóa/mở khóa.") -> Family Manager hiển thị gói cước hiện tại, trạng thái thanh toán hàng năm, giá hàng năm, ngày bắt đầu, ngày hết hạn, số ngày còn lại, các tính năng đang hoạt động và các chức năng bị khóa/mở khóa. | G60: =IF('Use Case Tracker'!G77="","",SWITCH('Use Case Tracker'!G77,"Must-have","Bắt buộc","Should-have","Nên có","Could-have","Có thể có",'Use Case Tracker'!G77)) -> Bắt buộc | H60: =IF('Use Case Tracker'!H77="","",SWITCH('Use Case Tracker'!H77,"Not Started","Chưa bắt đầu","In Progress","Đang làm","Done","Hoàn thành",'Use Case Tracker'!H77)) -> Chưa bắt đầu | I60: =IF('Use Case Tracker'!I77="","",'Use Case Tracker'!I77) | J60: =IF('Use Case Tracker'!J77="","",'Use Case Tracker'!J77) -> BR-SUB-01, BR-SUB-02, BR-SUB-03, BR-SUB-04, BR-SUB-07, BR-SUB-08, BR-SUB-10 | K60: =IFERROR(__xludf.DUMMYFUNCTION("IF('Use Case Tracker'!K77="""","""",IFERROR(GOOGLETRANSLATE('Use Case Tracker'!K77,""en"",""vi""),'Use Case Tracker'!K77))"),"Hiển thị gói hàng năm, ngày hết hạn, số ngày còn lại và quyền truy cập tính năng.") -> Hiển thị gói hàng năm, ngày hết hạn, số ngày còn lại và quyền truy cập tính năng. | L60: =IF('Use Case Tracker'!L77="","",SWITCH('Use Case Tracker'!L77,"Keep","Giữ trong scope","Could-have / Do after core","Có thể có / Làm sau core",'Use Case Tracker'!L77)) -> Giữ trong scope
A61: =IF('Use Case Tracker'!A80="","",'Use Case Tracker'!A80) -> UC79 | B61: =IFERROR(__xludf.DUMMYFUNCTION("IF('Use Case Tracker'!B80="""","""",IFERROR(GOOGLETRANSLATE('Use Case Tracker'!B80,""en"",""vi""),'Use Case Tracker'!B80))"),"Bật/Tắt chia sẻ vị trí") -> Bật/Tắt chia sẻ vị trí | C61: =IFERROR(__xludf.DUMMYFUNCTION("IF('Use Case Tracker'!C80="""","""",IFERROR(GOOGLETRANSLATE('Use Case Tracker'!C80,""en"",""vi""),'Use Case Tracker'!C80))"),"SF4") -> SF4 | D61: =IFERROR(__xludf.DUMMYFUNCTION("IF('Use Case Tracker'!D80="""","""",IFERROR(GOOGLETRANSLATE('Use Case Tracker'!D80,""en"",""vi""),'Use Case Tracker'!D80))"),"Vị trí / An toàn") -> Vị trí / An toàn | E61: =IFERROR(__xludf.DUMMYFUNCTION("IF('Use Case Tracker'!E80="""","""",IFERROR(GOOGLETRANSLATE('Use Case Tracker'!E80,""en"",""vi""),'Use Case Tracker'!E80))"),"Thành viên gia đình") -> Thành viên gia đình | F61: =IFERROR(__xludf.DUMMYFUNCTION("IF('Use Case Tracker'!F80="""","""",IFERROR(GOOGLETRANSLATE('Use Case Tracker'!F80,""en"",""vi""),'Use Case Tracker'!F80))"),"Tính năng Thành viên Gia đình cho phép hoặc vô hiệu hóa việc chia sẻ vị trí thông thường để theo dõi gia đình. Tính năng này kiểm soát việc theo dõi vị trí định kỳ ngoài các sự kiện SOS.") -> Tính năng Thành viên Gia đình cho phép hoặc vô hiệu hóa việc chia sẻ vị trí thông thường để theo dõi gia đình. Tính năng này kiểm soát việc theo dõi vị trí định kỳ ngoài các sự kiện SOS. | G61: =IF('Use Case Tracker'!G80="","",SWITCH('Use Case Tracker'!G80,"Must-have","Bắt buộc","Should-have","Nên có","Could-have","Có thể có",'Use Case Tracker'!G80)) -> Nên có | H61: =IF('Use Case Tracker'!H80="","",SWITCH('Use Case Tracker'!H80,"Not Started","Chưa bắt đầu","In Progress","Đang làm","Done","Hoàn thành",'Use Case Tracker'!H80)) -> Chưa bắt đầu | I61: =IF('Use Case Tracker'!I80="","",'Use Case Tracker'!I80) | J61: =IF('Use Case Tracker'!J80="","",'Use Case Tracker'!J80) -> BR-LOC-01, BR-LOC-03 | K61: =IFERROR(__xludf.DUMMYFUNCTION("IF('Use Case Tracker'!K80="""","""",IFERROR(GOOGLETRANSLATE('Use Case Tracker'!K80,""en"",""vi""),'Use Case Tracker'!K80))"),"Tính năng theo dõi vị trí thông thường nên dựa trên sự đồng ý/cho phép của người dùng. Hành vi theo dõi vị trí khi có yêu cầu hỗ trợ vẫn được kiểm soát bởi cài đặt SOS.") -> Tính năng theo dõi vị trí thông thường nên dựa trên sự đồng ý/cho phép của người dùng. Hành vi theo dõi vị trí khi có yêu cầu hỗ trợ vẫn được kiểm soát bởi cài đặt SOS. | L61: =IF('Use Case Tracker'!L80="","",SWITCH('Use Case Tracker'!L80,"Keep","Giữ trong scope","Could-have / Do after core","Có thể có / Làm sau core",'Use Case Tracker'!L80)) -> Planned / Prototype
A62: =IF('Use Case Tracker'!A81="","",'Use Case Tracker'!A81) -> UC80 | B62: =IFERROR(__xludf.DUMMYFUNCTION("IF('Use Case Tracker'!B81="""","""",IFERROR(GOOGLETRANSLATE('Use Case Tracker'!B81,""en"",""vi""),'Use Case Tracker'!B81))"),"Chia sẻ / Ghi lại vị trí điểm của thành viên") -> Chia sẻ / Ghi lại vị trí điểm của thành viên | C62: =IFERROR(__xludf.DUMMYFUNCTION("IF('Use Case Tracker'!C81="""","""",IFERROR(GOOGLETRANSLATE('Use Case Tracker'!C81,""en"",""vi""),'Use Case Tracker'!C81))"),"SF4") -> SF4 | D62: =IFERROR(__xludf.DUMMYFUNCTION("IF('Use Case Tracker'!D81="""","""",IFERROR(GOOGLETRANSLATE('Use Case Tracker'!D81,""en"",""vi""),'Use Case Tracker'!D81))"),"Vị trí / An toàn") -> Vị trí / An toàn | E62: =IFERROR(__xludf.DUMMYFUNCTION("IF('Use Case Tracker'!E81="""","""",IFERROR(GOOGLETRANSLATE('Use Case Tracker'!E81,""en"",""vi""),'Use Case Tracker'!E81))"),"Thành viên gia đình / Ứng dụng di động / Thiết bị đeo được") -> Thành viên gia đình / Ứng dụng di động / Thiết bị đeo được | F62: =IFERROR(__xludf.DUMMYFUNCTION("IF('Use Case Tracker'!F81="""","""",IFERROR(GOOGLETRANSLATE('Use Case Tracker'!F81,""en"",""vi""),'Use Case Tracker'!F81))"),"Ứng dụng di động hoặc thiết bị đeo tay sẽ gửi vị trí GPS hiện tại của thành viên. Hệ thống lưu trữ vị trí này như một MemberLocationPoint thông thường, tách biệt với việc theo dõi lộ trình SOS.") -> Ứng dụng di động hoặc thiết bị đeo tay sẽ gửi vị trí GPS hiện tại của thành viên. Hệ thống lưu trữ vị trí này như một MemberLocationPoint thông thường, tách biệt với việc theo dõi lộ trình SOS. | G62: =IF('Use Case Tracker'!G81="","",SWITCH('Use Case Tracker'!G81,"Must-have","Bắt buộc","Should-have","Nên có","Could-have","Có thể có",'Use Case Tracker'!G81)) -> Nên có | H62: =IF('Use Case Tracker'!H81="","",SWITCH('Use Case Tracker'!H81,"Not Started","Chưa bắt đầu","In Progress","Đang làm","Done","Hoàn thành",'Use Case Tracker'!H81)) -> Chưa bắt đầu | I62: =IF('Use Case Tracker'!I81="","",'Use Case Tracker'!I81) | J62: =IF('Use Case Tracker'!J81="","",'Use Case Tracker'!J81) -> BR-LOC-01, BR-LOC-02, BR-LOC-04 | K62: =IFERROR(__xludf.DUMMYFUNCTION("IF('Use Case Tracker'!K81="""","""",IFERROR(GOOGLETRANSLATE('Use Case Tracker'!K81,""en"",""vi""),'Use Case Tracker'!K81))"),"Thực thể ERD vật lý liên quan: member_location_points. Đây là theo dõi thông thường, không phải sos_location_points.") -> Thực thể ERD vật lý liên quan: member_location_points. Đây là theo dõi thông thường, không phải sos_location_points. | L62: =IF('Use Case Tracker'!L81="","",SWITCH('Use Case Tracker'!L81,"Keep","Giữ trong scope","Could-have / Do after core","Có thể có / Làm sau core",'Use Case Tracker'!L81)) -> Planned / ERD Present
